Workbook
Name _jglhyjAA4565: #REF!
Name _jglhyjAA4565: #REF!
Name AuditorsReport: #REF!
Name AuditorsReport: #REF!
Name AuditorsReport: #REF!
Name AuditorsReport: #REF!
Name AuditorsReport: #REF!
Name ColumnTitle1: #REF!
Name ColumnTitle1: #REF!
Name ColumnTitleRegion1..C13.1: #REF!
Name ColumnTitleRegion1..C13.1: #REF!
Name ColumnTitleRegion2..C15.1: #REF!
Name ColumnTitleRegion2..C15.1: #REF!
Name Exhibit_A: #REF!
Name Exhibit_A: #REF!
Name Exhibit_A: #REF!
Name Exhibit_A: #REF!
Name Exhibit_A: #REF!
Name Exhibit_B: #REF!
Name Exhibit_B: #REF!
Name Exhibit_B: #REF!
Name Exhibit_B: #REF!
Name Exhibit_B: #REF!
Name Exhibit_c: #REF!
Name Exhibit_c: #REF!
Name Exhibit_c: #REF!
Name Exhibit_c: #REF!
Name Exhibit_c: #REF!
Name fdf: #REF!
Name fdf: #REF!
Name fdf: #REF!
Name fdf: #REF!
Name fdf: #REF!
Name g: #REF!
Name g: #REF!
Name k: #REF!
Name k: #REF!
Name k: #REF!
Name k: #REF!
Name k: #REF!
Name Land: #REF!
Name Land: #REF!
Name Notes: #REF!
Name Notes: #REF!
Name Notes: #REF!
Name Notes: #REF!
Name Notes: #REF!
Name Part_1: #REF!
Name Part_1: #REF!
Name Part_1: #REF!
Name Part_1: #REF!
Name Part_1: #REF!
Name RowTitleRegion1..D6: #REF!
Name RowTitleRegion1..D6: #REF!
Name valHighlight: IFERROR(IF(#REF!="نعم", TRUE, FALSE),FALSE)
Name valHighlight: IFERROR(IF(#REF!="نعم", TRUE, FALSE),FALSE)
Name XDO_?BIRTH_DATE_EXP?: #REF!
Name XDO_?BIRTH_DATE_EXP?: #REF!
Name XDO_?BIRTH_DATE_EXP?: #REF!
Name XDO_?BIRTH_DATE_EXP?: #REF!

Sheet SOFP
B1: "COMPANY NAME AS PER AOA"
B2: "TYPE OF COMPANY AS PER AOA"
B3: Statement of Financial Position for the year ends at "END DATE AS PER TRIAL BALANCE
B4: (All amounts in Saudi Riyals unless otherwies stated) | G4: "A"
B6: Assets | C6: Note | E6: CURRENT YEAR | G6: PREVIOUS YEAR
B7: Current Assets | E7: SR | G7: SR
B8: Cash and Cash Equivalents | C8: 5 | E8: ='1..'!E10 -> 0 | G8: ='1..'!G10 -> 0
B9: Receivables & Other Debit balances | C9: 6 | E9: =+'1..'!E24 -> 0 | G9: ='1..'!G24 -> 0
B10: DUE FROM RELATED PARTY | E10: ='(2)..'!H24 -> 0 | G10: ='(2)..'!N30 -> 0
B11: TOTAL CURRENT ASSETS | E11: =SUM(E8:E10) -> 0 | G11: =SUM(G8:G10) -> 0
B12: Non - Current Assets
B13: Property and equipment - net | C13: 7 | E13: ='1..'!K39 -> 0 | G13: ='1..'!K40 -> 0
B14: TOTAL Non - Current CURRENT ASSETS | E14: =SUM(E13:E13) -> 0 | G14: =SUM(G13:G13) -> 0
B15: TOTAL ASSETS | E15: =E11+E14 -> 0 | G15: =G11+G14 -> 0
B17: LIABILITIES AND EQUITY
B18: Current Liabilities
B19: Creditors & Other Credit balances | C19: 8 | E19: ='(2)..'!F13 -> 0 | G19: ='(2)..'!H13 -> 0
B20: DUE TO RELATED PARTY | C20: 9 | E20: ='(2)..'!H30+'(2)..'!H29 -> 0 | G20: ='(2)..'!N24+'(2)..'!N29 -> 0
B21: Tax provision | C21: 10 | E21: ='2...'!F13 -> 0 | G21: ='2...'!H13 -> 0
B22: TOTAL CURRENT LIABILITIES | E22: =SUM(E19:E21) -> 0 | G22: =SUM(G19:G21) -> 0
B23: NON-CURRENT LIABILITY
B24: Employee Benefit Liability | C24: 11 | E24: ='2...'!F26 -> 0 | G24: ='2...'!H26 -> 0
B25: TOTAL LIABILITIES | E25: =SUM(E22:E24) -> 0 | G25: =SUM(G22:G24) -> 0
B26: EQUITY
B27: Share Capital | C27: 12 | E27: =+'5'!F13 -> 0 | G27: =+'5'!F13 -> 0
B28: Reserve | E28: =+SCE!G17 -> 0 | G28: =SCE!G12 -> 0
B29: Retained Earnings | E29: =SCE!H17 -> 0 | G29: =SCE!H12 -> 0
B30: TOTAL EQUITY | E30: =SUM(E27:E29) -> 0 | G30: =SUM(G27:G29) -> 0
B31: TOTAL EQUITY AND LIABILITIES | E31: =E25+E30 -> 0 | G31: =G25+G30 -> 0
B48: The Attached notes from (1) to (16) Form a part of these financial statements
B49: 4
G53: =G31-G11 -> 0

Sheet SCI
B1: =SOFP!B1 -> "COMPANY NAME AS PER AOA"
B2: =SOFP!B2 -> "TYPE OF COMPANY AS PER AOA"
B3: Statement of Comprehensive Income for the year ends at "END DATE AS PER TRIAL BALANCE"
B4: (All amounts in Saudi Riyals unless otherwies stated) | G4: "B"
C6: Note | E6: =SOFP!E6 -> CURRENT YEAR | G6: =SOFP!G6 -> PREVIOUS YEAR
E7: SR | G7: SR
B8: Revenue | E8: =-SUM('Client TB (2)'!I78,'Client TB (2)'!I77) -> 0
B9: Cost of Revenue | C9: 14 | E9: ='6'!D10 -> 0 | G9: ='6'!F9 -> 0
B10: Gross profit | E10: =SUM(E8:E9) -> 0 | G10: =SUM(G8:G9) -> 0 | I10: =+E10/E8 -> #DIV/0! | K10: =+G10/G8 -> #DIV/0!
B11: General & Administrative expenses | C11: 15 | E11: =-'6'!D35 -> 0 | G11: =-('6'!F35) -> 0
B12: Selling and marketing expense
B13: Other income | E13: =-SUM('Client TB (2)'!I91:I93) -> 0
B14: Other Loss | E14: 0
B15: PROFIT FOR THE PERIOD BEFORE Zakat | E15: =SUM(E10:E13) -> 0 | G15: =SUM(G10:G14) -> 0 | I15: =+E15/E8 -> #DIV/0! | K15: =+G15/G8 -> #DIV/0!
B16: Tax expense | E16: =-('2...'!F13) -> 0 | G16: =-('2...'!H13) -> 0
B17: Zakat Provision | C17: 10 | E17: 0 | G17: 0
B18: PROFIT FOR THE PERIOD AFTER Zakat | E18: =SUM(E15:E17) -> 0 | G18: =SUM(G15:G17) -> 0
B45: =SOFP!B48:G48 -> The Attached notes from (1) to (16) Form a part of these financial statements
B46: =SOFP!B49:G49+1 -> 5

Sheet SCE
B1: =SOFP!B1 -> "COMPANY NAME AS PER AOA"
B2: =SOFP!B2 -> "TYPE OF COMPANY AS PER AOA"
B3: Statement of Changes in Equity for the year ends at " END DATE AS PER TRIAL BALANCE"
B4: (All amounts in Saudi Riyals unless otherwies stated) | J4: "C"
E7: Capital | G7: Reserve | H7: Retained Earnings | J7: TOTAL EQUITY
B8: Statement of Changes in Equity for the period from" FIRST DATE OF CURRENT YEAR" to " END DATE OF CURRENT YEAR" | E8: SR | G8: SR | H8: SR | J8: SR
B9: Balance at the beginning of " FIRST DATE OF PREVIOUS YEAR" | J9: =SUM(D9:H9) -> 0
B10: Net profit for the year | E10: 0 | G10: 0 | H10: =SCI!G18 -> 0 | J10: =SUM(D10:H10) -> 0
B11: Trasnfer to reserve | E11: 0 | G11: 0 | H11: 0 | J11: 0
B12: Balance at the End of "" END DATE OF PRVIOUS YEAR" | E12: =SUM(E9:E11) -> 0 | G12: =SUM(G9:G10) -> 0 | H12: =SUM(H9:H11) -> 0 | J12: =E12+G12+H12 -> 0
B14: Balance at the beginning of "FIRST DATE OF CURRENT YEAR" | E14: =E12 -> 0 | G14: =G12 -> 0 | H14: =H12 -> 0 | J14: =SUM(D14:H14) -> 0
B15: Prior Period adjustment | H15: ='Client TB (2)'!H75 -> 0 | J15: =H15 -> 0
B16: Net profit for the year | E16: 0 | G16: 0 | H16: =+SCI!E18-G16 -> 0 | J16: =SUM(D16:H16) -> 0
B17: Balance at the End of " END DATE OF CURRENT YEAR" | E17: =SUM(E14:E16) -> 0 | G17: =SUM(G14:G16) -> 0 | H17: =SUM(H14:H16) -> 0 | J17: =SUM(J14:J16) -> 0
B29: =SCI!B45:G45 -> The Attached notes from (1) to (16) Form a part of these financial statements
B30: =SCI!B46:G46+1 -> 6

Sheet SCF
B1: =SCI!B1:G1 -> "COMPANY NAME AS PER AOA"
B2: =SCI!B2:G2 -> "TYPE OF COMPANY AS PER AOA"
B3: Statement of Cash Flow for the year ends at 31 MONTH XXX
B4: (All amounts in Saudi Riyals unless otherwies stated) | F4: "D"
D6: =SCI!E6 -> CURRENT YEAR | F6: =SCI!G6 -> PREVIOUS YEAR
B7: Cash flows from operational activities | D7: SR | F7: SR
B8: Net income before tax | D8: =SCI!E15 -> 0 | F8: =SCI!G15 -> 0
B9: Adjustments to reconcile profit before zakat and
B10: Tax to net cash flows
B11: Depreciation | D11: ='1..'!K35 -> 0
B12: Employees' defined benefit | D12: ='6'!D19 -> 0
B13: WHT provision | D13: ='Client TB (2)'!I145 -> 0
B14: Adjustments in operational assets and liabilities
B15: Receivables & Other Debit Balance
B16: Creditors & Other Credit Balances
B17: =SOFP!B20 -> DUE TO RELATED PARTY
B18: DUE FROM RELATED PARTY
B19: Net cash generated from operational activities | D19: =SUM(D8:D18) -> 0 | F19: =SUM(F8:F18) -> 0
B20: Tax Expenses | D20: 0
B21: Net cash generated from operational activities | D21: =D19+D20 -> 0 | F21: =F19+F20 -> 0
B22: Cash flow from investment activities
B23: Property and Equipment Purchase | D23: =-('1..'!K29) -> 0
B24: Net cash (used in) investment activities | D24: =SUM(D23) -> 0 | F24: =SUM(F23) -> 0
B25: Cash flows from financing activities
B26: Capital | D26: 0 | F26: 0
B27: Net cash (used in) financing activities | D27: =SUM(D26:D26) -> 0 | F27: =SUM(F26:F26) -> 0
B28: Net cash (used in) cash and cash equivalents | D28: =D21+D24+D27 -> 0 | F28: =F21+F24+F27 -> 0
B29: Cash and cash equivalents at period beginning | D29: =F30 -> 0
B30: Cash and cash equivalents at period-end | D30: =SUM(D28:D29) -> 0 | F30: =SUM(F28:F29) -> 0
D32: =SOFP!E8 -> 0 | F32: =SOFP!G8 -> 0
C33: =C32-C30 -> 0 | D33: =D32-D30 -> 0 | F33: =F32-F30 -> 0
B54: =SCE!B29:J29 -> The Attached notes from (1) to (16) Form a part of these financial statements
B55: =SCE!B30:J30+1 -> 7

Sheet S 1
B1: =SCF!B1:F1 -> "COMPANY NAME AS PER AOA"
B2: =SCI!B2:G2 -> "TYPE OF COMPANY AS PER AOA"
B3: NOTES TO THE FINANACIAL STATEMENT FOR THE YEAR ENDED " END DATE OF CURRENT YEAR"
B4: (All amounts in Saudi Riyals unless otherwies stated)
B6: 1 - Organization & activities
B7: "COMPANY NAME AS PER CR "- Limited Liability Company - Registered under "Commercial Register No AS PER CR " in" HEADQUARTERS AS PER CR ", on "INCORPORATION DATE IN ARABIC AS PER AOA" , corresponding to "INCORPORATION DATE INTO GREGORIAN DATE". The Company mainly operates in 'COMPANY ACTIVITY AS PER AOA"
B8: 1/1 - On Going Concern (IF any)
B9: The " REATINED EARNINGS/ACCUMULATED LOSS AS PER SOFP SHEET" as of unconsolidated financial statement date, amounting to " AMOUNT AS PER SOFP" Saudi Riyals, have exceeded the company's capital as at "END DATE OF CURRENT YEAR". Additionally, there was a "Surplus/Deficit wording as per positive or negative in working capital amount as per sheet 8" of " current year woking capital amount " Saudi Riyals as at "END YEAR AS PER TRIAL BALANCE". These circumstances indicate there is no significant doubt about the company's ability to continue its operations as a going concern. This situation does not requires calling a partner meeting to consider supporting the company and its continuation or liquidating it before the specified date in its founding contract. The necessary legal procedures should be initiated in accordance with Article 182 of the Saudi Companies Law and the company's founding contract. | L9: =SOFP!E29 -> 0 | M9: ='8'!C23 -> 0
B10: The Company’s headquarters
B11: "headquarters of company as per AOA"
B12: The Company doesn’t have any other branches.
B13: The Company's financial year begins on the date of its registration in the commercial register, which is "INCORPORATION DATE IN ARABIC AS PER CR" , corresponding to "INCORPORATION DATE INTO GREGORIAN DATE". and ends on " current year". Each subsequent financial year will be twelve months, starting on January 1 of each Gregorian year and ending at the end of December of the same year.
B14: 2- Basis of Preparation
B15: a. Statement of Compliance
B16: These financial statements have been prepared in accordance with International Financial Reporting Standard for Small and Medium-Sized Entities (“IFRS for SMEs”) issued by the International Accounting Standards Board (“IASB”), that is endorsed in the Kingdom of Saudi Arabia and other standards and pronouncements that are endorsed by Saudi Organization for Certified Public Accountants (“SOCPA”) (collectively referred to as “IFRS for SMEs as endorsed in KSA”).
B17: b. Basis of Measurement
B18: The Financial Statements have been prepared on the basis of historical cost and using the accrual principle of accounting and the Going Concern.
B19: c.Presentation and functional currency
B20: The presentation and functional currency of the Company is Saudi Riyal.
B23: =SCF!B55:F55+1 -> 8

Sheet S 2
B1: ='S 1'!B1 -> "COMPANY NAME AS PER AOA"
B2: ='S 1'!B2 -> "TYPE OF COMPANY AS PER AOA"
B3: ='S 1'!B3 -> NOTES TO THE FINANACIAL STATEMENT FOR THE YEAR ENDED " END DATE OF CURRENT YEAR"
B4: ='S 1'!B4 -> (All amounts in Saudi Riyals unless otherwies stated)
B6: 3. Summary of Significant Accounting Policies
B7: The accounting policies followed in preparing the Company’s Financial Statements in accordance with the IFRS for SMEs are as follows:
B8: a. Financial Instruments:
B9: A financial instrument is any contract that creates a financial asset for one enterprise and a financial liability or equity instrument for another enterprise. All financial instruments used by the Company are basic financial instruments to which Section 11 of the Financial Reporting Standard for Small and Medium-Sized Entities (IFRS for SMEs) applies. The Company's financial assets and liabilities consist primarily of cash and cash equivalents, accounts receivable and other receivables balances, transactions with related parties, and accounts payable and other payable balances. The Company does not use any derivative financial instruments.
B10: Initial Measurement:
B11: Financial instruments are initially measured at transaction price (which includes transaction costs) except for financial assets and liabilities measured at fair value through other comprehensive income. Nevertheless, if the arrangement represents a financing transaction, it is measured at the present value of future payments discounted at a market-related interest rate.
B12: Subsequent Measurement:
B13: After initial measurement, at the end of each reporting period the Company measures financial instruments as follows, without any deduction for the transaction costs that the entity would incur on sale or other disposal:
B14: Financial assets and liabilities that represent debt instruments are measured at amortized cost using the effective interest rate.
B15: Investments in financial assets that are listed on financial markets (if any), or those that can be measured at fair value, are measured at fair value without undue effort or cost, with changes in fair value being recognized in profit or loss. Other investments that cannot be measured at fair value without undue effort or cost are measured at cost less impairment.
B16: Impairment of the Value of Financial Assets
B17: On each Statement of Financial Position date, an evaluation is performed to ensure that there is evidence of an impairment in the value of a specific financial asset. If such evidence exists, the impairment loss is recognized in the Statement of Comprehensive Income. Impairment is determined as follows:
... B21: Financial assets and financial liabilities are offset and listed net in the Financial Statements when there is a binding contractual right to offset the recognized amounts and when there is an intention to settle the assets with the liabilities on a net basis, or realize the assets and pay the liabilities simultaneously.
B25: ='S 1'!B23+1 -> 9

Sheet S 3
B1: ='S 2'!B1 -> "COMPANY NAME AS PER AOA"
B2: ='S 2'!B2 -> "TYPE OF COMPANY AS PER AOA"
B3: ='S 2'!B3 -> NOTES TO THE FINANACIAL STATEMENT FOR THE YEAR ENDED " END DATE OF CURRENT YEAR"
B4: ='S 2'!B4 -> (All amounts in Saudi Riyals unless otherwies stated)
B6: 3. Summary of Significant Accounting Policies "continued"
B7: b. Cash and cash equivalents
B8: Cash and cash equivalents comprise of cash held at banks and on hand
B9: c. Accounts Receivable
B10: The trade receivables appear by the original invoice amount after deducting the provisions for the decrease in the trade receivables. The provision for the decline is formed when there is objective evidence that the company is unable to collect the amounts due and in accordance with the original terms of the receivables. Bad debts are written off when identified against the related provisions. The provisions are charged to income statement. At the end of each financial period, carrying amounts of trade and other receivables are reviewed by management to determine whether there is any objective evidence that the amounts are not recoverable If so, an impairment loss is recognized immediately in profit or loss in the statement of comprehensive income.
B11: d. Related Parties
B12: The Company will: Identify the related parties in accordance with the definition contained in Section ٣٣ of the International Standard for SMEs. Related party transactions include the transfer of resources, services or liabilities between the Company and the related parties, regardless of whether a price is charged. The basis and terms of these transactions are approved by the management.
B13: e. Property and Equipment
B14: Property and equipment are stated in the statement of financial position at cost after deducting accumulated depreciation and impairment (if any) up to the date of the Financial Statements. Depreciation is calculated on these assets according to the straight-line method in order to distribute the cost of these assets over their estimated useful lives using the following annual depreciation rates:
B15: Property and equipment sold or disposed of and their accumulated depreciation are deleted from the accounts on the date of their sale or disposal, and the resulting gains or losses are recognized in profits and losses. Items of property and equipment is added to the carrying amount of replacing part of these items when the cost is incurred if this replacement part is expected to provide additional benefits in the future, and the carrying amount of those replaced parts is derecognized. All other maintenance and repair expenses are charged to the Statement of Comprehensive Income in the year in which they are incurred. The residual value, useful lives and methods of depreciation of property and equipment are audited and adjusted prospectively, if appropriate, when there is an indication that there have been material changes since the last financial report. The carrying value of these assets is reduced to their recoverable amount immediately in the event that the carrying value exceeds the estimated recoverable amount
B23: ='S 2'!B25+1 -> 10

Sheet S 4
B1: ='S 3'!B1 -> "COMPANY NAME AS PER AOA"
B2: ='S 3'!B2 -> "TYPE OF COMPANY AS PER AOA"
B3: ='S 3'!B3 -> NOTES TO THE FINANACIAL STATEMENT FOR THE YEAR ENDED " END DATE OF CURRENT YEAR"
B4: ='S 3'!B4 -> (All amounts in Saudi Riyals unless otherwies stated)
B6: 3. Summary of Significant Accounting Policies "continued"
B7: f. Statutory reserve
B8: In compliance with the Companies Law in the Kingdom of Saudi Arabia and the Company’s Memorandum of Association, the Company shall set aside a statutory reserve of at least 10% of the net income annually, and the partners may stop the set aside whenever the reserve balance reaches 30% of the capital.
B9: g. Impairment of Non-Current Assets
B10: Impairment exists when the carrying value of an asset or cash generating unit exceeds its recoverable amount, which is the higher of its fair value less costs of disposal and its value in use. The fair value less costs of disposal calculation is based on available data from binding sales transactions, conducted at arm’s length, for similar assets or observable market prices less incremental costs for disposing off the asset.
B11: h. Trade payables, accruals and other payables
B12: Liabilities are recognized for amounts to be paid in the future for goods or services received, whether or not invoiced by suppliers. Trade payables are commitments to pay for goods or services that are obtained in the normal course of business from suppliers. Trade payables are classified as current liabilities if these are due within one year or less, otherwise they are presented as non-current liabilities.
B13: i . Post-Employment Benefits
B14: The Company's post-employment benefits include monthly subscriptions to the General Organization for Social Insurance and the end-of-service benefits program in accordance with the requirements of regulations in the Kingdom of Saudi Arabia.
B15: a) General Organization for Social Insurance
B16: The monthly subscriptions to the General Organization for Social Insurance (an Independent Authority) are classified as a specific subscriptions program. The Company recognizes its share of the fixed contributions to the General Organization for Social Insurance every month as expenses. The Company does not have any legal or regulatory obligation to pay any other contributions, and its only obligation is to pay contributions as they become due.
B17: b) End of Service Benefits
... B20: The provision for tax is measured and recognized in the Statement of Comprehensive Income for each period separately in accordance with the provisions and rules of tax in the Kingdom of Saudi Arabia. The tax provision is reconciled in the financial period being audited by adopting the final tax assessment issued by the Zakat, Tax, and Customs Authority. Variances in the tax provision are treated as adjustments to accounting estimates and are reflected in the financial period in which the final tax assessment is issued.
B21: ='S 3'!B23+1 -> 11

Sheet S 5
B1: ='S 3'!B1 -> "COMPANY NAME AS PER AOA"
B2: ='S 3'!B2 -> "TYPE OF COMPANY AS PER AOA"
B3: ='S 3'!B3 -> NOTES TO THE FINANACIAL STATEMENT FOR THE YEAR ENDED " END DATE OF CURRENT YEAR"
B4: ='S 3'!B4 -> (All amounts in Saudi Riyals unless otherwies stated)
B6: 3. Summary of Significant Accounting Policies "continued"
B7: k. Activity Revenues
B8: Revenue is recognized when the following recognition requirements are met:
B9: - The probability of achieving economic benefits for the Company.
B10: - It can be measured reliably regardless of payment readiness.
B11: - Costs incurred to date and future costs can be reliably recognized and measured.
B12: - The activities revenue comprises the value of invoices and progress billings issued for construction and building services rendered to the Company's clients. The revenue is recognized upon completion of the works and issuance of the invoice or statement to the client.
B13: l. General and Administrative Expenses
B14: Administrative and general expenses are recognized as annual expenses according to the accrual basis and these expenses are charged in the accounting year in which they are incurred. General and administrative expenses that benefit more than one accounting year are distributed on a time basis and using their historical cost.
B15: m. Translation of Foreign Currencies
B16: Transactions in foreign currency are translated into the functional currency using the exchange rate prevailing at the date of the transactions. Cash items in foreign currencies are translated at the exchange rate prevailing on the reporting date. The gains or losses resulting from the settlement of transactions and the retranslation of cash items at the end of the period are recognized in the profit or loss for the period in which they arise
B17: 4. Significant accounting estimates, assumptions and judgments
... B21: The key assumptions concerning the future and other key sources of estimation uncertainty at the reporting date, that have a significant risk of causing a material differences in the carrying amounts of assets and liabilities within the next financial period, are presented below. The Company used these assumptions and estimates on the basis available when the financial statements were prepared. However, existing circumstances and assumptions about future developments may change due to market changes or circumstances arising that are beyond the control of the Company. Such changes are reflected in the assumptions when they occur
B25: ='S 4'!B21+1 -> 12

Sheet 1..
B1: ='S 5'!B1 -> "COMPANY NAME AS PER AOA"
B2: ='S 5'!B2 -> "TYPE OF COMPANY AS PER AOA"
B3: ='S 5'!B3 -> NOTES TO THE FINANACIAL STATEMENT FOR THE YEAR ENDED " END DATE OF CURRENT YEAR"
B4: ='S 5'!B4 -> (All amounts in Saudi Riyals unless otherwies stated)
B6: 5- Cash and Cash Equivalents | E6: =SOFP!E6 -> CURRENT YEAR | G6: =SOFP!G6 -> PREVIOUS YEAR
E7: SR | G7: SR
B8: Cash in banks | E8: =SUM('Client TB (2)'!I68:I69) -> 0 | G8: =SUM('Client TB (2)'!D68:D69) -> 0
B9: Cash in Hand | E9: ='Client TB (2)'!I66 -> 0 | G9: ='Client TB (2)'!D66 -> 0
B10: Total | E10: =SUM(E8:E9) -> 0 | G10: =SUM(G8:G9) -> 0
B13: 6- Receivables & Other Debit balances | E13: =E6 -> CURRENT YEAR | G13: =G6 -> PREVIOUS YEAR
E14: SR | G14: SR
B15: Receivables | E15: ='Client TB (2)'!I63 -> 0 | G15: ='Client TB (2)'!D63 -> 0
B16: Inventory
B17: Prepaid Rent | E17: =SUM('Client TB (2)'!I70:I71) -> 0 | G17: =SUM('Client TB (2)'!D70:D71) -> 0
B18: Advance to suppliers
B19: salary advance
B20: Prepaid utility expense | E20: ='Client TB (2)'!I72 -> 0 | G20: ='Client TB (2)'!D72 -> 0
B21: Prepaid misa expense | E21: ='Client TB (2)'!I73 -> 0 | G21: ='Client TB (2)'!D73 -> 0
B22: Prepaid visa expense | E22: ='Client TB (2)'!I74 -> 0 | G22: ='Client TB (2)'!D74 -> 0
B23: Security Deposit | E23: ='Client TB (2)'!I75 -> 0 | G23: ='Client TB (2)'!D75 -> 0
B24: Total | E24: =SUM(E15:E23) -> 0 | G24: =SUM(G15:G23) -> 0
B26: 7- Property and equipment | E26: Furniture & fixtures | G26: Plant & machinery | H26: Leasehold Improvements | I26: Office equipments | J26: Motor vehicles | K26: TOTAL
E27: SR | G27: SR | K27: SR
B28: Balance in "first date of current year" | E28: =SUM('Client TB (2)'!D36:D38) -> 0 | G28: =SUM('Client TB (2)'!D53:D56) -> 0 | H28: =SUM('Client TB (2)'!D41) -> 0 | I28: =SUM('Client TB (2)'!D47:D50) -> 0 | J28: ='Client TB (2)'!D44 -> 0 | K28: =SUM(E28:J28) -> 0
B29: Additions | E29: 0 | G29: ='Client TB (2)'!E56 -> 0 | H29: 0 | I29: ='Client TB (2)'!E64 -> 0 | J29: 0 | K29: =SUM(E29:J29) -> 0
B30: Balance in "end date of current year" | E30: =SUM(E28:E29) -> 0 | F30: 0 | G30: =SUM(G28:G29) -> 0 | H30: =SUM(H28:H29) -> 0 | I30: =SUM(I28:I29) -> 0 | J30: =SUM(J28:J29) -> 0 | K30: =SUM(K28:K29) -> 0
B32: accumulated depreciation
B34: Balance in "first date of current year" | E34: =-'Client TB (2)'!D35 -> 0 | G34: =-'Client TB (2)'!D52 -> 0 | H34: =-'Client TB (2)'!D40 -> 0 | I34: =-'Client TB (2)'!D46 -> 0 | J34: =-'Client TB (2)'!D43 -> 0 | K34: =SUM(E34:J34) -> 0
B35: Additions | E35: ='Client TB (2)'!F35 -> 0 | G35: ='Client TB (2)'!F52 -> 0 | H35: ='Client TB (2)'!F40+'Client TB (2)'!H40 -> 0 | I35: ='Client TB (2)'!F46 -> 0 | J35: ='Client TB (2)'!F43 -> 0 | K35: =SUM(E35:J35) -> 0
B36: Balance in "end date of current year" | E36: =SUM(E34:E35) -> 0 | F36: 0 | G36: =SUM(G34:G35) -> 0 | H36: =SUM(H34:H35) -> 0 | I36: =SUM(I34:I35) -> 0 | J36: =SUM(J34:J35) -> 0 | K36: =SUM(K34:K35) -> 0
B38: Net book value
B39: Balance in "end date of current year" | E39: =E30-E36 -> 0 | G39: =G30-G36 -> 0 | H39: =H30-H36 -> 0 | I39: =I30-I36 -> 0 | J39: =J30-J36 -> 0 | K39: =K30-K36 -> 0
B40: Balance in " end date of previous year" | E40: =E28-E34 -> 0 | G40: =G28-G34 -> 0 | H40: =H28-H34 -> 0 | I40: =I28-I34 -> 0 | J40: =J28-J34 -> 0 | K40: =K28-K34 -> 0
B45: 13

Sheet (2)..
B1: ='S 5'!B1 -> "COMPANY NAME AS PER AOA"
B2: ='S 5'!B2 -> "TYPE OF COMPANY AS PER AOA"
B3: ='S 5'!B3 -> NOTES TO THE FINANACIAL STATEMENT FOR THE YEAR ENDED " END DATE OF CURRENT YEAR"
B4: ='S 5'!B4 -> (All amounts in Saudi Riyals unless otherwies stated)
B6: 8- Other Credit balances | F6: =SOFP!E6 -> CURRENT YEAR | H6: =SOFP!G6 -> PREVIOUS YEAR
F7: SR | H7: SR
B8: Creditors | F8: =-'Client TB (2)'!I17 -> 0 | H8: =-'Client TB (2)'!D17 -> 0
B9: VAT | F9: =-'Client TB (2)'!I30 -> 0 | H9: =-'Client TB (2)'!D30 -> 0
B10: Provisions | F10: =-SUM('Client TB (2)'!I12,'Client TB (2)'!I16) -> 0 | H10: =-SUM('Client TB (2)'!D12,'Client TB (2)'!D16) -> 0
B11: Accrued Expence | F11: =-SUM('Client TB (2)'!I22:I23,'Client TB (2)'!I27:I29,'Client TB (2)'!I31,'Client TB (2)'!I13) -> 0 | H11: =-SUM('Client TB (2)'!D22:D23,'Client TB (2)'!D29,'Client TB (2)'!D31:D32,'Client TB (2)'!D13) -> 0
B12: Advance from customer | F12: =-'Client TB (2)'!I33 -> 0
B13: Total | F13: =SUM(F8:F12) -> 0 | H13: =SUM(H8:H11) -> 0
B15: 9- DUE FROM RELATED PARTY
B16: Related parties include the company's shareholders, senior management, and entities owned or managed by these entities, as well as entities over which they have joint control or significant influence. The following is a summary of the most significant transactions between the company and related parties during the period ending December 31, 2025:
B20: Name of Partner | D20: Nature of the relationship | F20: Nature of transactions | H20: Balance at the end of the year | J20: Net transactions during the period Debit | L20: Net transactions during the period Credit | N20: Balance at the Beginning of the year
H21: SAR | J21: SAR | L21: SAR | N21: SAR
D22: "as per aoa" | H22: =-SUM(I22:N22) -> 0 | J22: =-'Client TB (2)'!E18 -> 0 | L22: ='Client TB (2)'!F18 -> 0 | N22: =-'Client TB (2)'!D18 -> 0
D23: as per aoa
H24: =SUM(H22:H23) -> 0 | J24: =SUM(J22:J23) -> 0 | L24: =SUM(L22:L23) -> 0 | N24: =SUM(N22:N23) -> 0
B27: DUE TO RELATED PARTY
D28: as per aoa | H28: =-(N28+J28-L28) -> 0 | J28: ='Client TB (2)'!E19 -> 0 | L28: ='Client TB (2)'!F19 -> 0 | N28: ='Client TB (2)'!D19 -> 0
D29: as per aoa | H29: =N29+L29-J29 -> 0 | J29: ='Client TB (2)'!E24+'Client TB (2)'!E26 -> 0 | L29: ='Client TB (2)'!F26 -> 0 | N29: =-SUM('Client TB (2)'!D24:D26) -> 0
H30: =SUM(H27:H28) -> 0 | J30: =SUM(J27:J28) -> 0 | L30: =SUM(L27:L28) -> 0 | N30: =SUM(N27:N28) -> 0
B36: 14

Sheet 2...
B1: ='(2)..'!B1:T1 -> "COMPANY NAME AS PER AOA"
B2: ='(2)..'!B2 -> "TYPE OF COMPANY AS PER AOA"
B3: ='(2)..'!B3 -> NOTES TO THE FINANACIAL STATEMENT FOR THE YEAR ENDED " END DATE OF CURRENT YEAR"
B4: ='[7]4'!B4:E4 -> (All amounts in Saudi Riyals unless otherwies stated)
B6: 10- Income tax provision | F6: ='(2)..'!F6 -> CURRENT YEAR | H6: ='(2)..'!H6 -> PREVIOUS YEAR
B7: a. The movement of Tax provision during the period is as follows: | F7: SR | H7: SR
B8: Balance of the zakat provision at the beginning of the period | F8: =H13 -> 0
B9: Paid during the Period
B10: Prior period adjustment | F10: 0
B11: Net zakat provision after settlements | F11: =SUM(F8:F10) -> 0 | H11: =SUM(H8:H10) -> 0
B12: Zakat provision for the current period
B13: Zakat provision as in the end of the period | F13: =SUM(F11:F12) -> 0 | H13: =SUM(H11:H12) -> 0
F15: =+F6 -> CURRENT YEAR | H15: =+H6 -> PREVIOUS YEAR
B16: b. Taxable base | F16: SR | H16: SR
B17: Adjusted net profit for the period | F17: =SCI!E15 -> 0 | H17: =SCI!G15 -> 0
B18: Tax rate | F18: 0.2 | H18: 0.2
B19: Income tax | F19: =F17*F18 -> 0 | H19: =H17*H18 -> 0
B20: 11- Employee Benefit Liability
F21: =+F15 -> CURRENT YEAR | H21: =+H15 -> PREVIOUS YEAR
F22: SR | H22: SR
B23: Balance at the beginning of the period | F23: =H26 -> 0
B24: Incurred expenses during the period | F24: ='Client TB (2)'!I109 -> 0
B25: Paid during the Period | F25: 0 | H25: 0
B26: Balance at the End of the period | F26: =SUM(F23:F25) -> 0 | H26: =SUM(H23:H25) -> 0
B51: 15

Sheet 5
B1: ='2...'!B1:E1 -> "COMPANY NAME AS PER AOA"
B2: ='2...'!B2:E2 -> "TYPE OF COMPANY AS PER AOA"
B3: ='2...'!B3:E3 -> NOTES TO THE FINANACIAL STATEMENT FOR THE YEAR ENDED " END DATE OF CURRENT YEAR"
B4: ='2...'!B4:E4 -> (All amounts in Saudi Riyals unless otherwies stated)
B6: 12. Capital
B7: "Definition of capital split as per AOA"
B9: Partner Name | C9: Value of each share | D9: Number of shares | F9: Capital
F10: SR
F12: =C12*D12 -> 0
B13: Total | C13: =SUM(C11:C12) -> 0 | D13: =SUM(D10:D12) -> 0 | F13: =SUM(F11:F12) -> 0
B16: 13- Company Going Concern
B17: The " REATINED EARNINGS/ACCUMULATED LOSS AS PER SOFP SHEET" as of unconsolidated financial statement date, amounting to " AMOUNT AS PER SOFP" Saudi Riyals, have exceeded the company's capital as at "END DATE OF CURRENT YEAR". Additionally, there was a "Surplus/Deficit wording as per positive or negative in working capital amount as per sheet 8" of " current year woking capital amount " Saudi Riyals as at "END YEAR AS PER TRIAL BALANCE". These circumstances indicate there is no significant doubt about the company's ability to continue its operations as a going concern. This situation does not requires calling a partner meeting to consider supporting the company and its continuation or liquidating it before the specified date in its founding contract. The necessary legal procedures should be initiated in accordance with Article 182 of the Saudi Companies Law and the company's founding contract.
I18: -305781.9
I19: 105344
B36: 16

Sheet 6
B1: ='2...'!B1:E1 -> "COMPANY NAME AS PER AOA"
B2: ='2...'!B2:E2 -> "TYPE OF COMPANY AS PER AOA"
B3: ='2...'!B3:E3 -> NOTES TO THE FINANACIAL STATEMENT FOR THE YEAR ENDED " END DATE OF CURRENT YEAR"
B4: ='2...'!B4:E4 -> (All amounts in Saudi Riyals unless otherwies stated)
B7: 14- Cost of revenue | D7: ='(2)..'!F6 -> CURRENT YEAR | F7: ='(2)..'!H6 -> PREVIOUS YEAR
D8: SR | F8: SR
B9: COGS | D9: =-SUM('Client TB (2)'!I79:I81,'Client TB (2)'!I84:I90) -> 0
B10: Total | D10: =SUM(D9:D9) -> 0 | F10: =SUM(F9) -> 0
B12: 15- General and Administrative Expenses | D12: =+D7 -> CURRENT YEAR | F12: =SCI!G6 -> PREVIOUS YEAR
D13: SR | F13: SR
B14: Government fees and subscriptions | D14: =SUM('Client TB (2)'!I119:I120,'Client TB (2)'!I125,'Client TB (2)'!I127,'Client TB (2)'!I137,'Client TB (2)'!I149,'Client TB (2)'!I147,'Client TB (2)'!I145) -> 0
B15: Salaries and wages, and their equivalents | D15: =SUM('Client TB (2)'!I112,'Client TB (2)'!I83) -> 0
B16: Rentals | D16: =SUM('Client TB (2)'!I105:I106) -> 0
B17: Social Insurance | D17: =SUM('Client TB (2)'!I115:I116,'Client TB (2)'!I128,'Client TB (2)'!I141:I142,'Client TB (2)'!I140) -> 0
B18: Insurance | D18: =SUM('Client TB (2)'!I144,) -> 0
B19: Employee benefits | D19: ='Client TB (2)'!I109 -> 0
B20: Travel expense | D20: =SUM('Client TB (2)'!I108,'Client TB (2)'!I139) -> 0
B21: Consulting charge | D21: =SUM('Client TB (2)'!I98:I99) -> 0
B22: Professional Fees | D22: =SUM('Client TB (2)'!I117,'Client TB (2)'!I131) -> 0
B23: Repair & Maintanance Expense | D23: =SUM('Client TB (2)'!I132:I134,'Client TB (2)'!I146,'Client TB (2)'!I113:I114) -> 0
B24: Vehicle expense
B25: Medical expense | D25: ='Client TB (2)'!I126 -> 0
B26: Telephone & Internet Expense | D26: ='Client TB (2)'!I138 -> 0
B27: Electricity & water expense | D27: =SUM('Client TB (2)'!I121,'Client TB (2)'!I148) -> 0
B28: Depreciation | D28: ='Client TB (2)'!I101 -> 0
B29: Printing & Stationary | D29: =SUM('Client TB (2)'!I95:I96) -> 0
B30: Banking fees | D30: ='Client TB (2)'!I103 -> 0
B31: Office Expenses | D31: =SUM('Client TB (2)'!I129:I130) -> 0
B32: Other operating expense | D32: =SUM('Client TB (2)'!I136,'Client TB (2)'!I110,'Client TB (2)'!I111) -> 0
B33: Fuel Expense | D33: ='Client TB (2)'!I124 -> 0
B34: Other expense | D34: =SUM('Client TB (2)'!I143,'Client TB (2)'!I135,'Client TB (2)'!I118,'Client TB (2)'!I122) -> 0
B35: Total | D35: =SUM(D14:D34) -> 0 | F35: =SUM(F14:F34) -> 0
B52: 17

Sheet 8
B1: ='6'!B1 -> "COMPANY NAME AS PER AOA"
B2: ='6'!B2 -> "TYPE OF COMPANY AS PER AOA"
B3: ='6'!B3 -> NOTES TO THE FINANACIAL STATEMENT FOR THE YEAR ENDED " END DATE OF CURRENT YEAR"
B4: ='6'!B4 -> (All amounts in Saudi Riyals unless otherwies stated)
B6: 16- FAIR VALUE OF FINANCIAL INSTRUMENTS
B7: Fair value
B8: Fair value of financial instruments risk is the amount for which as asset could be exchanged, or liability settled between knowledgeable willing parties in an arm's length transaction. Financial instruments comprised of financial assets and financial liabilities.
B9: RISK MANAGEMENT
B10: Risk management in the Companies activities are managed through a process of going identification, measurement and monitoring, subject to risk limits and other controls. The main risks arising from financial instruments are:
B11: Liquidity risk
B12: Credit risk
B13: Commission rate risk
B14: Foreign currency risk
B15: No changes were made in the risk management objectives, policies during the years ended December 31, 2025. The management of the Branch reviews and approves policies for managing each of these risks which are summarized below:
B16: Liquidity risk
B17: - The liquidity risks involve the Company facing difficulties in obtaining funds to meet financial obligations.
B18: - The Company works to mitigate liquidity risks by ensuring the availability of sufficient funding sources when needed.
C19: =+'6'!D7 -> CURRENT YEAR | E19: =+'6'!F7 -> PREVIOUS YEAR
C20: SAR | E20: SAR
B21: Current Assets | C21: =+SOFP!E11 -> 0 | E21: =SOFP!G11 -> 0
B22: Current Liabilities | C22: =-SOFP!E22 -> 0 | E22: =-SOFP!G22 -> 0
B23: Working Capital | C23: =SUM(C21:C22) -> 0 | E23: =SUM(E21:E22) -> 0
B25: Credit risk
B26: Credit risk is risk that one party will fall to discharge and cause the other party to incur a financial loss. Credit risk arises when failure by counterparties to discharge their obligations could reduce the amount of future cash follows from financial asset on hand at the reporting date. These has policies and procedures in place to limit the amount of credit exposure to any counter party and to monitor the collection of receivables on an ongoing basis.
B27: Commission rate risk
B28: Commission rate risk arises from the possibility that changes in commission rates will affect profitability or the fair values of financial instruments. The branch is not exposed to commission rate risk since there are no floating interest-bearing assets and liabilities at the balance sheet date.
B29: Foreign exchange risk
B30: Foreign exchange arises when future commercial transactions and recognized assets and liabilities are denominated in a currency that is not the Branch's financial currency. Foreign exchange risk is the risk that the value of a financial instrument will fluctuated due to changes in foreign exchange rates. The Branch did not undertake significant transaction in currencies other than Saudi Riyals and US Dollars, during the year/period. As the Saudi Riyal is pegged to the US Dollar, balances in Saudi Riyals are not considered to present significant currency risk.
B31: 17. Approval of Financial Statements
B32: The Financial Statements for issuance were approved by the general manager on , corresponding to .
B33: 18. General
B34: The figures in the Financial Statements have been rounded to the nearest Saudi riyal.
B37: 18

Sheet Client TB (2)
A1: TRIAL BALANCE FOR THE PERIOD FROM "FIRST DATE OF CURRENT YEAR AS PER AOA" TO " END DATE OF CURRENT YEAR AS PER AOA"
A2: Name | B2: Category | C2: Type | D2: Opening Balance | E2: Debit | F2: Credit | G2: Adjustment Entries | I2: 2025 Final
G3: Debit | H3: Credit
A150: Grand Total | D150: =SUM(D4:D149) -> 0 | E150: =SUM(E4:E149) -> 0 | F150: =SUM(F4:F149) -> 0 | G150: =SUM(G4:G149) -> 0 | H150: =SUM(H4:H149) -> 0 | I150: =SUM(I4:I149) -> 0
