Workbook

Sheet Materiality
B2: Materiality | H2: 500
B3: Client | E3: LRC
B4: Audit Area | E4: Risk Assessment | G4: Auditor | H4: 0
B5: Reporting Date | E5: 31 March 2026 | G5: Manager Review | H5: 0
B6: Date Prepared | G6: Partner Review | H6: 0
B7: Comment
B10: 1 | C10: Identify the principal users of the financial statements
C11: Users | F11: Comments
A12: 0 | B12: a
A13: 0 | B13: b
A14: 0 | B14: c
A15: 0 | B15: d
A16: 0 | B16: e
A17: 0 | B17: f
B19: 2 | C19: Describe nature and impact of qualitative considerations
C20: Nature | F20: Impact on audit plan
A21: 0 | B21: a
A22: 0 | B22: b
A23: 0 | B23: c
A24: 0 | B24: d
A25: 0 | B25: e
B27: 3 | C27: Determine quantitative materiality
C28: Planning data | F28: This period anticipated | G28: Previous period | H28: Preceding period
C29: Sales / revenues | F29: 1000000 | H29: 0
C30: Total assets | H30: 0
C31: Total equity | H31: 0
C32: Income before zakat/tax | H32: 0
C33: Previous materiality
B35: 4 | C35: Selecting a Numerical Threshold
E36: Basis | F36: Typical percentages | G36: Percentage applied | H36: Possible materiality
C37: Yes | E37: Sales / revenues | F37: 0.5% - 1% | G37: 0.5 | H37: =IF(C37="Yes",(F29*G37)/100, "") -> 5000
C38: No | E38: Total assets | F38: 0.5% - 1% | G38: 0.5
C39: No | E39: Total equity | F39: 0.01 | G39: 1
C40: No | E40: Income before zakat/tax | F40: 5% - 10% | G40: 5
C42: Based on the above considerations, the materiality is: | G42: SR | H42: =ABS(SUM(H37:H40)*80%) -> 4000

Sheet TB
A1: Ledger Code | B1: Account Name (TB) | C1: TB Debit | D1: TB Credit | E1: Ledger Debit (3 ledgers) | F1: Ledger Credit (3 ledgers) | G1: Debit difference | H1: Credit difference | I1: Reconciliation status | K1: TB debit/credit copied from Formated_TB.xlsx (sheet 'Formated'). Ledger columns are live sums of the three ledgers by Ledger Code.
A2: 10001 | B2: Accumulated Depreciation- Office Interiors | C2: 0 | D2: 3212.0439 | E2: =SUMIF('Revenue Ledger'!$C$2:$C$4500,$A2,'Revenue Ledger'!$G$2:$G$4500)+SUMIF('COGS Ledger'!$C$2:$C$400,$A2,'COGS Ledger'!$G$2:$G$400)+SUMIF('Expense Ledger'!$C$2:$C$800,$A2,'Expense Ledger'!$G$2:$G$800) -> 0 | F2: =SUMIF('Revenue Ledger'!$C$2:$C$4500,$A2,'Revenue Ledger'!$H$2:$H$4500)+SUMIF('COGS Ledger'!$C$2:$C$400,$A2,'COGS Ledger'!$H$2:$H$400)+SUMIF('Expense Ledger'!$C$2:$C$800,$A2,'Expense Ledger'!$H$2:$H$800) -> 0 | G2: =E2-C2 -> 0 | H2: =F2-D2 -> -3212.0439 | I2: =IF(AND(E2=0,F2=0),"No ledger lines",IF(AND(ABS(G2)<1,ABS(H2)<1),"Ties to TB","Difference – review")) -> No ledger lines
A3: 10002 | B3: Accumulated Amortisation- Software- Jbm | C3: 0 | D3: 2041.433 | E3: =SUMIF('Revenue Ledger'!$C$2:$C$4500,$A3,'Revenue Ledger'!$G$2:$G$4500)+SUMIF('COGS Ledger'!$C$2:$C$400,$A3,'COGS Ledger'!$G$2:$G$400)+SUMIF('Expense Ledger'!$C$2:$C$800,$A3,'Expense Ledger'!$G$2:$G$800) -> 0 | F3: =SUMIF('Revenue Ledger'!$C$2:$C$4500,$A3,'Revenue Ledger'!$H$2:$H$4500)+SUMIF('COGS Ledger'!$C$2:$C$400,$A3,'COGS Ledger'!$H$2:$H$400)+SUMIF('Expense Ledger'!$C$2:$C$800,$A3,'Expense Ledger'!$H$2:$H$800) -> 0 | G3: =E3-C3 -> 0 | H3: =F3-D3 -> -2041.433 | I3: =IF(AND(E3=0,F3=0),"No ledger lines",IF(AND(ABS(G3)<1,ABS(H3)<1),"Ties to TB","Difference – review")) -> No ledger lines
A4: 10003 | B4: Accumulated Depreciation- Computer Hardware | C4: 0 | D4: 22579.452 | E4: =SUMIF('Revenue Ledger'!$C$2:$C$4500,$A4,'Revenue Ledger'!$G$2:$G$4500)+SUMIF('COGS Ledger'!$C$2:$C$400,$A4,'COGS Ledger'!$G$2:$G$400)+SUMIF('Expense Ledger'!$C$2:$C$800,$A4,'Expense Ledger'!$G$2:$G$800) -> 0 | F4: =SUMIF('Revenue Ledger'!$C$2:$C$4500,$A4,'Revenue Ledger'!$H$2:$H$4500)+SUMIF('COGS Ledger'!$C$2:$C$400,$A4,'COGS Ledger'!$H$2:$H$400)+SUMIF('Expense Ledger'!$C$2:$C$800,$A4,'Expense Ledger'!$H$2:$H$800) -> 0 | G4: =E4-C4 -> 0 | H4: =F4-D4 -> -22579.452 | I4: =IF(AND(E4=0,F4=0),"No ledger lines",IF(AND(ABS(G4)<1,ABS(H4)<1),"Ties to TB","Difference – review")) -> No ledger lines
A5: 10004 | B5: Cash In Hand | C5: 7000 | D5: 6284.5 | E5: =SUMIF('Revenue Ledger'!$C$2:$C$4500,$A5,'Revenue Ledger'!$G$2:$G$4500)+SUMIF('COGS Ledger'!$C$2:$C$400,$A5,'COGS Ledger'!$G$2:$G$400)+SUMIF('Expense Ledger'!$C$2:$C$800,$A5,'Expense Ledger'!$G$2:$G$800) -> 0 | F5: =SUMIF('Revenue Ledger'!$C$2:$C$4500,$A5,'Revenue Ledger'!$H$2:$H$4500)+SUMIF('COGS Ledger'!$C$2:$C$400,$A5,'COGS Ledger'!$H$2:$H$400)+SUMIF('Expense Ledger'!$C$2:$C$800,$A5,'Expense Ledger'!$H$2:$H$800) -> 0 | G5: =E5-C5 -> -7000 | H5: =F5-D5 -> -6284.5 | I5: =IF(AND(E5=0,F5=0),"No ledger lines",IF(AND(ABS(G5)<1,ABS(H5)<1),"Ties to TB","Difference – review")) -> No ledger lines
A6: 10005 | B6: Computer Hardware | C6: 30606.85 | D6: 0 | E6: =SUMIF('Revenue Ledger'!$C$2:$C$4500,$A6,'Revenue Ledger'!$G$2:$G$4500)+SUMIF('COGS Ledger'!$C$2:$C$400,$A6,'COGS Ledger'!$G$2:$G$400)+SUMIF('Expense Ledger'!$C$2:$C$800,$A6,'Expense Ledger'!$G$2:$G$800) -> 0 | F6: =SUMIF('Revenue Ledger'!$C$2:$C$4500,$A6,'Revenue Ledger'!$H$2:$H$4500)+SUMIF('COGS Ledger'!$C$2:$C$400,$A6,'COGS Ledger'!$H$2:$H$400)+SUMIF('Expense Ledger'!$C$2:$C$800,$A6,'Expense Ledger'!$H$2:$H$800) -> 0 | G6: =E6-C6 -> -30606.85 | H6: =F6-D6 -> 0 | I6: =IF(AND(E6=0,F6=0),"No ledger lines",IF(AND(ABS(G6)<1,ABS(H6)<1),"Ties to TB","Difference – review")) -> No ledger lines
A7: 10006 | B7: Office Interior Cost | C7: 265000 | D7: 0 | E7: =SUMIF('Revenue Ledger'!$C$2:$C$4500,$A7,'Revenue Ledger'!$G$2:$G$4500)+SUMIF('COGS Ledger'!$C$2:$C$400,$A7,'COGS Ledger'!$G$2:$G$400)+SUMIF('Expense Ledger'!$C$2:$C$800,$A7,'Expense Ledger'!$G$2:$G$800) -> 0 | F7: =SUMIF('Revenue Ledger'!$C$2:$C$4500,$A7,'Revenue Ledger'!$H$2:$H$4500)+SUMIF('COGS Ledger'!$C$2:$C$400,$A7,'COGS Ledger'!$H$2:$H$400)+SUMIF('Expense Ledger'!$C$2:$C$800,$A7,'Expense Ledger'!$H$2:$H$800) -> 0 | G7: =E7-C7 -> -265000 | H7: =F7-D7 -> 0 | I7: =IF(AND(E7=0,F7=0),"No ledger lines",IF(AND(ABS(G7)<1,ABS(H7)<1),"Ties to TB","Difference – review")) -> No ledger lines
A8: 10007 | B8: Software- Jbm | C8: 37727.75 | D8: 0 | E8: =SUMIF('Revenue Ledger'!$C$2:$C$4500,$A8,'Revenue Ledger'!$G$2:$G$4500)+SUMIF('COGS Ledger'!$C$2:$C$400,$A8,'COGS Ledger'!$G$2:$G$400)+SUMIF('Expense Ledger'!$C$2:$C$800,$A8,'Expense Ledger'!$G$2:$G$800) -> 0 | F8: =SUMIF('Revenue Ledger'!$C$2:$C$4500,$A8,'Revenue Ledger'!$H$2:$H$4500)+SUMIF('COGS Ledger'!$C$2:$C$400,$A8,'COGS Ledger'!$H$2:$H$400)+SUMIF('Expense Ledger'!$C$2:$C$800,$A8,'Expense Ledger'!$H$2:$H$800) -> 0 | G8: =E8-C8 -> -37727.75 | H8: =F8-D8 -> 0 | I8: =IF(AND(E8=0,F8=0),"No ledger lines",IF(AND(ABS(G8)<1,ABS(H8)<1),"Ties to TB","Difference – review")) -> No ledger lines
A9: 10008 | B9: Health Insurance- Non Saudis | C9: 4252 | D9: 419.37534 | E9: =SUMIF('Revenue Ledger'!$C$2:$C$4500,$A9,'Revenue Ledger'!$G$2:$G$4500)+SUMIF('COGS Ledger'!$C$2:$C$400,$A9,'COGS Ledger'!$G$2:$G$400)+SUMIF('Expense Ledger'!$C$2:$C$800,$A9,'Expense Ledger'!$G$2:$G$800) -> 0 | F9: =SUMIF('Revenue Ledger'!$C$2:$C$4500,$A9,'Revenue Ledger'!$H$2:$H$4500)+SUMIF('COGS Ledger'!$C$2:$C$400,$A9,'COGS Ledger'!$H$2:$H$400)+SUMIF('Expense Ledger'!$C$2:$C$800,$A9,'Expense Ledger'!$H$2:$H$800) -> 0 | G9: =E9-C9 -> -4252 | H9: =F9-D9 -> -419.37534 | I9: =IF(AND(E9=0,F9=0),"No ledger lines",IF(AND(ABS(G9)<1,ABS(H9)<1),"Ties to TB","Difference – review")) -> No ledger lines
A10: 10009 | B10: Health Insurance- Saudi | C10: 7667 | D10: 756.19726 | E10: =SUMIF('Revenue Ledger'!$C$2:$C$4500,$A10,'Revenue Ledger'!$G$2:$G$4500)+SUMIF('COGS Ledger'!$C$2:$C$400,$A10,'COGS Ledger'!$G$2:$G$400)+SUMIF('Expense Ledger'!$C$2:$C$800,$A10,'Expense Ledger'!$G$2:$G$800) -> 0 | F10: =SUMIF('Revenue Ledger'!$C$2:$C$4500,$A10,'Revenue Ledger'!$H$2:$H$4500)+SUMIF('COGS Ledger'!$C$2:$C$400,$A10,'COGS Ledger'!$H$2:$H$400)+SUMIF('Expense Ledger'!$C$2:$C$800,$A10,'Expense Ledger'!$H$2:$H$800) -> 0 | G10: =E10-C10 -> -7667 | H10: =F10-D10 -> -756.19726 | I10: =IF(AND(E10=0,F10=0),"No ledger lines",IF(AND(ABS(G10)<1,ABS(H10)<1),"Ties to TB","Difference – review")) -> No ledger lines
A11: 10010 | B11: Prepaid- Employee Iqama | C11: 35200 | D11: 6474.97 | E11: =SUMIF('Revenue Ledger'!$C$2:$C$4500,$A11,'Revenue Ledger'!$G$2:$G$4500)+SUMIF('COGS Ledger'!$C$2:$C$400,$A11,'COGS Ledger'!$G$2:$G$400)+SUMIF('Expense Ledger'!$C$2:$C$800,$A11,'Expense Ledger'!$G$2:$G$800) -> 0 | F11: =SUMIF('Revenue Ledger'!$C$2:$C$4500,$A11,'Revenue Ledger'!$H$2:$H$4500)+SUMIF('COGS Ledger'!$C$2:$C$400,$A11,'COGS Ledger'!$H$2:$H$400)+SUMIF('Expense Ledger'!$C$2:$C$800,$A11,'Expense Ledger'!$H$2:$H$800) -> 0 | G11: =E11-C11 -> -35200 | H11: =F11-D11 -> -6474.97 | I11: =IF(AND(E11=0,F11=0),"No ledger lines",IF(AND(ABS(G11)<1,ABS(H11)<1),"Ties to TB","Difference – review")) -> No ledger lines
A12: 10011 | B12: Insurance- Deposits | C12: 500000 | D12: 0 | E12: =SUMIF('Revenue Ledger'!$C$2:$C$4500,$A12,'Revenue Ledger'!$G$2:$G$4500)+SUMIF('COGS Ledger'!$C$2:$C$400,$A12,'COGS Ledger'!$G$2:$G$400)+SUMIF('Expense Ledger'!$C$2:$C$800,$A12,'Expense Ledger'!$G$2:$G$800) -> 0 | F12: =SUMIF('Revenue Ledger'!$C$2:$C$4500,$A12,'Revenue Ledger'!$H$2:$H$4500)+SUMIF('COGS Ledger'!$C$2:$C$400,$A12,'COGS Ledger'!$H$2:$H$400)+SUMIF('Expense Ledger'!$C$2:$C$800,$A12,'Expense Ledger'!$H$2:$H$800) -> 0 | G12: =E12-C12 -> -500000 | H12: =F12-D12 -> 0 | I12: =IF(AND(E12=0,F12=0),"No ledger lines",IF(AND(ABS(G12)<1,ABS(H12)<1),"Ties to TB","Difference – review")) -> No ledger lines
A13: 10012 | B13: Rent- Advance | C13: 87600 | D13: 87600 | E13: =SUMIF('Revenue Ledger'!$C$2:$C$4500,$A13,'Revenue Ledger'!$G$2:$G$4500)+SUMIF('COGS Ledger'!$C$2:$C$400,$A13,'COGS Ledger'!$G$2:$G$400)+SUMIF('Expense Ledger'!$C$2:$C$800,$A13,'Expense Ledger'!$G$2:$G$800) -> 0 | F13: =SUMIF('Revenue Ledger'!$C$2:$C$4500,$A13,'Revenue Ledger'!$H$2:$H$4500)+SUMIF('COGS Ledger'!$C$2:$C$400,$A13,'COGS Ledger'!$H$2:$H$400)+SUMIF('Expense Ledger'!$C$2:$C$800,$A13,'Expense Ledger'!$H$2:$H$800) -> 0 | G13: =E13-C13 -> -87600 | H13: =F13-D13 -> -87600 | I13: =IF(AND(E13=0,F13=0),"No ledger lines",IF(AND(ABS(G13)<1,ABS(H13)<1),"Ties to TB","Difference – review")) -> No ledger lines
... A124: 10124 | B124: Gosi Payable | C124: 0 | D124: 4518.08 | E124: =SUMIF('Revenue Ledger'!$C$2:$C$4500,$A124,'Revenue Ledger'!$G$2:$G$4500)+SUMIF('COGS Ledger'!$C$2:$C$400,$A124,'COGS Ledger'!$G$2:$G$400)+SUMIF('Expense Ledger'!$C$2:$C$800,$A124,'Expense Ledger'!$G$2:$G$800) -> 0 | F124: =SUMIF('Revenue Ledger'!$C$2:$C$4500,$A124,'Revenue Ledger'!$H$2:$H$4500)+SUMIF('COGS Ledger'!$C$2:$C$400,$A124,'COGS Ledger'!$H$2:$H$400)+SUMIF('Expense Ledger'!$C$2:$C$800,$A124,'Expense Ledger'!$H$2:$H$800) -> 0 | G124: =E124-C124 -> 0 | H124: =F124-D124 -> -4518.08 | I124: =IF(AND(E124=0,F124=0),"No ledger lines",IF(AND(ABS(G124)<1,ABS(H124)<1),"Ties to TB","Difference – review")) -> No ledger lines

Sheet Ledger Codes
A1: Ledger code map – every ledger account → TB ledger code
A2: Codes come from the TB sheet. Edit a code (yellow) and every ledger, the TB reconciliation and the sample lists update.
A3: Match basis: Exact name match | Mapped – ties to TB (amounts agree to the TB) | Proposed – confirm (best fit, please check) | No TB account – confirm.
A5: # | B5: Account name in ledger (trimmed) | C5: Ledger Code | D5: TB account name | E5: Used in | F5: Match basis | G5: Note | H5: Ledger lines
A6: 1 | B6: AGENCY COMMISSION EXPORT- INC | C6: 10069 | D6: =IF(C6="","",IFERROR(INDEX(TB!$B$2:$B$130,MATCH(C6,TB!$A$2:$A$130,0)),"Code not in TB")) -> Agency Commission Import- Inc | E6: Revenue | F6: Mapped – ties to TB | G6: Export + Import lines together = TB 10069 credit | H6: =IF(B6="","",COUNTIF('Revenue Ledger'!$S$2:$S$4500,B6)+COUNTIF('COGS Ledger'!$S$2:$S$400,B6)+COUNTIF('Expense Ledger'!$S$2:$S$800,B6)) -> 4
A7: 2 | B7: AGENCY COMMISSION IMPORT- INC | C7: 10069 | D7: =IF(C7="","",IFERROR(INDEX(TB!$B$2:$B$130,MATCH(C7,TB!$A$2:$A$130,0)),"Code not in TB")) -> Agency Commission Import- Inc | E7: Revenue | F7: Exact name match | H7: =IF(B7="","",COUNTIF('Revenue Ledger'!$S$2:$S$4500,B7)+COUNTIF('COGS Ledger'!$S$2:$S$400,B7)+COUNTIF('Expense Ledger'!$S$2:$S$800,B7)) -> 7
A8: 3 | B8: AGENCY COMMISSION- T/S HANDLING | C8: 10070 | D8: =IF(C8="","",IFERROR(INDEX(TB!$B$2:$B$130,MATCH(C8,TB!$A$2:$A$130,0)),"Code not in TB")) -> Agency Commission- T/S Handling | E8: Revenue | F8: Exact name match | H8: =IF(B8="","",COUNTIF('Revenue Ledger'!$S$2:$S$4500,B8)+COUNTIF('COGS Ledger'!$S$2:$S$400,B8)+COUNTIF('Expense Ledger'!$S$2:$S$800,B8)) -> 3
A9: 4 | B9: AGENCY COMMISSION- VESSEL HANDLING | C9: 10071 | D9: =IF(C9="","",IFERROR(INDEX(TB!$B$2:$B$130,MATCH(C9,TB!$A$2:$A$130,0)),"Code not in TB")) -> Agency Commission- Vessel Handling | E9: Revenue | F9: Exact name match | H9: =IF(B9="","",COUNTIF('Revenue Ledger'!$S$2:$S$4500,B9)+COUNTIF('COGS Ledger'!$S$2:$S$400,B9)+COUNTIF('Expense Ledger'!$S$2:$S$800,B9)) -> 5
A10: 5 | B10: BERTHING & UNBERTHING CHARGES- INC | C10: 10047 | D10: =IF(C10="","",IFERROR(INDEX(TB!$B$2:$B$130,MATCH(C10,TB!$A$2:$A$130,0)),"Code not in TB")) -> Berthing & Unberthing Charges- Inc | E10: Revenue | F10: Exact name match | H10: =IF(B10="","",COUNTIF('Revenue Ledger'!$S$2:$S$4500,B10)+COUNTIF('COGS Ledger'!$S$2:$S$400,B10)+COUNTIF('Expense Ledger'!$S$2:$S$800,B10)) -> 5
A11: 6 | B11: BILL OF LADING FEE- INC | C11: 10072 | D11: =IF(C11="","",IFERROR(INDEX(TB!$B$2:$B$130,MATCH(C11,TB!$A$2:$A$130,0)),"Code not in TB")) -> Bill Of Lading Fee- Inc | E11: Revenue | F11: Exact name match | H11: =IF(B11="","",COUNTIF('Revenue Ledger'!$S$2:$S$4500,B11)+COUNTIF('COGS Ledger'!$S$2:$S$400,B11)+COUNTIF('Expense Ledger'!$S$2:$S$800,B11)) -> 5
A12: 7 | B12: CONTAINER DAMAGE CHARGES- INC | C12: 10048 | D12: =IF(C12="","",IFERROR(INDEX(TB!$B$2:$B$130,MATCH(C12,TB!$A$2:$A$130,0)),"Code not in TB")) -> Container Damage Charges- Inc | E12: Revenue | F12: Exact name match | H12: =IF(B12="","",COUNTIF('Revenue Ledger'!$S$2:$S$4500,B12)+COUNTIF('COGS Ledger'!$S$2:$S$400,B12)+COUNTIF('Expense Ledger'!$S$2:$S$800,B12)) -> 65
A13: 8 | B13: CONTAINER GATE PASS FEE- INC | C13: 10049 | D13: =IF(C13="","",IFERROR(INDEX(TB!$B$2:$B$130,MATCH(C13,TB!$A$2:$A$130,0)),"Code not in TB")) -> Container Gate Pass Fee- Inc | E13: Revenue | F13: Exact name match | H13: =IF(B13="","",COUNTIF('Revenue Ledger'!$S$2:$S$4500,B13)+COUNTIF('COGS Ledger'!$S$2:$S$400,B13)+COUNTIF('Expense Ledger'!$S$2:$S$800,B13)) -> 558
A14: 9 | B14: DELIVERY ORDER CHARGES- INC | C14: 10073 | D14: =IF(C14="","",IFERROR(INDEX(TB!$B$2:$B$130,MATCH(C14,TB!$A$2:$A$130,0)),"Code not in TB")) -> Delivery Order Charges- Inc | E14: Revenue | F14: Exact name match | H14: =IF(B14="","",COUNTIF('Revenue Ledger'!$S$2:$S$4500,B14)+COUNTIF('COGS Ledger'!$S$2:$S$400,B14)+COUNTIF('Expense Ledger'!$S$2:$S$800,B14)) -> 504
A15: 10 | B15: DEPARTURE FEES & CLEANING CHARGES- INC | C15: 10050 | D15: =IF(C15="","",IFERROR(INDEX(TB!$B$2:$B$130,MATCH(C15,TB!$A$2:$A$130,0)),"Code not in TB")) -> Departure Fees & Cleaning Charges- Inc | E15: Revenue | F15: Exact name match | H15: =IF(B15="","",COUNTIF('Revenue Ledger'!$S$2:$S$4500,B15)+COUNTIF('COGS Ledger'!$S$2:$S$400,B15)+COUNTIF('Expense Ledger'!$S$2:$S$800,B15)) -> 1
A16: 11 | B16: DETENTION COMMISSION- INC | C16: 10067 | D16: =IF(C16="","",IFERROR(INDEX(TB!$B$2:$B$130,MATCH(C16,TB!$A$2:$A$130,0)),"Code not in TB")) -> Detention Commission- Inc | E16: Revenue | F16: Exact name match | H16: =IF(B16="","",COUNTIF('Revenue Ledger'!$S$2:$S$4500,B16)+COUNTIF('COGS Ledger'!$S$2:$S$400,B16)+COUNTIF('Expense Ledger'!$S$2:$S$800,B16)) -> 21
A17: 12 | B17: EDI CHARGES- INC | C17: 10068 | D17: =IF(C17="","",IFERROR(INDEX(TB!$B$2:$B$130,MATCH(C17,TB!$A$2:$A$130,0)),"Code not in TB")) -> Edi Charges- Inc | E17: Revenue | F17: Exact name match | H17: =IF(B17="","",COUNTIF('Revenue Ledger'!$S$2:$S$4500,B17)+COUNTIF('COGS Ledger'!$S$2:$S$400,B17)+COUNTIF('Expense Ledger'!$S$2:$S$800,B17)) -> 504
A18: 13 | B18: FASAH CHARGES- INC | C18: 10066 | D18: =IF(C18="","",IFERROR(INDEX(TB!$B$2:$B$130,MATCH(C18,TB!$A$2:$A$130,0)),"Code not in TB")) -> Fasah Charges- Inc | E18: Revenue | F18: Exact name match | H18: =IF(B18="","",COUNTIF('Revenue Ledger'!$S$2:$S$4500,B18)+COUNTIF('COGS Ledger'!$S$2:$S$400,B18)+COUNTIF('Expense Ledger'!$S$2:$S$800,B18)) -> 562
... A34: 29 | B34: TRANSPORTATION CHARGES | C34: 10065 | D34: =IF(C34="","",IFERROR(INDEX(TB!$B$2:$B$130,MATCH(C34,TB!$A$2:$A$130,0)),"Code not in TB")) -> Transportation Charges | E34: Revenue | F34: Exact name match | H34: =IF(B34="","",COUNTIF('Revenue Ledger'!$S$2:$S$4500,B34)+COUNTIF('COGS Ledger'!$S$2:$S$400,B34)+COUNTIF('Expense Ledger'!$S$2:$S$800,B34)) -> 9
A35: 30 | B35: BERTHING & UNBERTHING CHARGES- EXP | C35: 10047 | D35: =IF(C35="","",IFERROR(INDEX(TB!$B$2:$B$130,MATCH(C35,TB!$A$2:$A$130,0)),"Code not in TB")) -> Berthing & Unberthing Charges- Inc | E35: COGS | F35: Mapped – ties to TB | G35: TB keeps income and cost in one account; debits tie | H35: =IF(B35="","",COUNTIF('Revenue Ledger'!$S$2:$S$4500,B35)+COUNTIF('COGS Ledger'!$S$2:$S$400,B35)+COUNTIF('Expense Ledger'!$S$2:$S$800,B35)) -> 7
A36: 31 | B36: CONTAINER DAMAGE CHARGES- COST | C36: 10048 | D36: =IF(C36="","",IFERROR(INDEX(TB!$B$2:$B$130,MATCH(C36,TB!$A$2:$A$130,0)),"Code not in TB")) -> Container Damage Charges- Inc | E36: COGS | F36: Mapped – ties to TB | G36: Debits tie to TB combined account | H36: =IF(B36="","",COUNTIF('Revenue Ledger'!$S$2:$S$4500,B36)+COUNTIF('COGS Ledger'!$S$2:$S$400,B36)+COUNTIF('Expense Ledger'!$S$2:$S$800,B36)) -> 4
A37: 32 | B37: CONTAINER GATE PASS FEE- EXP | C37: 10049 | D37: =IF(C37="","",IFERROR(INDEX(TB!$B$2:$B$130,MATCH(C37,TB!$A$2:$A$130,0)),"Code not in TB")) -> Container Gate Pass Fee- Inc | E37: COGS | F37: Mapped – ties to TB | G37: Debits tie to TB combined account | H37: =IF(B37="","",COUNTIF('Revenue Ledger'!$S$2:$S$4500,B37)+COUNTIF('COGS Ledger'!$S$2:$S$400,B37)+COUNTIF('Expense Ledger'!$S$2:$S$800,B37)) -> 9
A38: 33 | B38: CONTAINER HOLD CHARGES-EXP | C38: 10084 | D38: =IF(C38="","",IFERROR(INDEX(TB!$B$2:$B$130,MATCH(C38,TB!$A$2:$A$130,0)),"Code not in TB")) -> Container Hold Charges-Exp | E38: COGS | F38: Exact name match | H38: =IF(B38="","",COUNTIF('Revenue Ledger'!$S$2:$S$4500,B38)+COUNTIF('COGS Ledger'!$S$2:$S$400,B38)+COUNTIF('Expense Ledger'!$S$2:$S$800,B38)) -> 1
A39: 34 | B39: DEPARTURE FEES & CLEANING CHARGES- EXP | C39: 10050 | D39: =IF(C39="","",IFERROR(INDEX(TB!$B$2:$B$130,MATCH(C39,TB!$A$2:$A$130,0)),"Code not in TB")) -> Departure Fees & Cleaning Charges- Inc | E39: COGS | F39: Mapped – ties to TB | G39: Debits tie to TB combined account | H39: =IF(B39="","",COUNTIF('Revenue Ledger'!$S$2:$S$4500,B39)+COUNTIF('COGS Ledger'!$S$2:$S$400,B39)+COUNTIF('Expense Ledger'!$S$2:$S$800,B39)) -> 1
A40: 35 | B40: ELECTRONIC AMENDMENT LETTERS | C40: 10068 | D40: =IF(C40="","",IFERROR(INDEX(TB!$B$2:$B$130,MATCH(C40,TB!$A$2:$A$130,0)),"Code not in TB")) -> Edi Charges- Inc | E40: COGS | F40: Mapped – ties to TB | G40: With Electronic Data Interchange, debits = TB 10068 | H40: =IF(B40="","",COUNTIF('Revenue Ledger'!$S$2:$S$4500,B40)+COUNTIF('COGS Ledger'!$S$2:$S$400,B40)+COUNTIF('Expense Ledger'!$S$2:$S$800,B40)) -> 2
A41: 36 | B41: ELECTRONIC DATA INTERCHANGE- EXP | C41: 10068 | D41: =IF(C41="","",IFERROR(INDEX(TB!$B$2:$B$130,MATCH(C41,TB!$A$2:$A$130,0)),"Code not in TB")) -> Edi Charges- Inc | E41: COGS | F41: Mapped – ties to TB | G41: With Electronic Amendment Letters, debits = TB 10068 | H41: =IF(B41="","",COUNTIF('Revenue Ledger'!$S$2:$S$4500,B41)+COUNTIF('COGS Ledger'!$S$2:$S$400,B41)+COUNTIF('Expense Ledger'!$S$2:$S$800,B41)) -> 2
A42: 37 | B42: FASAH APPOINTMENT FEES | C42: 10066 | D42: =IF(C42="","",IFERROR(INDEX(TB!$B$2:$B$130,MATCH(C42,TB!$A$2:$A$130,0)),"Code not in TB")) -> Fasah Charges- Inc | E42: COGS | F42: Mapped – ties to TB | G42: With Fasah Pay Service Charges, debits = TB 10066 | H42: =IF(B42="","",COUNTIF('Revenue Ledger'!$S$2:$S$4500,B42)+COUNTIF('COGS Ledger'!$S$2:$S$400,B42)+COUNTIF('Expense Ledger'!$S$2:$S$800,B42)) -> 8
A43: 38 | B43: FASAH PAY SERVICE CHARGES | C43: 10066 | D43: =IF(C43="","",IFERROR(INDEX(TB!$B$2:$B$130,MATCH(C43,TB!$A$2:$A$130,0)),"Code not in TB")) -> Fasah Charges- Inc | E43: COGS | F43: Mapped – ties to TB | G43: With Fasah Appointment Fees, debits = TB 10066 | H43: =IF(B43="","",COUNTIF('Revenue Ledger'!$S$2:$S$4500,B43)+COUNTIF('COGS Ledger'!$S$2:$S$400,B43)+COUNTIF('Expense Ledger'!$S$2:$S$800,B43)) -> 1
A44: 39 | B44: FRESH WATER SUPPLY | C44: 10079 | D44: =IF(C44="","",IFERROR(INDEX(TB!$B$2:$B$130,MATCH(C44,TB!$A$2:$A$130,0)),"Code not in TB")) -> Fresh Water Supply | E44: COGS | F44: Exact name match | H44: =IF(B44="","",COUNTIF('Revenue Ledger'!$S$2:$S$4500,B44)+COUNTIF('COGS Ledger'!$S$2:$S$400,B44)+COUNTIF('Expense Ledger'!$S$2:$S$800,B44)) -> 4
A45: 40 | B45: FUMIGATION CHARGES | C45: 10080 | D45: =IF(C45="","",IFERROR(INDEX(TB!$B$2:$B$130,MATCH(C45,TB!$A$2:$A$130,0)),"Code not in TB")) -> Fumigation Charges | E45: COGS | F45: Exact name match | H45: =IF(B45="","",COUNTIF('Revenue Ledger'!$S$2:$S$4500,B45)+COUNTIF('COGS Ledger'!$S$2:$S$400,B45)+COUNTIF('Expense Ledger'!$S$2:$S$800,B45)) -> 4
A46: 41 | B46: IMPORT DETENTION-EXP | C46: 10067 | D46: =IF(C46="","",IFERROR(INDEX(TB!$B$2:$B$130,MATCH(C46,TB!$A$2:$A$130,0)),"Code not in TB")) -> Detention Commission- Inc | E46: COGS | F46: Mapped – ties to TB | G46: Debits tie to TB 10067 | H46: =IF(B46="","",COUNTIF('Revenue Ledger'!$S$2:$S$4500,B46)+COUNTIF('COGS Ledger'!$S$2:$S$400,B46)+COUNTIF('Expense Ledger'!$S$2:$S$800,B46)) -> 6
A47: 42 | B47: INVOICE AMENDMENT CHARGES | C47: 10081 | D47: =IF(C47="","",IFERROR(INDEX(TB!$B$2:$B$130,MATCH(C47,TB!$A$2:$A$130,0)),"Code not in TB")) -> Invoice Amendment Charges | E47: COGS | F47: Exact name match | H47: =IF(B47="","",COUNTIF('Revenue Ledger'!$S$2:$S$4500,B47)+COUNTIF('COGS Ledger'!$S$2:$S$400,B47)+COUNTIF('Expense Ledger'!$S$2:$S$800,B47)) -> 1
A48: 43 | B48: LINER EXP UNDER COMPANY ACCOUNT | C48: 10085 | D48: =IF(C48="","",IFERROR(INDEX(TB!$B$2:$B$130,MATCH(C48,TB!$A$2:$A$130,0)),"Code not in TB")) -> Liner Exp Under Company Account | E48: COGS | F48: Exact name match | H48: =IF(B48="","",COUNTIF('Revenue Ledger'!$S$2:$S$4500,B48)+COUNTIF('COGS Ledger'!$S$2:$S$400,B48)+COUNTIF('Expense Ledger'!$S$2:$S$800,B48)) -> 4
A49: 44 | B49: LOLO CHARGES - EXP | C49: 10051 | D49: =IF(C49="","",IFERROR(INDEX(TB!$B$2:$B$130,MATCH(C49,TB!$A$2:$A$130,0)),"Code not in TB")) -> Lolo Charges- Inc | E49: COGS | F49: Mapped – ties to TB | G49: Debits tie to TB combined account | H49: =IF(B49="","",COUNTIF('Revenue Ledger'!$S$2:$S$4500,B49)+COUNTIF('COGS Ledger'!$S$2:$S$400,B49)+COUNTIF('Expense Ledger'!$S$2:$S$800,B49)) -> 11
A50: 45 | B50: OCEAN FREIGHT- EXP | C50: 10052 | D50: =IF(C50="","",IFERROR(INDEX(TB!$B$2:$B$130,MATCH(C50,TB!$A$2:$A$130,0)),"Code not in TB")) -> Ocean Freight- Inc | E50: COGS | F50: Mapped – ties to TB | G50: Debits tie to TB combined account | H50: =IF(B50="","",COUNTIF('Revenue Ledger'!$S$2:$S$4500,B50)+COUNTIF('COGS Ledger'!$S$2:$S$400,B50)+COUNTIF('Expense Ledger'!$S$2:$S$800,B50)) -> 14
A51: 46 | B51: OPERATION RECOVERY COST | C51: 10053 | D51: =IF(C51="","",IFERROR(INDEX(TB!$B$2:$B$130,MATCH(C51,TB!$A$2:$A$130,0)),"Code not in TB")) -> Operation Recovery Cost- Inc | E51: COGS | F51: Mapped – ties to TB | G51: Debits tie to TB combined account | H51: =IF(B51="","",COUNTIF('Revenue Ledger'!$S$2:$S$4500,B51)+COUNTIF('COGS Ledger'!$S$2:$S$400,B51)+COUNTIF('Expense Ledger'!$S$2:$S$800,B51)) -> 49
A52: 47 | B52: PHOTO CHARGE- EXP | C52: 10054 | D52: =IF(C52="","",IFERROR(INDEX(TB!$B$2:$B$130,MATCH(C52,TB!$A$2:$A$130,0)),"Code not in TB")) -> Photo Charges- Inc | E52: COGS | F52: Mapped – ties to TB | G52: With Photo Charges- Exp, debits = TB 10054 | H52: =IF(B52="","",COUNTIF('Revenue Ledger'!$S$2:$S$4500,B52)+COUNTIF('COGS Ledger'!$S$2:$S$400,B52)+COUNTIF('Expense Ledger'!$S$2:$S$800,B52)) -> 8
A53: 48 | B53: PHOTO CHARGES- EXP | C53: 10054 | D53: =IF(C53="","",IFERROR(INDEX(TB!$B$2:$B$130,MATCH(C53,TB!$A$2:$A$130,0)),"Code not in TB")) -> Photo Charges- Inc | E53: COGS | F53: Mapped – ties to TB | G53: With Photo Charge- Exp, debits = TB 10054 | H53: =IF(B53="","",COUNTIF('Revenue Ledger'!$S$2:$S$4500,B53)+COUNTIF('COGS Ledger'!$S$2:$S$400,B53)+COUNTIF('Expense Ledger'!$S$2:$S$800,B53)) -> 1
A54: 49 | B54: PRE ARRIVAL NOTIFICATION | C54: 10086 | D54: =IF(C54="","",IFERROR(INDEX(TB!$B$2:$B$130,MATCH(C54,TB!$A$2:$A$130,0)),"Code not in TB")) -> Pre Arrival Notification | E54: COGS | F54: Exact name match | H54: =IF(B54="","",COUNTIF('Revenue Ledger'!$S$2:$S$4500,B54)+COUNTIF('COGS Ledger'!$S$2:$S$400,B54)+COUNTIF('Expense Ledger'!$S$2:$S$800,B54)) -> 2
A55: 50 | B55: RECOVERY HOLDING CHARGES- EXP | C55: 10055 | D55: =IF(C55="","",IFERROR(INDEX(TB!$B$2:$B$130,MATCH(C55,TB!$A$2:$A$130,0)),"Code not in TB")) -> Recovery Holding Charges- Inc | E55: COGS | F55: Mapped – ties to TB | G55: Debits tie to TB combined account | H55: =IF(B55="","",COUNTIF('Revenue Ledger'!$S$2:$S$4500,B55)+COUNTIF('COGS Ledger'!$S$2:$S$400,B55)+COUNTIF('Expense Ledger'!$S$2:$S$800,B55)) -> 3
A56: 51 | B56: REEFER MONITORING/MAINTENANCE | C56: 10060 | D56: =IF(C56="","",IFERROR(INDEX(TB!$B$2:$B$130,MATCH(C56,TB!$A$2:$A$130,0)),"Code not in TB")) -> Reefer Monitoring/Maintenance | E56: COGS | F56: Exact name match | H56: =IF(B56="","",COUNTIF('Revenue Ledger'!$S$2:$S$4500,B56)+COUNTIF('COGS Ledger'!$S$2:$S$400,B56)+COUNTIF('Expense Ledger'!$S$2:$S$800,B56)) -> 2
A57: 52 | B57: RENOMINATION CHARGES | C57: 10061 | D57: =IF(C57="","",IFERROR(INDEX(TB!$B$2:$B$130,MATCH(C57,TB!$A$2:$A$130,0)),"Code not in TB")) -> Renomination Charges | E57: COGS | F57: Exact name match | H57: =IF(B57="","",COUNTIF('Revenue Ledger'!$S$2:$S$4500,B57)+COUNTIF('COGS Ledger'!$S$2:$S$400,B57)+COUNTIF('Expense Ledger'!$S$2:$S$800,B57)) -> 5
A58: 53 | B58: RESTOW CHARGES - EXP | C58: 10056 | D58: =IF(C58="","",IFERROR(INDEX(TB!$B$2:$B$130,MATCH(C58,TB!$A$2:$A$130,0)),"Code not in TB")) -> Restow Charges - Inc | E58: COGS | F58: Mapped – ties to TB | G58: Debits tie to TB combined account | H58: =IF(B58="","",COUNTIF('Revenue Ledger'!$S$2:$S$4500,B58)+COUNTIF('COGS Ledger'!$S$2:$S$400,B58)+COUNTIF('Expense Ledger'!$S$2:$S$800,B58)) -> 1
A59: 54 | B59: SHIFTING CHARGES - EXP | C59: 10057 | D59: =IF(C59="","",IFERROR(INDEX(TB!$B$2:$B$130,MATCH(C59,TB!$A$2:$A$130,0)),"Code not in TB")) -> Shifting Charges- Inc | E59: COGS | F59: Mapped – ties to TB | G59: Debits tie to TB combined account | H59: =IF(B59="","",COUNTIF('Revenue Ledger'!$S$2:$S$4500,B59)+COUNTIF('COGS Ledger'!$S$2:$S$400,B59)+COUNTIF('Expense Ledger'!$S$2:$S$800,B59)) -> 1
A60: 55 | B60: SLOT CHARGES | C60: 10077 | D60: =IF(C60="","",IFERROR(INDEX(TB!$B$2:$B$130,MATCH(C60,TB!$A$2:$A$130,0)),"Code not in TB")) -> Slot Charges- Inc | E60: COGS | F60: Mapped – ties to TB | G60: Credit of 712.50 belongs to TB 10077 | H60: =IF(B60="","",COUNTIF('Revenue Ledger'!$S$2:$S$4500,B60)+COUNTIF('COGS Ledger'!$S$2:$S$400,B60)+COUNTIF('Expense Ledger'!$S$2:$S$800,B60)) -> 1
A61: 56 | B61: SLOT CHARGES- EXP | C61: 10077 | D61: =IF(C61="","",IFERROR(INDEX(TB!$B$2:$B$130,MATCH(C61,TB!$A$2:$A$130,0)),"Code not in TB")) -> Slot Charges- Inc | E61: COGS | F61: Mapped – ties to TB | G61: Debits tie to TB 10077 | H61: =IF(B61="","",COUNTIF('Revenue Ledger'!$S$2:$S$4500,B61)+COUNTIF('COGS Ledger'!$S$2:$S$400,B61)+COUNTIF('Expense Ledger'!$S$2:$S$800,B61)) -> 1
A62: 57 | B62: STORAGE CHARGES - EXP | C62: 10062 | D62: =IF(C62="","",IFERROR(INDEX(TB!$B$2:$B$130,MATCH(C62,TB!$A$2:$A$130,0)),"Code not in TB")) -> Storage Charges - Exp | E62: COGS | F62: Exact name match | H62: =IF(B62="","",COUNTIF('Revenue Ledger'!$S$2:$S$4500,B62)+COUNTIF('COGS Ledger'!$S$2:$S$400,B62)+COUNTIF('Expense Ledger'!$S$2:$S$800,B62)) -> 2
A63: 58 | B63: SURVEY CHARGES | C63: 10082 | D63: =IF(C63="","",IFERROR(INDEX(TB!$B$2:$B$130,MATCH(C63,TB!$A$2:$A$130,0)),"Code not in TB")) -> Survey Charges | E63: COGS | F63: Exact name match | H63: =IF(B63="","",COUNTIF('Revenue Ledger'!$S$2:$S$4500,B63)+COUNTIF('COGS Ledger'!$S$2:$S$400,B63)+COUNTIF('Expense Ledger'!$S$2:$S$800,B63)) -> 3
A64: 59 | B64: W/O EXPENSES | C64: 10088 | D64: =IF(C64="","",IFERROR(INDEX(TB!$B$2:$B$130,MATCH(C64,TB!$A$2:$A$130,0)),"Code not in TB")) -> W/O Expenses | E64: COGS | F64: Exact name match | H64: =IF(B64="","",COUNTIF('Revenue Ledger'!$S$2:$S$4500,B64)+COUNTIF('COGS Ledger'!$S$2:$S$400,B64)+COUNTIF('Expense Ledger'!$S$2:$S$800,B64)) -> 7
A65: 60 | B65: EXPENSE Forwarding | C65: 10089 | D65: =IF(C65="","",IFERROR(INDEX(TB!$B$2:$B$130,MATCH(C65,TB!$A$2:$A$130,0)),"Code not in TB")) -> Expense Forwarding | E65: COGS | F65: Exact name match | H65: =IF(B65="","",COUNTIF('Revenue Ledger'!$S$2:$S$4500,B65)+COUNTIF('COGS Ledger'!$S$2:$S$400,B65)+COUNTIF('Expense Ledger'!$S$2:$S$800,B65)) -> 1
A66: 61 | B66: EXPENSE-SEA FREIGHT EXPORT FCL | C66: 10090 | D66: =IF(C66="","",IFERROR(INDEX(TB!$B$2:$B$130,MATCH(C66,TB!$A$2:$A$130,0)),"Code not in TB")) -> Expense-Sea Freight Export Fcl | E66: COGS | F66: Exact name match | H66: =IF(B66="","",COUNTIF('Revenue Ledger'!$S$2:$S$4500,B66)+COUNTIF('COGS Ledger'!$S$2:$S$400,B66)+COUNTIF('Expense Ledger'!$S$2:$S$800,B66)) -> 6
A67: 62 | B67: Preliminary expense | D67: =IF(C67="","",IFERROR(INDEX(TB!$B$2:$B$130,MATCH(C67,TB!$A$2:$A$130,0)),"Code not in TB")) | E67: Expenses | F67: No TB account – confirm | G67: No TB account; TB 10121 Incorporation Expense is nil | H67: =IF(B67="","",COUNTIF('Revenue Ledger'!$S$2:$S$4500,B67)+COUNTIF('COGS Ledger'!$S$2:$S$400,B67)+COUNTIF('Expense Ledger'!$S$2:$S$800,B67)) -> 1
A68: 63 | B68: SALARY & ALLOWANCES | C68: 10115 | D68: =IF(C68="","",IFERROR(INDEX(TB!$B$2:$B$130,MATCH(C68,TB!$A$2:$A$130,0)),"Code not in TB")) -> Salary & Allowances | E68: Expenses | F68: Exact name match | H68: =IF(B68="","",COUNTIF('Revenue Ledger'!$S$2:$S$4500,B68)+COUNTIF('COGS Ledger'!$S$2:$S$400,B68)+COUNTIF('Expense Ledger'!$S$2:$S$800,B68)) -> 39
A69: 64 | B69: DEPRECIATION- OFFICE INTERIORS | C69: 10123 | D69: =IF(C69="","",IFERROR(INDEX(TB!$B$2:$B$130,MATCH(C69,TB!$A$2:$A$130,0)),"Code not in TB")) -> Depreciation Expense | E69: Expenses | F69: Mapped – ties to TB | G69: Three depreciation lines together = TB 10123 | H69: =IF(B69="","",COUNTIF('Revenue Ledger'!$S$2:$S$4500,B69)+COUNTIF('COGS Ledger'!$S$2:$S$400,B69)+COUNTIF('Expense Ledger'!$S$2:$S$800,B69)) -> 1
A70: 65 | B70: EOSB Expense | C70: 10117 | D70: =IF(C70="","",IFERROR(INDEX(TB!$B$2:$B$130,MATCH(C70,TB!$A$2:$A$130,0)),"Code not in TB")) -> EOSB Expense | E70: Expenses | F70: Exact name match | H70: =IF(B70="","",COUNTIF('Revenue Ledger'!$S$2:$S$4500,B70)+COUNTIF('COGS Ledger'!$S$2:$S$400,B70)+COUNTIF('Expense Ledger'!$S$2:$S$800,B70)) -> 1
A71: 66 | B71: OFFICE EXPENSES | C71: 10104 | D71: =IF(C71="","",IFERROR(INDEX(TB!$B$2:$B$130,MATCH(C71,TB!$A$2:$A$130,0)),"Code not in TB")) -> Office Expenses | E71: Expenses | F71: Exact name match | H71: =IF(B71="","",COUNTIF('Revenue Ledger'!$S$2:$S$4500,B71)+COUNTIF('COGS Ledger'!$S$2:$S$400,B71)+COUNTIF('Expense Ledger'!$S$2:$S$800,B71)) -> 26
A72: 67 | B72: Zakat & Tax Expense | C72: 10109 | D72: =IF(C72="","",IFERROR(INDEX(TB!$B$2:$B$130,MATCH(C72,TB!$A$2:$A$130,0)),"Code not in TB")) -> Zakat Fees | E72: Expenses | F72: Proposed – confirm | G72: TB 10109 Zakat Fees; this line is not in the TB amount | H72: =IF(B72="","",COUNTIF('Revenue Ledger'!$S$2:$S$4500,B72)+COUNTIF('COGS Ledger'!$S$2:$S$400,B72)+COUNTIF('Expense Ledger'!$S$2:$S$800,B72)) -> 1
A73: 68 | B73: Audit Fee | C73: 10119 | D73: =IF(C73="","",IFERROR(INDEX(TB!$B$2:$B$130,MATCH(C73,TB!$A$2:$A$130,0)),"Code not in TB")) -> Audit Fee | E73: Expenses | F73: Exact name match | H73: =IF(B73="","",COUNTIF('Revenue Ledger'!$S$2:$S$4500,B73)+COUNTIF('COGS Ledger'!$S$2:$S$400,B73)+COUNTIF('Expense Ledger'!$S$2:$S$800,B73)) -> 1
A74: 69 | B74: RENT- OFFICE | C74: 10114 | D74: =IF(C74="","",IFERROR(INDEX(TB!$B$2:$B$130,MATCH(C74,TB!$A$2:$A$130,0)),"Code not in TB")) -> Rent- Office | E74: Expenses | F74: Exact name match | H74: =IF(B74="","",COUNTIF('Revenue Ledger'!$S$2:$S$4500,B74)+COUNTIF('COGS Ledger'!$S$2:$S$400,B74)+COUNTIF('Expense Ledger'!$S$2:$S$800,B74)) -> 12
A75: 70 | B75: SADAD PAYMENTS | C75: 10096 | D75: =IF(C75="","",IFERROR(INDEX(TB!$B$2:$B$130,MATCH(C75,TB!$A$2:$A$130,0)),"Code not in TB")) -> Sadad Payments | E75: Expenses | F75: Exact name match | H75: =IF(B75="","",COUNTIF('Revenue Ledger'!$S$2:$S$4500,B75)+COUNTIF('COGS Ledger'!$S$2:$S$400,B75)+COUNTIF('Expense Ledger'!$S$2:$S$800,B75)) -> 36
A76: 71 | B76: IQAMA EXPENSES | C76: 10098 | D76: =IF(C76="","",IFERROR(INDEX(TB!$B$2:$B$130,MATCH(C76,TB!$A$2:$A$130,0)),"Code not in TB")) -> Iqama Expenses | E76: Expenses | F76: Exact name match | H76: =IF(B76="","",COUNTIF('Revenue Ledger'!$S$2:$S$4500,B76)+COUNTIF('COGS Ledger'!$S$2:$S$400,B76)+COUNTIF('Expense Ledger'!$S$2:$S$800,B76)) -> 10
A77: 72 | B77: Zakat Fee | C77: 10109 | D77: =IF(C77="","",IFERROR(INDEX(TB!$B$2:$B$130,MATCH(C77,TB!$A$2:$A$130,0)),"Code not in TB")) -> Zakat Fees | E77: Expenses | F77: Proposed – confirm | G77: TB 10109 Zakat Fees; this line is not in the TB amount | H77: =IF(B77="","",COUNTIF('Revenue Ledger'!$S$2:$S$4500,B77)+COUNTIF('COGS Ledger'!$S$2:$S$400,B77)+COUNTIF('Expense Ledger'!$S$2:$S$800,B77)) -> 1
A78: 73 | B78: VISA/RE-ENTRY EXPENSE | C78: 10097 | D78: =IF(C78="","",IFERROR(INDEX(TB!$B$2:$B$130,MATCH(C78,TB!$A$2:$A$130,0)),"Code not in TB")) -> Visa/Re-Entry Expense | E78: Expenses | F78: Exact name match | H78: =IF(B78="","",COUNTIF('Revenue Ledger'!$S$2:$S$4500,B78)+COUNTIF('COGS Ledger'!$S$2:$S$400,B78)+COUNTIF('Expense Ledger'!$S$2:$S$800,B78)) -> 9
A79: 74 | B79: GOSI Expense | C79: 10112 | D79: =IF(C79="","",IFERROR(INDEX(TB!$B$2:$B$130,MATCH(C79,TB!$A$2:$A$130,0)),"Code not in TB")) -> Gosi Payments | E79: Expenses | F79: Proposed – confirm | G79: TB 10112 Gosi Payments; ledger is 111.22 higher than TB | H79: =IF(B79="","",COUNTIF('Revenue Ledger'!$S$2:$S$4500,B79)+COUNTIF('COGS Ledger'!$S$2:$S$400,B79)+COUNTIF('Expense Ledger'!$S$2:$S$800,B79)) -> 25
A80: 75 | B80: UTILITY BILLLS | C80: 10108 | D80: =IF(C80="","",IFERROR(INDEX(TB!$B$2:$B$130,MATCH(C80,TB!$A$2:$A$130,0)),"Code not in TB")) -> Utility Billls | E80: Expenses | F80: Exact name match | H80: =IF(B80="","",COUNTIF('Revenue Ledger'!$S$2:$S$4500,B80)+COUNTIF('COGS Ledger'!$S$2:$S$400,B80)+COUNTIF('Expense Ledger'!$S$2:$S$800,B80)) -> 1
A81: 76 | B81: Other Expense | C81: 10101 | D81: =IF(C81="","",IFERROR(INDEX(TB!$B$2:$B$130,MATCH(C81,TB!$A$2:$A$130,0)),"Code not in TB")) -> Other Expense | E81: Expenses | F81: Exact name match | H81: =IF(B81="","",COUNTIF('Revenue Ledger'!$S$2:$S$4500,B81)+COUNTIF('COGS Ledger'!$S$2:$S$400,B81)+COUNTIF('Expense Ledger'!$S$2:$S$800,B81)) -> 2
A82: 77 | B82: Salary and Allowance | C82: 10115 | D82: =IF(C82="","",IFERROR(INDEX(TB!$B$2:$B$130,MATCH(C82,TB!$A$2:$A$130,0)),"Code not in TB")) -> Salary & Allowances | E82: Expenses | F82: Proposed – confirm | G82: TB 10115 Salary & Allowances; this line is not in the TB amount | H82: =IF(B82="","",COUNTIF('Revenue Ledger'!$S$2:$S$4500,B82)+COUNTIF('COGS Ledger'!$S$2:$S$400,B82)+COUNTIF('Expense Ledger'!$S$2:$S$800,B82)) -> 5
A83: 78 | B83: DEPRECIATION-COMPUTERS | C83: 10123 | D83: =IF(C83="","",IFERROR(INDEX(TB!$B$2:$B$130,MATCH(C83,TB!$A$2:$A$130,0)),"Code not in TB")) -> Depreciation Expense | E83: Expenses | F83: Mapped – ties to TB | G83: Three depreciation lines together = TB 10123 | H83: =IF(B83="","",COUNTIF('Revenue Ledger'!$S$2:$S$4500,B83)+COUNTIF('COGS Ledger'!$S$2:$S$400,B83)+COUNTIF('Expense Ledger'!$S$2:$S$800,B83)) -> 1
A84: 79 | B84: ZAKAT FEES | C84: 10109 | D84: =IF(C84="","",IFERROR(INDEX(TB!$B$2:$B$130,MATCH(C84,TB!$A$2:$A$130,0)),"Code not in TB")) -> Zakat Fees | E84: Expenses | F84: Exact name match | H84: =IF(B84="","",COUNTIF('Revenue Ledger'!$S$2:$S$4500,B84)+COUNTIF('COGS Ledger'!$S$2:$S$400,B84)+COUNTIF('Expense Ledger'!$S$2:$S$800,B84)) -> 1
A85: 80 | B85: TRAVEL EXPENSE | C85: 10105 | D85: =IF(C85="","",IFERROR(INDEX(TB!$B$2:$B$130,MATCH(C85,TB!$A$2:$A$130,0)),"Code not in TB")) -> Travel Expense | E85: Expenses | F85: Exact name match | H85: =IF(B85="","",COUNTIF('Revenue Ledger'!$S$2:$S$4500,B85)+COUNTIF('COGS Ledger'!$S$2:$S$400,B85)+COUNTIF('Expense Ledger'!$S$2:$S$800,B85)) -> 11
A86: 81 | B86: CONSULTATION CHARGES | C86: 10106 | D86: =IF(C86="","",IFERROR(INDEX(TB!$B$2:$B$130,MATCH(C86,TB!$A$2:$A$130,0)),"Code not in TB")) -> Consultation Charges | E86: Expenses | F86: Exact name match | H86: =IF(B86="","",COUNTIF('Revenue Ledger'!$S$2:$S$4500,B86)+COUNTIF('COGS Ledger'!$S$2:$S$400,B86)+COUNTIF('Expense Ledger'!$S$2:$S$800,B86)) -> 1
A87: 82 | B87: QIWA EXPENSE | C87: 10095 | D87: =IF(C87="","",IFERROR(INDEX(TB!$B$2:$B$130,MATCH(C87,TB!$A$2:$A$130,0)),"Code not in TB")) -> Qiwa Expense | E87: Expenses | F87: Exact name match | H87: =IF(B87="","",COUNTIF('Revenue Ledger'!$S$2:$S$4500,B87)+COUNTIF('COGS Ledger'!$S$2:$S$400,B87)+COUNTIF('Expense Ledger'!$S$2:$S$800,B87)) -> 1
A88: 83 | B88: DEPRECIATIN- SOFTWARE | C88: 10123 | D88: =IF(C88="","",IFERROR(INDEX(TB!$B$2:$B$130,MATCH(C88,TB!$A$2:$A$130,0)),"Code not in TB")) -> Depreciation Expense | E88: Expenses | F88: Mapped – ties to TB | G88: Three depreciation lines together = TB 10123 | H88: =IF(B88="","",COUNTIF('Revenue Ledger'!$S$2:$S$4500,B88)+COUNTIF('COGS Ledger'!$S$2:$S$400,B88)+COUNTIF('Expense Ledger'!$S$2:$S$800,B88)) -> 1
A89: 84 | B89: GENERAL EXPENSES | C89: 10100 | D89: =IF(C89="","",IFERROR(INDEX(TB!$B$2:$B$130,MATCH(C89,TB!$A$2:$A$130,0)),"Code not in TB")) -> General Expenses | E89: Expenses | F89: Exact name match | H89: =IF(B89="","",COUNTIF('Revenue Ledger'!$S$2:$S$4500,B89)+COUNTIF('COGS Ledger'!$S$2:$S$400,B89)+COUNTIF('Expense Ledger'!$S$2:$S$800,B89)) -> 7
A90: 85 | B90: CR RENEWAL | C90: 10094 | D90: =IF(C90="","",IFERROR(INDEX(TB!$B$2:$B$130,MATCH(C90,TB!$A$2:$A$130,0)),"Code not in TB")) -> Cr Renewal | E90: Expenses | F90: Exact name match | H90: =IF(B90="","",COUNTIF('Revenue Ledger'!$S$2:$S$4500,B90)+COUNTIF('COGS Ledger'!$S$2:$S$400,B90)+COUNTIF('Expense Ledger'!$S$2:$S$800,B90)) -> 2
A91: 86 | B91: MOBILE & INTERNET EXPENSE | C91: 10113 | D91: =IF(C91="","",IFERROR(INDEX(TB!$B$2:$B$130,MATCH(C91,TB!$A$2:$A$130,0)),"Code not in TB")) -> Mobile & Internet Expense | E91: Expenses | F91: Exact name match | H91: =IF(B91="","",COUNTIF('Revenue Ledger'!$S$2:$S$4500,B91)+COUNTIF('COGS Ledger'!$S$2:$S$400,B91)+COUNTIF('Expense Ledger'!$S$2:$S$800,B91)) -> 8
A92: 87 | B92: Bank Charges | C92: 10092 | D92: =IF(C92="","",IFERROR(INDEX(TB!$B$2:$B$130,MATCH(C92,TB!$A$2:$A$130,0)),"Code not in TB")) -> Bank Charges | E92: Expenses | F92: Exact name match | H92: =IF(B92="","",COUNTIF('Revenue Ledger'!$S$2:$S$4500,B92)+COUNTIF('COGS Ledger'!$S$2:$S$400,B92)+COUNTIF('Expense Ledger'!$S$2:$S$800,B92)) -> 67
A93: 88 | B93: STATIONERY | C93: 10116 | D93: =IF(C93="","",IFERROR(INDEX(TB!$B$2:$B$130,MATCH(C93,TB!$A$2:$A$130,0)),"Code not in TB")) -> Stationery | E93: Expenses | F93: Exact name match | H93: =IF(B93="","",COUNTIF('Revenue Ledger'!$S$2:$S$4500,B93)+COUNTIF('COGS Ledger'!$S$2:$S$400,B93)+COUNTIF('Expense Ledger'!$S$2:$S$800,B93)) -> 4
A94: 89 | B94: CLEANING EXPENSE | C94: 10093 | D94: =IF(C94="","",IFERROR(INDEX(TB!$B$2:$B$130,MATCH(C94,TB!$A$2:$A$130,0)),"Code not in TB")) -> Cleaning Expense | E94: Expenses | F94: Exact name match | H94: =IF(B94="","",COUNTIF('Revenue Ledger'!$S$2:$S$4500,B94)+COUNTIF('COGS Ledger'!$S$2:$S$400,B94)+COUNTIF('Expense Ledger'!$S$2:$S$800,B94)) -> 7
A95: 90 | B95: INSURANCE EXPENSE | C95: 10107 | D95: =IF(C95="","",IFERROR(INDEX(TB!$B$2:$B$130,MATCH(C95,TB!$A$2:$A$130,0)),"Code not in TB")) -> Insurance Expense | E95: Expenses | F95: Exact name match | H95: =IF(B95="","",COUNTIF('Revenue Ledger'!$S$2:$S$4500,B95)+COUNTIF('COGS Ledger'!$S$2:$S$400,B95)+COUNTIF('Expense Ledger'!$S$2:$S$800,B95)) -> 9
A96: 91 | B96: Business Promotion | C96: 10122 | D96: =IF(C96="","",IFERROR(INDEX(TB!$B$2:$B$130,MATCH(C96,TB!$A$2:$A$130,0)),"Code not in TB")) -> Business Promotion | E96: Expenses | F96: Exact name match | H96: =IF(B96="","",COUNTIF('Revenue Ledger'!$S$2:$S$4500,B96)+COUNTIF('COGS Ledger'!$S$2:$S$400,B96)+COUNTIF('Expense Ledger'!$S$2:$S$800,B96)) -> 5
A97: 92 | B97: HOTEL ACCOMMODATION EXPENSE | C97: 10102 | D97: =IF(C97="","",IFERROR(INDEX(TB!$B$2:$B$130,MATCH(C97,TB!$A$2:$A$130,0)),"Code not in TB")) -> Hotel Accommodation Expense | E97: Expenses | F97: Exact name match | H97: =IF(B97="","",COUNTIF('Revenue Ledger'!$S$2:$S$4500,B97)+COUNTIF('COGS Ledger'!$S$2:$S$400,B97)+COUNTIF('Expense Ledger'!$S$2:$S$800,B97)) -> 2
A98: 93 | B98: ELECTRICITY & WATER | C98: 10099 | D98: =IF(C98="","",IFERROR(INDEX(TB!$B$2:$B$130,MATCH(C98,TB!$A$2:$A$130,0)),"Code not in TB")) -> Electricity & Water | E98: Expenses | F98: Exact name match | H98: =IF(B98="","",COUNTIF('Revenue Ledger'!$S$2:$S$4500,B98)+COUNTIF('COGS Ledger'!$S$2:$S$400,B98)+COUNTIF('Expense Ledger'!$S$2:$S$800,B98)) -> 3
A99: 94 | B99: CONVEYENCE EXPENSES | C99: 10110 | D99: =IF(C99="","",IFERROR(INDEX(TB!$B$2:$B$130,MATCH(C99,TB!$A$2:$A$130,0)),"Code not in TB")) -> Conveyence Expenses | E99: Expenses | F99: Exact name match | H99: =IF(B99="","",COUNTIF('Revenue Ledger'!$S$2:$S$4500,B99)+COUNTIF('COGS Ledger'!$S$2:$S$400,B99)+COUNTIF('Expense Ledger'!$S$2:$S$800,B99)) -> 1
A100: 95 | B100: Insurance | C100: 10107 | D100: =IF(C100="","",IFERROR(INDEX(TB!$B$2:$B$130,MATCH(C100,TB!$A$2:$A$130,0)),"Code not in TB")) -> Insurance Expense | E100: Expenses | F100: Proposed – confirm | G100: TB 10107 Insurance Expense; this line is not in the TB amount | H100: =IF(B100="","",COUNTIF('Revenue Ledger'!$S$2:$S$4500,B100)+COUNTIF('COGS Ledger'!$S$2:$S$400,B100)+COUNTIF('Expense Ledger'!$S$2:$S$800,B100)) -> 1
A101: 96 | B101: STAFF MEDICAL EXPENSE | C101: 10103 | D101: =IF(C101="","",IFERROR(INDEX(TB!$B$2:$B$130,MATCH(C101,TB!$A$2:$A$130,0)),"Code not in TB")) -> Staff Medical Expense | E101: Expenses | F101: Exact name match | H101: =IF(B101="","",COUNTIF('Revenue Ledger'!$S$2:$S$4500,B101)+COUNTIF('COGS Ledger'!$S$2:$S$400,B101)+COUNTIF('Expense Ledger'!$S$2:$S$800,B101)) -> 2
A102: 97 | B102: Office expense | C102: 10104 | D102: =IF(C102="","",IFERROR(INDEX(TB!$B$2:$B$130,MATCH(C102,TB!$A$2:$A$130,0)),"Code not in TB")) -> Office Expenses | E102: Expenses | F102: Proposed – confirm | G102: TB 10104 Office Expenses; this line is not in the TB amount | H102: =IF(B102="","",COUNTIF('Revenue Ledger'!$S$2:$S$4500,B102)+COUNTIF('COGS Ledger'!$S$2:$S$400,B102)+COUNTIF('Expense Ledger'!$S$2:$S$800,B102)) -> 1
D103: =IF(C103="","",IFERROR(INDEX(TB!$B$2:$B$130,MATCH(C103,TB!$A$2:$A$130,0)),"Code not in TB")) | H103: =IF(B103="","",COUNTIF('Revenue Ledger'!$S$2:$S$4500,B103)+COUNTIF('COGS Ledger'!$S$2:$S$400,B103)+COUNTIF('Expense Ledger'!$S$2:$S$800,B103))
D104: =IF(C104="","",IFERROR(INDEX(TB!$B$2:$B$130,MATCH(C104,TB!$A$2:$A$130,0)),"Code not in TB")) | H104: =IF(B104="","",COUNTIF('Revenue Ledger'!$S$2:$S$4500,B104)+COUNTIF('COGS Ledger'!$S$2:$S$400,B104)+COUNTIF('Expense Ledger'!$S$2:$S$800,B104))
D105: =IF(C105="","",IFERROR(INDEX(TB!$B$2:$B$130,MATCH(C105,TB!$A$2:$A$130,0)),"Code not in TB")) | H105: =IF(B105="","",COUNTIF('Revenue Ledger'!$S$2:$S$4500,B105)+COUNTIF('COGS Ledger'!$S$2:$S$400,B105)+COUNTIF('Expense Ledger'!$S$2:$S$800,B105))
D106: =IF(C106="","",IFERROR(INDEX(TB!$B$2:$B$130,MATCH(C106,TB!$A$2:$A$130,0)),"Code not in TB")) | H106: =IF(B106="","",COUNTIF('Revenue Ledger'!$S$2:$S$4500,B106)+COUNTIF('COGS Ledger'!$S$2:$S$400,B106)+COUNTIF('Expense Ledger'!$S$2:$S$800,B106))
D107: =IF(C107="","",IFERROR(INDEX(TB!$B$2:$B$130,MATCH(C107,TB!$A$2:$A$130,0)),"Code not in TB")) | H107: =IF(B107="","",COUNTIF('Revenue Ledger'!$S$2:$S$4500,B107)+COUNTIF('COGS Ledger'!$S$2:$S$400,B107)+COUNTIF('Expense Ledger'!$S$2:$S$800,B107))
D108: =IF(C108="","",IFERROR(INDEX(TB!$B$2:$B$130,MATCH(C108,TB!$A$2:$A$130,0)),"Code not in TB")) | H108: =IF(B108="","",COUNTIF('Revenue Ledger'!$S$2:$S$4500,B108)+COUNTIF('COGS Ledger'!$S$2:$S$400,B108)+COUNTIF('Expense Ledger'!$S$2:$S$800,B108))
D109: =IF(C109="","",IFERROR(INDEX(TB!$B$2:$B$130,MATCH(C109,TB!$A$2:$A$130,0)),"Code not in TB")) | H109: =IF(B109="","",COUNTIF('Revenue Ledger'!$S$2:$S$4500,B109)+COUNTIF('COGS Ledger'!$S$2:$S$400,B109)+COUNTIF('Expense Ledger'!$S$2:$S$800,B109))
D110: =IF(C110="","",IFERROR(INDEX(TB!$B$2:$B$130,MATCH(C110,TB!$A$2:$A$130,0)),"Code not in TB")) | H110: =IF(B110="","",COUNTIF('Revenue Ledger'!$S$2:$S$4500,B110)+COUNTIF('COGS Ledger'!$S$2:$S$400,B110)+COUNTIF('Expense Ledger'!$S$2:$S$800,B110))
D111: =IF(C111="","",IFERROR(INDEX(TB!$B$2:$B$130,MATCH(C111,TB!$A$2:$A$130,0)),"Code not in TB")) | H111: =IF(B111="","",COUNTIF('Revenue Ledger'!$S$2:$S$4500,B111)+COUNTIF('COGS Ledger'!$S$2:$S$400,B111)+COUNTIF('Expense Ledger'!$S$2:$S$800,B111))
D112: =IF(C112="","",IFERROR(INDEX(TB!$B$2:$B$130,MATCH(C112,TB!$A$2:$A$130,0)),"Code not in TB")) | H112: =IF(B112="","",COUNTIF('Revenue Ledger'!$S$2:$S$4500,B112)+COUNTIF('COGS Ledger'!$S$2:$S$400,B112)+COUNTIF('Expense Ledger'!$S$2:$S$800,B112))
D113: =IF(C113="","",IFERROR(INDEX(TB!$B$2:$B$130,MATCH(C113,TB!$A$2:$A$130,0)),"Code not in TB")) | H113: =IF(B113="","",COUNTIF('Revenue Ledger'!$S$2:$S$4500,B113)+COUNTIF('COGS Ledger'!$S$2:$S$400,B113)+COUNTIF('Expense Ledger'!$S$2:$S$800,B113))
D114: =IF(C114="","",IFERROR(INDEX(TB!$B$2:$B$130,MATCH(C114,TB!$A$2:$A$130,0)),"Code not in TB")) | H114: =IF(B114="","",COUNTIF('Revenue Ledger'!$S$2:$S$4500,B114)+COUNTIF('COGS Ledger'!$S$2:$S$400,B114)+COUNTIF('Expense Ledger'!$S$2:$S$800,B114))
... D205: =IF(C205="","",IFERROR(INDEX(TB!$B$2:$B$130,MATCH(C205,TB!$A$2:$A$130,0)),"Code not in TB")) | H205: =IF(B205="","",COUNTIF('Revenue Ledger'!$S$2:$S$4500,B205)+COUNTIF('COGS Ledger'!$S$2:$S$400,B205)+COUNTIF('Expense Ledger'!$S$2:$S$800,B205))

Sheet Revenue Ledger
A1: Voucher Ref | B1: Date | C1: Ledger Code | D1: Ledger Name | E1: ArAp Ref | F1: Description (Remarks) | G1: Debit | H1: Credit | I1: Original Amount (Dr − Cr) | J1: Absolute Amount | K1: Excluded – account set to Exclude (1 = yes) | L1: Above materiality – selected (1 = yes) | M1: Random No. (fixed) | N1: Possible duplicate | O1: Below-materiality eligible pop. (1 = yes) | P1: Rank key – above | Q1: Rank key – random | R1: Excluded-record key | S1: Account key (trimmed)
A2: DNAMS0025/25 | B2: 45930 | C2: =IF(S2="","",IFERROR(IF(INDEX('Ledger Codes'!$C$6:$C$205,MATCH(S2,'Ledger Codes'!$B$6:$B$205,0))="","",INDEX('Ledger Codes'!$C$6:$C$205,MATCH(S2,'Ledger Codes'!$B$6:$B$205,0))),"")) -> 10069 | D2: AGENCY COMMISSION EXPORT- INC | E2: AGENCY IMPORT COMMISSION- SOA SEP 2025- CAPE CONT UK | F2: AGENCY IMPORT COMMISSION- SOA SEP 2025- CAPE CONT UK | G2: 0 | H2: 20 | I2: =IF(AND(G2="",H2=""),"",N(G2)-N(H2)) -> -20 | J2: =IF(I2="","",ABS(I2)) -> 20 | K2: =IF(S2="","",0) -> 0 | L2: =IF(J2="","",IF(AND(J2>'Revenue Testing'!$E$9,K2=0),1,0)) -> 0 | M2: 0.74713993 | N2: =IF(OR(A2="",I2=""),"",IF(COUNTIFS($A$2:$A$4500,A2,$D$2:$D$4500,D2,$I$2:$I$4500,I2)>1,"Possible duplicate","")) | O2: =IF(J2="","",IF(AND(L2=0,K2=0),1,0)) -> 1 | P2: =IF(L2=1,J2+ROW()/10^7,"") | Q2: =IF(O2=1,M2,"") -> 0.74713993 | R2: =IF(K2=1,ROW(),"") | S2: =IF(D2="","",TRIM(D2)) -> AGENCY COMMISSION EXPORT- INC
A3: DNAMS0026/25 | B3: 45961 | C3: =IF(S3="","",IFERROR(IF(INDEX('Ledger Codes'!$C$6:$C$205,MATCH(S3,'Ledger Codes'!$B$6:$B$205,0))="","",INDEX('Ledger Codes'!$C$6:$C$205,MATCH(S3,'Ledger Codes'!$B$6:$B$205,0))),"")) -> 10069 | D3: AGENCY COMMISSION EXPORT- INC | E3: IMPORT DETENTION COMMISSION FTM OCT 2025- CAPE CONTAINERS UK | F3: IMPORT DETENTION COMMISSION FTM OCT 2025- CAPE CONTAINERS UK AGENCY EXPORT COMMISSION- OCT 2025 AGENCY IMPORT COMMISSION- OCT 2025 | G3: 0 | H3: 20 | I3: =IF(AND(G3="",H3=""),"",N(G3)-N(H3)) -> -20 | J3: =IF(I3="","",ABS(I3)) -> 20 | K3: =IF(S3="","",0) -> 0 | L3: =IF(J3="","",IF(AND(J3>'Revenue Testing'!$E$9,K3=0),1,0)) -> 0 | M3: 0.49935839 | N3: =IF(OR(A3="",I3=""),"",IF(COUNTIFS($A$2:$A$4500,A3,$D$2:$D$4500,D3,$I$2:$I$4500,I3)>1,"Possible duplicate","")) | O3: =IF(J3="","",IF(AND(L3=0,K3=0),1,0)) -> 1 | P3: =IF(L3=1,J3+ROW()/10^7,"") | Q3: =IF(O3=1,M3,"") -> 0.49935839 | R3: =IF(K3=1,ROW(),"") | S3: =IF(D3="","",TRIM(D3)) -> AGENCY COMMISSION EXPORT- INC
A4: DNAMS0027/25 | B4: 45991 | C4: =IF(S4="","",IFERROR(IF(INDEX('Ledger Codes'!$C$6:$C$205,MATCH(S4,'Ledger Codes'!$B$6:$B$205,0))="","",INDEX('Ledger Codes'!$C$6:$C$205,MATCH(S4,'Ledger Codes'!$B$6:$B$205,0))),"")) -> 10069 | D4: AGENCY COMMISSION EXPORT- INC | E4: EXPORT AGENCY COMMISSION- SOA NOV 2025- CAPE CONTAINER UK | F4: EXPORT AGENCY COMMISSION- SOA NOV 2025- CAPE CONTAINER UK AND TRANSPORTATION CHARGES- "TRANSPORTATION CHGS- EMCU5255887 TRIU0777668" JSI-25-4053 | G4: 0 | H4: 80 | I4: =IF(AND(G4="",H4=""),"",N(G4)-N(H4)) -> -80 | J4: =IF(I4="","",ABS(I4)) -> 80 | K4: =IF(S4="","",0) -> 0 | L4: =IF(J4="","",IF(AND(J4>'Revenue Testing'!$E$9,K4=0),1,0)) -> 0 | M4: 0.11101516 | N4: =IF(OR(A4="",I4=""),"",IF(COUNTIFS($A$2:$A$4500,A4,$D$2:$D$4500,D4,$I$2:$I$4500,I4)>1,"Possible duplicate","")) | O4: =IF(J4="","",IF(AND(L4=0,K4=0),1,0)) -> 1 | P4: =IF(L4=1,J4+ROW()/10^7,"") | Q4: =IF(O4=1,M4,"") -> 0.11101516 | R4: =IF(K4=1,ROW(),"") | S4: =IF(D4="","",TRIM(D4)) -> AGENCY COMMISSION EXPORT- INC
A5: DNAMS0028/25 | B5: 46022 | C5: =IF(S5="","",IFERROR(IF(INDEX('Ledger Codes'!$C$6:$C$205,MATCH(S5,'Ledger Codes'!$B$6:$B$205,0))="","",INDEX('Ledger Codes'!$C$6:$C$205,MATCH(S5,'Ledger Codes'!$B$6:$B$205,0))),"")) -> 10069 | D5: AGENCY COMMISSION EXPORT- INC | E5: AGENCY COMMISSION FTM DEC 2025- CAPE CONATINERS UK | F5: AGENCY COMMISSION FTM DEC 2025- CAPE CONATINERS UK | G5: 0 | H5: 20 | I5: =IF(AND(G5="",H5=""),"",N(G5)-N(H5)) -> -20 | J5: =IF(I5="","",ABS(I5)) -> 20 | K5: =IF(S5="","",0) -> 0 | L5: =IF(J5="","",IF(AND(J5>'Revenue Testing'!$E$9,K5=0),1,0)) -> 0 | M5: 0.54971743 | N5: =IF(OR(A5="",I5=""),"",IF(COUNTIFS($A$2:$A$4500,A5,$D$2:$D$4500,D5,$I$2:$I$4500,I5)>1,"Possible duplicate","")) | O5: =IF(J5="","",IF(AND(L5=0,K5=0),1,0)) -> 1 | P5: =IF(L5=1,J5+ROW()/10^7,"") | Q5: =IF(O5=1,M5,"") -> 0.54971743 | R5: =IF(K5=1,ROW(),"") | S5: =IF(D5="","",TRIM(D5)) -> AGENCY COMMISSION EXPORT- INC
A6: DNAMS0024/25 | B6: 45900 | C6: =IF(S6="","",IFERROR(IF(INDEX('Ledger Codes'!$C$6:$C$205,MATCH(S6,'Ledger Codes'!$B$6:$B$205,0))="","",INDEX('Ledger Codes'!$C$6:$C$205,MATCH(S6,'Ledger Codes'!$B$6:$B$205,0))),"")) -> 10069 | D6: AGENCY COMMISSION IMPORT- INC | E6: IMPORT AGENCY COMMISSION- SOA AUG 2025 | F6: IMPORT AGENCY COMMISSION- SOA AUG 2025 | G6: 0 | H6: 300 | I6: =IF(AND(G6="",H6=""),"",N(G6)-N(H6)) -> -300 | J6: =IF(I6="","",ABS(I6)) -> 300 | K6: =IF(S6="","",0) -> 0 | L6: =IF(J6="","",IF(AND(J6>'Revenue Testing'!$E$9,K6=0),1,0)) -> 0 | M6: 0.24180374 | N6: =IF(OR(A6="",I6=""),"",IF(COUNTIFS($A$2:$A$4500,A6,$D$2:$D$4500,D6,$I$2:$I$4500,I6)>1,"Possible duplicate","")) | O6: =IF(J6="","",IF(AND(L6=0,K6=0),1,0)) -> 1 | P6: =IF(L6=1,J6+ROW()/10^7,"") | Q6: =IF(O6=1,M6,"") -> 0.24180374 | R6: =IF(K6=1,ROW(),"") | S6: =IF(D6="","",TRIM(D6)) -> AGENCY COMMISSION IMPORT- INC
A7: DNAMS0012/25 | B7: 45930 | C7: =IF(S7="","",IFERROR(IF(INDEX('Ledger Codes'!$C$6:$C$205,MATCH(S7,'Ledger Codes'!$B$6:$B$205,0))="","",INDEX('Ledger Codes'!$C$6:$C$205,MATCH(S7,'Ledger Codes'!$B$6:$B$205,0))),"")) -> 10069 | D7: AGENCY COMMISSION IMPORT- INC | E7: IMPORT AGENCY COMMISSION- SEP 2025 | F7: IMPORT AGENCY COMMISSION- SEP 2025- CSTAR | G7: 0 | H7: 15525 | I7: =IF(AND(G7="",H7=""),"",N(G7)-N(H7)) -> -15525 | J7: =IF(I7="","",ABS(I7)) -> 15525 | K7: =IF(S7="","",0) -> 0 | L7: =IF(J7="","",IF(AND(J7>'Revenue Testing'!$E$9,K7=0),1,0)) -> 1 | M7: 0.53334083 | N7: =IF(OR(A7="",I7=""),"",IF(COUNTIFS($A$2:$A$4500,A7,$D$2:$D$4500,D7,$I$2:$I$4500,I7)>1,"Possible duplicate","")) | O7: =IF(J7="","",IF(AND(L7=0,K7=0),1,0)) -> 0 | P7: =IF(L7=1,J7+ROW()/10^7,"") -> 15525 | Q7: =IF(O7=1,M7,"") | R7: =IF(K7=1,ROW(),"") | S7: =IF(D7="","",TRIM(D7)) -> AGENCY COMMISSION IMPORT- INC
A8: DNAMS0025/25 | B8: 45930 | C8: =IF(S8="","",IFERROR(IF(INDEX('Ledger Codes'!$C$6:$C$205,MATCH(S8,'Ledger Codes'!$B$6:$B$205,0))="","",INDEX('Ledger Codes'!$C$6:$C$205,MATCH(S8,'Ledger Codes'!$B$6:$B$205,0))),"")) -> 10069 | D8: AGENCY COMMISSION IMPORT- INC | E8: AGENCY IMPORT COMMISSION- SOA SEP 2025- CAPE CONT UK | F8: AGENCY IMPORT COMMISSION- SOA SEP 2025- CAPE CONT UK | G8: 0 | H8: 375 | I8: =IF(AND(G8="",H8=""),"",N(G8)-N(H8)) -> -375 | J8: =IF(I8="","",ABS(I8)) -> 375 | K8: =IF(S8="","",0) -> 0 | L8: =IF(J8="","",IF(AND(J8>'Revenue Testing'!$E$9,K8=0),1,0)) -> 0 | M8: 0.99680177 | N8: =IF(OR(A8="",I8=""),"",IF(COUNTIFS($A$2:$A$4500,A8,$D$2:$D$4500,D8,$I$2:$I$4500,I8)>1,"Possible duplicate","")) | O8: =IF(J8="","",IF(AND(L8=0,K8=0),1,0)) -> 1 | P8: =IF(L8=1,J8+ROW()/10^7,"") | Q8: =IF(O8=1,M8,"") -> 0.99680177 | R8: =IF(K8=1,ROW(),"") | S8: =IF(D8="","",TRIM(D8)) -> AGENCY COMMISSION IMPORT- INC
A9: DNAMS0014/25 | B9: 45961 | C9: =IF(S9="","",IFERROR(IF(INDEX('Ledger Codes'!$C$6:$C$205,MATCH(S9,'Ledger Codes'!$B$6:$B$205,0))="","",INDEX('Ledger Codes'!$C$6:$C$205,MATCH(S9,'Ledger Codes'!$B$6:$B$205,0))),"")) -> 10069 | D9: AGENCY COMMISSION IMPORT- INC | E9: IMPORT AGENCY COMMISSION- OCT 2025 | F9: IMPORT AGENCY COMMISSION- OCT 2025- CSTAR | G9: 0 | H9: 14250 | I9: =IF(AND(G9="",H9=""),"",N(G9)-N(H9)) -> -14250 | J9: =IF(I9="","",ABS(I9)) -> 14250 | K9: =IF(S9="","",0) -> 0 | L9: =IF(J9="","",IF(AND(J9>'Revenue Testing'!$E$9,K9=0),1,0)) -> 1 | M9: 0.53873675 | N9: =IF(OR(A9="",I9=""),"",IF(COUNTIFS($A$2:$A$4500,A9,$D$2:$D$4500,D9,$I$2:$I$4500,I9)>1,"Possible duplicate","")) | O9: =IF(J9="","",IF(AND(L9=0,K9=0),1,0)) -> 0 | P9: =IF(L9=1,J9+ROW()/10^7,"") -> 14250 | Q9: =IF(O9=1,M9,"") | R9: =IF(K9=1,ROW(),"") | S9: =IF(D9="","",TRIM(D9)) -> AGENCY COMMISSION IMPORT- INC
A10: DNAMS0018/25 | B10: 45991 | C10: =IF(S10="","",IFERROR(IF(INDEX('Ledger Codes'!$C$6:$C$205,MATCH(S10,'Ledger Codes'!$B$6:$B$205,0))="","",INDEX('Ledger Codes'!$C$6:$C$205,MATCH(S10,'Ledger Codes'!$B$6:$B$205,0))),"")) -> 10069 | D10: AGENCY COMMISSION IMPORT- INC | E10: IMPORT AGENCY COMMISSION- NOV 2025 | F10: IMPORT AGENCY COMMISSION- NOV 2025- CSTAR | G10: 0 | H10: 3637.5 | I10: =IF(AND(G10="",H10=""),"",N(G10)-N(H10)) -> -3637.5 | J10: =IF(I10="","",ABS(I10)) -> 3637.5 | K10: =IF(S10="","",0) -> 0 | L10: =IF(J10="","",IF(AND(J10>'Revenue Testing'!$E$9,K10=0),1,0)) -> 0 | M10: 0.042012031 | N10: =IF(OR(A10="",I10=""),"",IF(COUNTIFS($A$2:$A$4500,A10,$D$2:$D$4500,D10,$I$2:$I$4500,I10)>1,"Possible duplicate","")) | O10: =IF(J10="","",IF(AND(L10=0,K10=0),1,0)) -> 1 | P10: =IF(L10=1,J10+ROW()/10^7,"") | Q10: =IF(O10=1,M10,"") -> 0.042012031 | R10: =IF(K10=1,ROW(),"") | S10: =IF(D10="","",TRIM(D10)) -> AGENCY COMMISSION IMPORT- INC
A11: DNAMS0004/25 | B11: 46022 | C11: =IF(S11="","",IFERROR(IF(INDEX('Ledger Codes'!$C$6:$C$205,MATCH(S11,'Ledger Codes'!$B$6:$B$205,0))="","",INDEX('Ledger Codes'!$C$6:$C$205,MATCH(S11,'Ledger Codes'!$B$6:$B$205,0))),"")) -> 10069 | D11: AGENCY COMMISSION IMPORT- INC | E11: DR-ALMJDH/00002/202512 | F11: TIME LOG- ASL SHEKOU - ASLS02548E- 1X20' LADEN- AGENCY COMMISSION, SLOT CHARGES, AGENCY RECOVERY CHARGES, DETEMTION CHARGES & COMMISSION | G11: 0 | H11: 75 | I11: =IF(AND(G11="",H11=""),"",N(G11)-N(H11)) -> -75 | J11: =IF(I11="","",ABS(I11)) -> 75 | K11: =IF(S11="","",0) -> 0 | L11: =IF(J11="","",IF(AND(J11>'Revenue Testing'!$E$9,K11=0),1,0)) -> 0 | M11: 0.17742278 | N11: =IF(OR(A11="",I11=""),"",IF(COUNTIFS($A$2:$A$4500,A11,$D$2:$D$4500,D11,$I$2:$I$4500,I11)>1,"Possible duplicate","")) | O11: =IF(J11="","",IF(AND(L11=0,K11=0),1,0)) -> 1 | P11: =IF(L11=1,J11+ROW()/10^7,"") | Q11: =IF(O11=1,M11,"") -> 0.17742278 | R11: =IF(K11=1,ROW(),"") | S11: =IF(D11="","",TRIM(D11)) -> AGENCY COMMISSION IMPORT- INC
A12: DNAMS0028/25 | B12: 46022 | C12: =IF(S12="","",IFERROR(IF(INDEX('Ledger Codes'!$C$6:$C$205,MATCH(S12,'Ledger Codes'!$B$6:$B$205,0))="","",INDEX('Ledger Codes'!$C$6:$C$205,MATCH(S12,'Ledger Codes'!$B$6:$B$205,0))),"")) -> 10069 | D12: AGENCY COMMISSION IMPORT- INC | E12: AGENCY COMMISSION FTM DEC 2025- CAPE CONATINERS UK | F12: AGENCY COMMISSION FTM DEC 2025- CAPE CONATINERS UK | G12: 0 | H12: 150 | I12: =IF(AND(G12="",H12=""),"",N(G12)-N(H12)) -> -150 | J12: =IF(I12="","",ABS(I12)) -> 150 | K12: =IF(S12="","",0) -> 0 | L12: =IF(J12="","",IF(AND(J12>'Revenue Testing'!$E$9,K12=0),1,0)) -> 0 | M12: 0.89911643 | N12: =IF(OR(A12="",I12=""),"",IF(COUNTIFS($A$2:$A$4500,A12,$D$2:$D$4500,D12,$I$2:$I$4500,I12)>1,"Possible duplicate","")) | O12: =IF(J12="","",IF(AND(L12=0,K12=0),1,0)) -> 1 | P12: =IF(L12=1,J12+ROW()/10^7,"") | Q12: =IF(O12=1,M12,"") -> 0.89911643 | R12: =IF(K12=1,ROW(),"") | S12: =IF(D12="","",TRIM(D12)) -> AGENCY COMMISSION IMPORT- INC
A13: DNAMS0013/25 | B13: 45930 | C13: =IF(S13="","",IFERROR(IF(INDEX('Ledger Codes'!$C$6:$C$205,MATCH(S13,'Ledger Codes'!$B$6:$B$205,0))="","",INDEX('Ledger Codes'!$C$6:$C$205,MATCH(S13,'Ledger Codes'!$B$6:$B$205,0))),"")) -> 10070 | D13: AGENCY COMMISSION- T/S HANDLING | E13: T/S AGENCY COMMISSION- SEP 2025 | F13: T/S AGENCY COMMISSION- SEP 2025- CSTAR | G13: 0 | H13: 11756.25 | I13: =IF(AND(G13="",H13=""),"",N(G13)-N(H13)) -> -11756.25 | J13: =IF(I13="","",ABS(I13)) -> 11756.25 | K13: =IF(S13="","",0) -> 0 | L13: =IF(J13="","",IF(AND(J13>'Revenue Testing'!$E$9,K13=0),1,0)) -> 1 | M13: 0.1545322 | N13: =IF(OR(A13="",I13=""),"",IF(COUNTIFS($A$2:$A$4500,A13,$D$2:$D$4500,D13,$I$2:$I$4500,I13)>1,"Possible duplicate","")) | O13: =IF(J13="","",IF(AND(L13=0,K13=0),1,0)) -> 0 | P13: =IF(L13=1,J13+ROW()/10^7,"") -> 11756.25 | Q13: =IF(O13=1,M13,"") | R13: =IF(K13=1,ROW(),"") | S13: =IF(D13="","",TRIM(D13)) -> AGENCY COMMISSION- T/S HANDLING
... A3915: GJAMS0089/25 | B3915: 46022 | C3915: =IF(S3915="","",IFERROR(IF(INDEX('Ledger Codes'!$C$6:$C$205,MATCH(S3915,'Ledger Codes'!$B$6:$B$205,0))="","",INDEX('Ledger Codes'!$C$6:$C$205,MATCH(S3915,'Ledger Codes'!$B$6:$B$205,0))),"")) -> 10059 | D3915: INCOME-SEA FREIGHT EXPORT FCL | E3915: 000007/25 | F3915: Service : SEA FREIGHT EXPORT FCL | G3915: 0 | H3915: 165750 | I3915: =IF(AND(G3915="",H3915=""),"",N(G3915)-N(H3915)) -> -165750 | J3915: =IF(I3915="","",ABS(I3915)) -> 165750 | K3915: =IF(S3915="","",0) -> 0 | L3915: =IF(J3915="","",IF(AND(J3915>'Revenue Testing'!$E$9,K3915=0),1,0)) -> 1 | M3915: 0.13358104 | N3915: =IF(OR(A3915="",I3915=""),"",IF(COUNTIFS($A$2:$A$4500,A3915,$D$2:$D$4500,D3915,$I$2:$I$4500,I3915)>1,"Possible duplicate","")) | O3915: =IF(J3915="","",IF(AND(L3915=0,K3915=0),1,0)) -> 0 | P3915: =IF(L3915=1,J3915+ROW()/10^7,"") -> 165750 | Q3915: =IF(O3915=1,M3915,"") | R3915: =IF(K3915=1,ROW(),"") | S3915: =IF(D3915="","",TRIM(D3915)) -> INCOME-SEA FREIGHT EXPORT FCL
A3916: GJAMS0074/25 | B3916: 45900 | C3916: =IF(S3916="","",IFERROR(IF(INDEX('Ledger Codes'!$C$6:$C$205,MATCH(S3916,'Ledger Codes'!$B$6:$B$205,0))="","",INDEX('Ledger Codes'!$C$6:$C$205,MATCH(S3916,'Ledger Codes'!$B$6:$B$205,0))),"")) -> 10083 | D3916: MISCELLANEOUS INCOME | F3916: PROFIT- SAR 237.5 FROM ALLIED CONTAINER LINE ON FREIGHT FORWARDING DURING AUG 2025 CHARGED OFRT USD 650 WHEREAS SAFEEN FEEDERS CHARGED USD 600 PTI CHARGED SAR 200- FREIGHT WORLD SAR 150 PER CONT USD 50*3.75- SAR 187.5 SAR 200- SAR 150 -SAR 50 TOTAL SAR 237.5 | G3916: 0 | H3916: 237.5 | I3916: =IF(AND(G3916="",H3916=""),"",N(G3916)-N(H3916)) -> -237.5 | J3916: =IF(I3916="","",ABS(I3916)) -> 237.5 | K3916: =IF(S3916="","",0) -> 0 | L3916: =IF(J3916="","",IF(AND(J3916>'Revenue Testing'!$E$9,K3916=0),1,0)) -> 0 | M3916: 0.39909215 | N3916: =IF(OR(A3916="",I3916=""),"",IF(COUNTIFS($A$2:$A$4500,A3916,$D$2:$D$4500,D3916,$I$2:$I$4500,I3916)>1,"Possible duplicate","")) | O3916: =IF(J3916="","",IF(AND(L3916=0,K3916=0),1,0)) -> 1 | P3916: =IF(L3916=1,J3916+ROW()/10^7,"") | Q3916: =IF(O3916=1,M3916,"") -> 0.39909215 | R3916: =IF(K3916=1,ROW(),"") | S3916: =IF(D3916="","",TRIM(D3916)) -> MISCELLANEOUS INCOME
A3917: DNAMS0034/25 | B3917: 45900 | C3917: =IF(S3917="","",IFERROR(IF(INDEX('Ledger Codes'!$C$6:$C$205,MATCH(S3917,'Ledger Codes'!$B$6:$B$205,0))="","",INDEX('Ledger Codes'!$C$6:$C$205,MATCH(S3917,'Ledger Codes'!$B$6:$B$205,0))),"")) -> 10083 | D3917: MISCELLANEOUS INCOME | E3917: BALTIC- OFRT | F3917: OFRT AGREED ON BALTIC- SAR 121500 ACTUAL COST INCURRED AS PER INVOICES RECEIVED- SAR 89391 AGREED EMAIL AND CONFIRMATION OF COST BY MR MOHTISIM AND MR MAHESH AND MR SIDDIQUI IE SAR 92730 REMAINING BALANCE- AL MANARA PROFIT- SAR | G3917: 0 | H3917: 3339 | I3917: =IF(AND(G3917="",H3917=""),"",N(G3917)-N(H3917)) -> -3339 | J3917: =IF(I3917="","",ABS(I3917)) -> 3339 | K3917: =IF(S3917="","",0) -> 0 | L3917: =IF(J3917="","",IF(AND(J3917>'Revenue Testing'!$E$9,K3917=0),1,0)) -> 0 | M3917: 0.42678846 | N3917: =IF(OR(A3917="",I3917=""),"",IF(COUNTIFS($A$2:$A$4500,A3917,$D$2:$D$4500,D3917,$I$2:$I$4500,I3917)>1,"Possible duplicate","")) | O3917: =IF(J3917="","",IF(AND(L3917=0,K3917=0),1,0)) -> 1 | P3917: =IF(L3917=1,J3917+ROW()/10^7,"") | Q3917: =IF(O3917=1,M3917,"") -> 0.42678846 | R3917: =IF(K3917=1,ROW(),"") | S3917: =IF(D3917="","",TRIM(D3917)) -> MISCELLANEOUS INCOME
A3918: GJAMS0092/25 | B3918: 45900 | C3918: =IF(S3918="","",IFERROR(IF(INDEX('Ledger Codes'!$C$6:$C$205,MATCH(S3918,'Ledger Codes'!$B$6:$B$205,0))="","",INDEX('Ledger Codes'!$C$6:$C$205,MATCH(S3918,'Ledger Codes'!$B$6:$B$205,0))),"")) -> 10083 | D3918: MISCELLANEOUS INCOME | E3918: REVERSAL OF GJAMS0074- | F3918: REVERSAL OF GJAMS0074- MISC INCOME ACCOUNTED THROUGH JOB NO AMSSFEF0007- ACL | G3918: 237.5 | H3918: 0 | I3918: =IF(AND(G3918="",H3918=""),"",N(G3918)-N(H3918)) -> 237.5 | J3918: =IF(I3918="","",ABS(I3918)) -> 237.5 | K3918: =IF(S3918="","",0) -> 0 | L3918: =IF(J3918="","",IF(AND(J3918>'Revenue Testing'!$E$9,K3918=0),1,0)) -> 0 | M3918: 0.93515279 | N3918: =IF(OR(A3918="",I3918=""),"",IF(COUNTIFS($A$2:$A$4500,A3918,$D$2:$D$4500,D3918,$I$2:$I$4500,I3918)>1,"Possible duplicate","")) | O3918: =IF(J3918="","",IF(AND(L3918=0,K3918=0),1,0)) -> 1 | P3918: =IF(L3918=1,J3918+ROW()/10^7,"") | Q3918: =IF(O3918=1,M3918,"") -> 0.93515279 | R3918: =IF(K3918=1,ROW(),"") | S3918: =IF(D3918="","",TRIM(D3918)) -> MISCELLANEOUS INCOME
A3919: CNAMS0037/25 | B3919: 45900 | C3919: =IF(S3919="","",IFERROR(IF(INDEX('Ledger Codes'!$C$6:$C$205,MATCH(S3919,'Ledger Codes'!$B$6:$B$205,0))="","",INDEX('Ledger Codes'!$C$6:$C$205,MATCH(S3919,'Ledger Codes'!$B$6:$B$205,0))),"")) -> 10083 | D3919: MISCELLANEOUS INCOME | E3919: REVERSAL OF DNAMS0034- MISC INCOME | F3919: REVERSAL OF DNAMS0034- MISC INCOME- WRONG ENTRY | G3919: 3339 | H3919: 0 | I3919: =IF(AND(G3919="",H3919=""),"",N(G3919)-N(H3919)) -> 3339 | J3919: =IF(I3919="","",ABS(I3919)) -> 3339 | K3919: =IF(S3919="","",0) -> 0 | L3919: =IF(J3919="","",IF(AND(J3919>'Revenue Testing'!$E$9,K3919=0),1,0)) -> 0 | M3919: 0.1413499 | N3919: =IF(OR(A3919="",I3919=""),"",IF(COUNTIFS($A$2:$A$4500,A3919,$D$2:$D$4500,D3919,$I$2:$I$4500,I3919)>1,"Possible duplicate","")) | O3919: =IF(J3919="","",IF(AND(L3919=0,K3919=0),1,0)) -> 1 | P3919: =IF(L3919=1,J3919+ROW()/10^7,"") | Q3919: =IF(O3919=1,M3919,"") -> 0.1413499 | R3919: =IF(K3919=1,ROW(),"") | S3919: =IF(D3919="","",TRIM(D3919)) -> MISCELLANEOUS INCOME
A3920: DNAMS0009/25 | B3920: 45905 | C3920: =IF(S3920="","",IFERROR(IF(INDEX('Ledger Codes'!$C$6:$C$205,MATCH(S3920,'Ledger Codes'!$B$6:$B$205,0))="","",INDEX('Ledger Codes'!$C$6:$C$205,MATCH(S3920,'Ledger Codes'!$B$6:$B$205,0))),"")) -> 10083 | D3920: MISCELLANEOUS INCOME | E3920: 11184 | F3920: INV 11184 FW SUPPLY 180 MT @ USD 11/SAR 41.25 PER MT- USD 3 PER MT PROFIT | G3920: 0 | H3920: 1350.03 | I3920: =IF(AND(G3920="",H3920=""),"",N(G3920)-N(H3920)) -> -1350.03 | J3920: =IF(I3920="","",ABS(I3920)) -> 1350.03 | K3920: =IF(S3920="","",0) -> 0 | L3920: =IF(J3920="","",IF(AND(J3920>'Revenue Testing'!$E$9,K3920=0),1,0)) -> 0 | M3920: 0.31243604 | N3920: =IF(OR(A3920="",I3920=""),"",IF(COUNTIFS($A$2:$A$4500,A3920,$D$2:$D$4500,D3920,$I$2:$I$4500,I3920)>1,"Possible duplicate","")) | O3920: =IF(J3920="","",IF(AND(L3920=0,K3920=0),1,0)) -> 1 | P3920: =IF(L3920=1,J3920+ROW()/10^7,"") | Q3920: =IF(O3920=1,M3920,"") -> 0.31243604 | R3920: =IF(K3920=1,ROW(),"") | S3920: =IF(D3920="","",TRIM(D3920)) -> MISCELLANEOUS INCOME
A3921: GJAMS0022/25 | B3921: 45907 | C3921: =IF(S3921="","",IFERROR(IF(INDEX('Ledger Codes'!$C$6:$C$205,MATCH(S3921,'Ledger Codes'!$B$6:$B$205,0))="","",INDEX('Ledger Codes'!$C$6:$C$205,MATCH(S3921,'Ledger Codes'!$B$6:$B$205,0))),"")) -> 10083 | D3921: MISCELLANEOUS INCOME | F3921: EXCESS AMOUNT PAID FOR DO INV- SAR 207.5- PROFIT SINCE 8 MONTHS CUSTOMER NOT FOLLOWED UP FOR CLAIM CHARGED AS PER 40HC INSTEAD OF 20DV | G3921: 0 | H3921: 207.5 | I3921: =IF(AND(G3921="",H3921=""),"",N(G3921)-N(H3921)) -> -207.5 | J3921: =IF(I3921="","",ABS(I3921)) -> 207.5 | K3921: =IF(S3921="","",0) -> 0 | L3921: =IF(J3921="","",IF(AND(J3921>'Revenue Testing'!$E$9,K3921=0),1,0)) -> 0 | M3921: 0.13358422 | N3921: =IF(OR(A3921="",I3921=""),"",IF(COUNTIFS($A$2:$A$4500,A3921,$D$2:$D$4500,D3921,$I$2:$I$4500,I3921)>1,"Possible duplicate","")) | O3921: =IF(J3921="","",IF(AND(L3921=0,K3921=0),1,0)) -> 1 | P3921: =IF(L3921=1,J3921+ROW()/10^7,"") | Q3921: =IF(O3921=1,M3921,"") -> 0.13358422 | R3921: =IF(K3921=1,ROW(),"") | S3921: =IF(D3921="","",TRIM(D3921)) -> MISCELLANEOUS INCOME
A3922: GJAMS0024/25 | B3922: 45907 | C3922: =IF(S3922="","",IFERROR(IF(INDEX('Ledger Codes'!$C$6:$C$205,MATCH(S3922,'Ledger Codes'!$B$6:$B$205,0))="","",INDEX('Ledger Codes'!$C$6:$C$205,MATCH(S3922,'Ledger Codes'!$B$6:$B$205,0))),"")) -> 10083 | D3922: MISCELLANEOUS INCOME | F3922: EXCESS AMT PAID SAR 9- CSDSHA032816 GOLDEN AUTOMATED BATTERY- CSTAR | G3922: 0 | H3922: 9 | I3922: =IF(AND(G3922="",H3922=""),"",N(G3922)-N(H3922)) -> -9 | J3922: =IF(I3922="","",ABS(I3922)) -> 9 | K3922: =IF(S3922="","",0) -> 0 | L3922: =IF(J3922="","",IF(AND(J3922>'Revenue Testing'!$E$9,K3922=0),1,0)) -> 0 | M3922: 0.38983589 | N3922: =IF(OR(A3922="",I3922=""),"",IF(COUNTIFS($A$2:$A$4500,A3922,$D$2:$D$4500,D3922,$I$2:$I$4500,I3922)>1,"Possible duplicate","")) | O3922: =IF(J3922="","",IF(AND(L3922=0,K3922=0),1,0)) -> 1 | P3922: =IF(L3922=1,J3922+ROW()/10^7,"") | Q3922: =IF(O3922=1,M3922,"") -> 0.38983589 | R3922: =IF(K3922=1,ROW(),"") | S3922: =IF(D3922="","",TRIM(D3922)) -> MISCELLANEOUS INCOME
A3923: GJAMS0026/25 | B3923: 45907 | C3923: =IF(S3923="","",IFERROR(IF(INDEX('Ledger Codes'!$C$6:$C$205,MATCH(S3923,'Ledger Codes'!$B$6:$B$205,0))="","",INDEX('Ledger Codes'!$C$6:$C$205,MATCH(S3923,'Ledger Codes'!$B$6:$B$205,0))),"")) -> 10083 | D3923: MISCELLANEOUS INCOME | F3923: EXCESS AMT PAID SAR 207.5- CSDSHA032863 CHARGED AS PER 40HC INSTEAD OF 20DV | G3923: 0 | H3923: 207.5 | I3923: =IF(AND(G3923="",H3923=""),"",N(G3923)-N(H3923)) -> -207.5 | J3923: =IF(I3923="","",ABS(I3923)) -> 207.5 | K3923: =IF(S3923="","",0) -> 0 | L3923: =IF(J3923="","",IF(AND(J3923>'Revenue Testing'!$E$9,K3923=0),1,0)) -> 0 | M3923: 0.40360017 | N3923: =IF(OR(A3923="",I3923=""),"",IF(COUNTIFS($A$2:$A$4500,A3923,$D$2:$D$4500,D3923,$I$2:$I$4500,I3923)>1,"Possible duplicate","")) | O3923: =IF(J3923="","",IF(AND(L3923=0,K3923=0),1,0)) -> 1 | P3923: =IF(L3923=1,J3923+ROW()/10^7,"") | Q3923: =IF(O3923=1,M3923,"") -> 0.40360017 | R3923: =IF(K3923=1,ROW(),"") | S3923: =IF(D3923="","",TRIM(D3923)) -> MISCELLANEOUS INCOME
A3924: GJAMS0027/25 | B3924: 45908 | C3924: =IF(S3924="","",IFERROR(IF(INDEX('Ledger Codes'!$C$6:$C$205,MATCH(S3924,'Ledger Codes'!$B$6:$B$205,0))="","",INDEX('Ledger Codes'!$C$6:$C$205,MATCH(S3924,'Ledger Codes'!$B$6:$B$205,0))),"")) -> 10083 | D3924: MISCELLANEOUS INCOME | F3924: EXCESS AMT SAR 134 PAID FOR REEFER SURCHARGE FOR 3 DAYS INSTEAD OF 2 DAYS | G3924: 0 | H3924: 134 | I3924: =IF(AND(G3924="",H3924=""),"",N(G3924)-N(H3924)) -> -134 | J3924: =IF(I3924="","",ABS(I3924)) -> 134 | K3924: =IF(S3924="","",0) -> 0 | L3924: =IF(J3924="","",IF(AND(J3924>'Revenue Testing'!$E$9,K3924=0),1,0)) -> 0 | M3924: 0.81339547 | N3924: =IF(OR(A3924="",I3924=""),"",IF(COUNTIFS($A$2:$A$4500,A3924,$D$2:$D$4500,D3924,$I$2:$I$4500,I3924)>1,"Possible duplicate","")) | O3924: =IF(J3924="","",IF(AND(L3924=0,K3924=0),1,0)) -> 1 | P3924: =IF(L3924=1,J3924+ROW()/10^7,"") | Q3924: =IF(O3924=1,M3924,"") -> 0.81339547 | R3924: =IF(K3924=1,ROW(),"") | S3924: =IF(D3924="","",TRIM(D3924)) -> MISCELLANEOUS INCOME
A3925: GJAMS0023/25 | B3925: 45929 | C3925: =IF(S3925="","",IFERROR(IF(INDEX('Ledger Codes'!$C$6:$C$205,MATCH(S3925,'Ledger Codes'!$B$6:$B$205,0))="","",INDEX('Ledger Codes'!$C$6:$C$205,MATCH(S3925,'Ledger Codes'!$B$6:$B$205,0))),"")) -> 10083 | D3925: MISCELLANEOUS INCOME | F3925: PAYMENT EXCESS SAR 35 RECEIVED ON EXPORT SHIPMENT INV TO GLOBIWN FORWARDING CO- CAPELINE LLC | G3925: 0 | H3925: 35 | I3925: =IF(AND(G3925="",H3925=""),"",N(G3925)-N(H3925)) -> -35 | J3925: =IF(I3925="","",ABS(I3925)) -> 35 | K3925: =IF(S3925="","",0) -> 0 | L3925: =IF(J3925="","",IF(AND(J3925>'Revenue Testing'!$E$9,K3925=0),1,0)) -> 0 | M3925: 0.47724031 | N3925: =IF(OR(A3925="",I3925=""),"",IF(COUNTIFS($A$2:$A$4500,A3925,$D$2:$D$4500,D3925,$I$2:$I$4500,I3925)>1,"Possible duplicate","")) | O3925: =IF(J3925="","",IF(AND(L3925=0,K3925=0),1,0)) -> 1 | P3925: =IF(L3925=1,J3925+ROW()/10^7,"") | Q3925: =IF(O3925=1,M3925,"") -> 0.47724031 | R3925: =IF(K3925=1,ROW(),"") | S3925: =IF(D3925="","",TRIM(D3925)) -> MISCELLANEOUS INCOME
A3926: GJAMS0028/25 | B3926: 45942 | C3926: =IF(S3926="","",IFERROR(IF(INDEX('Ledger Codes'!$C$6:$C$205,MATCH(S3926,'Ledger Codes'!$B$6:$B$205,0))="","",INDEX('Ledger Codes'!$C$6:$C$205,MATCH(S3926,'Ledger Codes'!$B$6:$B$205,0))),"")) -> 10083 | D3926: MISCELLANEOUS INCOME | F3926: EXCESS DETENTION PAID SAR 120- SAUDI INDUSTRIES FOR PVC WINDOWS CO. LTD. | G3926: 0 | H3926: 120 | I3926: =IF(AND(G3926="",H3926=""),"",N(G3926)-N(H3926)) -> -120 | J3926: =IF(I3926="","",ABS(I3926)) -> 120 | K3926: =IF(S3926="","",0) -> 0 | L3926: =IF(J3926="","",IF(AND(J3926>'Revenue Testing'!$E$9,K3926=0),1,0)) -> 0 | M3926: 0.58032359 | N3926: =IF(OR(A3926="",I3926=""),"",IF(COUNTIFS($A$2:$A$4500,A3926,$D$2:$D$4500,D3926,$I$2:$I$4500,I3926)>1,"Possible duplicate","")) | O3926: =IF(J3926="","",IF(AND(L3926=0,K3926=0),1,0)) -> 1 | P3926: =IF(L3926=1,J3926+ROW()/10^7,"") | Q3926: =IF(O3926=1,M3926,"") -> 0.58032359 | R3926: =IF(K3926=1,ROW(),"") | S3926: =IF(D3926="","",TRIM(D3926)) -> MISCELLANEOUS INCOME
A3927: DNAMS0022/25 | B3927: 45961 | C3927: =IF(S3927="","",IFERROR(IF(INDEX('Ledger Codes'!$C$6:$C$205,MATCH(S3927,'Ledger Codes'!$B$6:$B$205,0))="","",INDEX('Ledger Codes'!$C$6:$C$205,MATCH(S3927,'Ledger Codes'!$B$6:$B$205,0))),"")) -> 10083 | D3927: MISCELLANEOUS INCOME | E3927: 2369993- OVER THC CHARGED TO CSTAR | F3927: CSTAR-- 2369993- OVER THC CHARGED TO CSTAR FOR VESSEL CMA CGM ROSSINI - CCRO0RDMBE1MA ON T/S BASIS ON 40' | G3927: 0 | H3927: 210 | I3927: =IF(AND(G3927="",H3927=""),"",N(G3927)-N(H3927)) -> -210 | J3927: =IF(I3927="","",ABS(I3927)) -> 210 | K3927: =IF(S3927="","",0) -> 0 | L3927: =IF(J3927="","",IF(AND(J3927>'Revenue Testing'!$E$9,K3927=0),1,0)) -> 0 | M3927: 0.31755365 | N3927: =IF(OR(A3927="",I3927=""),"",IF(COUNTIFS($A$2:$A$4500,A3927,$D$2:$D$4500,D3927,$I$2:$I$4500,I3927)>1,"Possible duplicate","")) | O3927: =IF(J3927="","",IF(AND(L3927=0,K3927=0),1,0)) -> 1 | P3927: =IF(L3927=1,J3927+ROW()/10^7,"") | Q3927: =IF(O3927=1,M3927,"") -> 0.31755365 | R3927: =IF(K3927=1,ROW(),"") | S3927: =IF(D3927="","",TRIM(D3927)) -> MISCELLANEOUS INCOME
A3928: GJAMS0031/25 | B3928: 45965 | C3928: =IF(S3928="","",IFERROR(IF(INDEX('Ledger Codes'!$C$6:$C$205,MATCH(S3928,'Ledger Codes'!$B$6:$B$205,0))="","",INDEX('Ledger Codes'!$C$6:$C$205,MATCH(S3928,'Ledger Codes'!$B$6:$B$205,0))),"")) -> 10083 | D3928: MISCELLANEOUS INCOME | F3928: RSGT- 2373434- RSGT- CLF- CUL BANGKOK - BANK2538E- LOAD T/S EMPTY- 2X20'- SAR 149.5 34X40'- SAR 224.5 SAR 224.5 EXTRA CHARGED TO CSTAR ACTUAL INV AMT- SAR 7707.5 CHARGED SAR 7932- REF INV TO CSTAR | G3928: 0 | H3928: 224.5 | I3928: =IF(AND(G3928="",H3928=""),"",N(G3928)-N(H3928)) -> -224.5 | J3928: =IF(I3928="","",ABS(I3928)) -> 224.5 | K3928: =IF(S3928="","",0) -> 0 | L3928: =IF(J3928="","",IF(AND(J3928>'Revenue Testing'!$E$9,K3928=0),1,0)) -> 0 | M3928: 0.64838014 | N3928: =IF(OR(A3928="",I3928=""),"",IF(COUNTIFS($A$2:$A$4500,A3928,$D$2:$D$4500,D3928,$I$2:$I$4500,I3928)>1,"Possible duplicate","")) | O3928: =IF(J3928="","",IF(AND(L3928=0,K3928=0),1,0)) -> 1 | P3928: =IF(L3928=1,J3928+ROW()/10^7,"") | Q3928: =IF(O3928=1,M3928,"") -> 0.64838014 | R3928: =IF(K3928=1,ROW(),"") | S3928: =IF(D3928="","",TRIM(D3928)) -> MISCELLANEOUS INCOME
A3929: GJAMS0025/25 | B3929: 45971 | C3929: =IF(S3929="","",IFERROR(IF(INDEX('Ledger Codes'!$C$6:$C$205,MATCH(S3929,'Ledger Codes'!$B$6:$B$205,0))="","",INDEX('Ledger Codes'!$C$6:$C$205,MATCH(S3929,'Ledger Codes'!$B$6:$B$205,0))),"")) -> 10083 | D3929: MISCELLANEOUS INCOME | F3929: EXCESS DETENTION PAID AMT SAR 120- CSDIST002912- CSTAR | G3929: 0 | H3929: 120 | I3929: =IF(AND(G3929="",H3929=""),"",N(G3929)-N(H3929)) -> -120 | J3929: =IF(I3929="","",ABS(I3929)) -> 120 | K3929: =IF(S3929="","",0) -> 0 | L3929: =IF(J3929="","",IF(AND(J3929>'Revenue Testing'!$E$9,K3929=0),1,0)) -> 0 | M3929: 0.9966784 | N3929: =IF(OR(A3929="",I3929=""),"",IF(COUNTIFS($A$2:$A$4500,A3929,$D$2:$D$4500,D3929,$I$2:$I$4500,I3929)>1,"Possible duplicate","")) | O3929: =IF(J3929="","",IF(AND(L3929=0,K3929=0),1,0)) -> 1 | P3929: =IF(L3929=1,J3929+ROW()/10^7,"") | Q3929: =IF(O3929=1,M3929,"") -> 0.9966784 | R3929: =IF(K3929=1,ROW(),"") | S3929: =IF(D3929="","",TRIM(D3929)) -> MISCELLANEOUS INCOME
A3930: GJAMS0019/25 | B3930: 45972 | C3930: =IF(S3930="","",IFERROR(IF(INDEX('Ledger Codes'!$C$6:$C$205,MATCH(S3930,'Ledger Codes'!$B$6:$B$205,0))="","",INDEX('Ledger Codes'!$C$6:$C$205,MATCH(S3930,'Ledger Codes'!$B$6:$B$205,0))),"")) -> 10083 | D3930: MISCELLANEOUS INCOME | F3930: EXCESS DETENTION SAR 60- BL CSDSHA034080 | G3930: 0 | H3930: 60 | I3930: =IF(AND(G3930="",H3930=""),"",N(G3930)-N(H3930)) -> -60 | J3930: =IF(I3930="","",ABS(I3930)) -> 60 | K3930: =IF(S3930="","",0) -> 0 | L3930: =IF(J3930="","",IF(AND(J3930>'Revenue Testing'!$E$9,K3930=0),1,0)) -> 0 | M3930: 0.66049409 | N3930: =IF(OR(A3930="",I3930=""),"",IF(COUNTIFS($A$2:$A$4500,A3930,$D$2:$D$4500,D3930,$I$2:$I$4500,I3930)>1,"Possible duplicate","")) | O3930: =IF(J3930="","",IF(AND(L3930=0,K3930=0),1,0)) -> 1 | P3930: =IF(L3930=1,J3930+ROW()/10^7,"") | Q3930: =IF(O3930=1,M3930,"") -> 0.66049409 | R3930: =IF(K3930=1,ROW(),"") | S3930: =IF(D3930="","",TRIM(D3930)) -> MISCELLANEOUS INCOME
A3931: DNAMS0010/25 | B3931: 45979 | C3931: =IF(S3931="","",IFERROR(IF(INDEX('Ledger Codes'!$C$6:$C$205,MATCH(S3931,'Ledger Codes'!$B$6:$B$205,0))="","",INDEX('Ledger Codes'!$C$6:$C$205,MATCH(S3931,'Ledger Codes'!$B$6:$B$205,0))),"")) -> 10083 | D3931: MISCELLANEOUS INCOME | E3931: 11345 | F3931: INV 11345 CSTAR FW SUPPLY 120 MT USD 3 PER MT PROFIT | G3931: 0 | H3931: 900.08 | I3931: =IF(AND(G3931="",H3931=""),"",N(G3931)-N(H3931)) -> -900.08 | J3931: =IF(I3931="","",ABS(I3931)) -> 900.08 | K3931: =IF(S3931="","",0) -> 0 | L3931: =IF(J3931="","",IF(AND(J3931>'Revenue Testing'!$E$9,K3931=0),1,0)) -> 0 | M3931: 0.11284376 | N3931: =IF(OR(A3931="",I3931=""),"",IF(COUNTIFS($A$2:$A$4500,A3931,$D$2:$D$4500,D3931,$I$2:$I$4500,I3931)>1,"Possible duplicate","")) | O3931: =IF(J3931="","",IF(AND(L3931=0,K3931=0),1,0)) -> 1 | P3931: =IF(L3931=1,J3931+ROW()/10^7,"") | Q3931: =IF(O3931=1,M3931,"") -> 0.11284376 | R3931: =IF(K3931=1,ROW(),"") | S3931: =IF(D3931="","",TRIM(D3931)) -> MISCELLANEOUS INCOME
A3932: GJAMS0020/25 | B3932: 45984 | C3932: =IF(S3932="","",IFERROR(IF(INDEX('Ledger Codes'!$C$6:$C$205,MATCH(S3932,'Ledger Codes'!$B$6:$B$205,0))="","",INDEX('Ledger Codes'!$C$6:$C$205,MATCH(S3932,'Ledger Codes'!$B$6:$B$205,0))),"")) -> 10083 | D3932: MISCELLANEOUS INCOME | F3932: EXCESS DETENTION PAID SAR 440- BL CSDSHA033634 AL-MUSAMIR MEMIZA AL-FAKHRA FOR TRADING | G3932: 0 | H3932: 440 | I3932: =IF(AND(G3932="",H3932=""),"",N(G3932)-N(H3932)) -> -440 | J3932: =IF(I3932="","",ABS(I3932)) -> 440 | K3932: =IF(S3932="","",0) -> 0 | L3932: =IF(J3932="","",IF(AND(J3932>'Revenue Testing'!$E$9,K3932=0),1,0)) -> 0 | M3932: 0.83417225 | N3932: =IF(OR(A3932="",I3932=""),"",IF(COUNTIFS($A$2:$A$4500,A3932,$D$2:$D$4500,D3932,$I$2:$I$4500,I3932)>1,"Possible duplicate","")) | O3932: =IF(J3932="","",IF(AND(L3932=0,K3932=0),1,0)) -> 1 | P3932: =IF(L3932=1,J3932+ROW()/10^7,"") | Q3932: =IF(O3932=1,M3932,"") -> 0.83417225 | R3932: =IF(K3932=1,ROW(),"") | S3932: =IF(D3932="","",TRIM(D3932)) -> MISCELLANEOUS INCOME
A3933: GJAMS0021/25 | B3933: 46000 | C3933: =IF(S3933="","",IFERROR(IF(INDEX('Ledger Codes'!$C$6:$C$205,MATCH(S3933,'Ledger Codes'!$B$6:$B$205,0))="","",INDEX('Ledger Codes'!$C$6:$C$205,MATCH(S3933,'Ledger Codes'!$B$6:$B$205,0))),"")) -> 10083 | D3933: MISCELLANEOUS INCOME | F3933: EXCESS DETENTION PAID SAR 120- CSDIST002939 | G3933: 0 | H3933: 120 | I3933: =IF(AND(G3933="",H3933=""),"",N(G3933)-N(H3933)) -> -120 | J3933: =IF(I3933="","",ABS(I3933)) -> 120 | K3933: =IF(S3933="","",0) -> 0 | L3933: =IF(J3933="","",IF(AND(J3933>'Revenue Testing'!$E$9,K3933=0),1,0)) -> 0 | M3933: 0.4113673 | N3933: =IF(OR(A3933="",I3933=""),"",IF(COUNTIFS($A$2:$A$4500,A3933,$D$2:$D$4500,D3933,$I$2:$I$4500,I3933)>1,"Possible duplicate","")) | O3933: =IF(J3933="","",IF(AND(L3933=0,K3933=0),1,0)) -> 1 | P3933: =IF(L3933=1,J3933+ROW()/10^7,"") | Q3933: =IF(O3933=1,M3933,"") -> 0.4113673 | R3933: =IF(K3933=1,ROW(),"") | S3933: =IF(D3933="","",TRIM(D3933)) -> MISCELLANEOUS INCOME
A3934: DNAMS0008/25 | B3934: 46021 | C3934: =IF(S3934="","",IFERROR(IF(INDEX('Ledger Codes'!$C$6:$C$205,MATCH(S3934,'Ledger Codes'!$B$6:$B$205,0))="","",INDEX('Ledger Codes'!$C$6:$C$205,MATCH(S3934,'Ledger Codes'!$B$6:$B$205,0))),"")) -> 10083 | D3934: MISCELLANEOUS INCOME | E3934: 4365 | F3934: DEBIT NOTE AS AGREED WITH FREIGHT WORLD AGAINST INV 4365 | G3934: 0 | H3934: 270 | I3934: =IF(AND(G3934="",H3934=""),"",N(G3934)-N(H3934)) -> -270 | J3934: =IF(I3934="","",ABS(I3934)) -> 270 | K3934: =IF(S3934="","",0) -> 0 | L3934: =IF(J3934="","",IF(AND(J3934>'Revenue Testing'!$E$9,K3934=0),1,0)) -> 0 | M3934: 0.64076685 | N3934: =IF(OR(A3934="",I3934=""),"",IF(COUNTIFS($A$2:$A$4500,A3934,$D$2:$D$4500,D3934,$I$2:$I$4500,I3934)>1,"Possible duplicate","")) | O3934: =IF(J3934="","",IF(AND(L3934=0,K3934=0),1,0)) -> 1 | P3934: =IF(L3934=1,J3934+ROW()/10^7,"") | Q3934: =IF(O3934=1,M3934,"") -> 0.64076685 | R3934: =IF(K3934=1,ROW(),"") | S3934: =IF(D3934="","",TRIM(D3934)) -> MISCELLANEOUS INCOME
A3935: PJAMS0046/25 | B3935: 45963 | C3935: =IF(S3935="","",IFERROR(IF(INDEX('Ledger Codes'!$C$6:$C$205,MATCH(S3935,'Ledger Codes'!$B$6:$B$205,0))="","",INDEX('Ledger Codes'!$C$6:$C$205,MATCH(S3935,'Ledger Codes'!$B$6:$B$205,0))),"")) -> 10065 | D3935: TRANSPORTATION CHARGES | E3935: 3574 | F3935: PJ Ref:AMSLAP0018/25 ; INV- 3574 CSTAR- TRAMSPORTATION CHGS- SAR 270 X 7 TRIPS , SAR 135 X 1 TRIP- 20DV & SAR 270 X 29 TRIPS 40HC & FASAH APPOINTEMNT CHGS | G3935: 2025 | H3935: 0 | I3935: =IF(AND(G3935="",H3935=""),"",N(G3935)-N(H3935)) -> 2025 | J3935: =IF(I3935="","",ABS(I3935)) -> 2025 | K3935: =IF(S3935="","",0) -> 0 | L3935: =IF(J3935="","",IF(AND(J3935>'Revenue Testing'!$E$9,K3935=0),1,0)) -> 0 | M3935: 0.34241209 | N3935: =IF(OR(A3935="",I3935=""),"",IF(COUNTIFS($A$2:$A$4500,A3935,$D$2:$D$4500,D3935,$I$2:$I$4500,I3935)>1,"Possible duplicate","")) | O3935: =IF(J3935="","",IF(AND(L3935=0,K3935=0),1,0)) -> 1 | P3935: =IF(L3935=1,J3935+ROW()/10^7,"") | Q3935: =IF(O3935=1,M3935,"") -> 0.34241209 | R3935: =IF(K3935=1,ROW(),"") | S3935: =IF(D3935="","",TRIM(D3935)) -> TRANSPORTATION CHARGES
A3936: PJAMS0046/25 | B3936: 45963 | C3936: =IF(S3936="","",IFERROR(IF(INDEX('Ledger Codes'!$C$6:$C$205,MATCH(S3936,'Ledger Codes'!$B$6:$B$205,0))="","",INDEX('Ledger Codes'!$C$6:$C$205,MATCH(S3936,'Ledger Codes'!$B$6:$B$205,0))),"")) -> 10065 | D3936: TRANSPORTATION CHARGES | E3936: 3574 | F3936: PJ Ref:AMSLAP0018/25 ; INV- 3574 CSTAR- TRAMSPORTATION CHGS- SAR 270 X 7 TRIPS , SAR 135 X 1 TRIP- 20DV & SAR 270 X 29 TRIPS 40HC & FASAH APPOINTEMNT CHGS | G3936: 7830 | H3936: 0 | I3936: =IF(AND(G3936="",H3936=""),"",N(G3936)-N(H3936)) -> 7830 | J3936: =IF(I3936="","",ABS(I3936)) -> 7830 | K3936: =IF(S3936="","",0) -> 0 | L3936: =IF(J3936="","",IF(AND(J3936>'Revenue Testing'!$E$9,K3936=0),1,0)) -> 1 | M3936: 0.038374993 | N3936: =IF(OR(A3936="",I3936=""),"",IF(COUNTIFS($A$2:$A$4500,A3936,$D$2:$D$4500,D3936,$I$2:$I$4500,I3936)>1,"Possible duplicate","")) | O3936: =IF(J3936="","",IF(AND(L3936=0,K3936=0),1,0)) -> 0 | P3936: =IF(L3936=1,J3936+ROW()/10^7,"") -> 7830.0004 | Q3936: =IF(O3936=1,M3936,"") | R3936: =IF(K3936=1,ROW(),"") | S3936: =IF(D3936="","",TRIM(D3936)) -> TRANSPORTATION CHARGES
A3937: SJAMS0565/25 | B3937: 45963 | C3937: =IF(S3937="","",IFERROR(IF(INDEX('Ledger Codes'!$C$6:$C$205,MATCH(S3937,'Ledger Codes'!$B$6:$B$205,0))="","",INDEX('Ledger Codes'!$C$6:$C$205,MATCH(S3937,'Ledger Codes'!$B$6:$B$205,0))),"")) -> 10065 | D3937: TRANSPORTATION CHARGES | E3937: AMSLAS0022/25 | F3937: FREIGHT WORLD- JSI-25-3574- TRANSPORTATION CHARGES ARAP REF - JSI-25-3574 | G3937: 0 | H3937: 11333.25 | I3937: =IF(AND(G3937="",H3937=""),"",N(G3937)-N(H3937)) -> -11333.25 | J3937: =IF(I3937="","",ABS(I3937)) -> 11333.25 | K3937: =IF(S3937="","",0) -> 0 | L3937: =IF(J3937="","",IF(AND(J3937>'Revenue Testing'!$E$9,K3937=0),1,0)) -> 1 | M3937: 0.14286337 | N3937: =IF(OR(A3937="",I3937=""),"",IF(COUNTIFS($A$2:$A$4500,A3937,$D$2:$D$4500,D3937,$I$2:$I$4500,I3937)>1,"Possible duplicate","")) | O3937: =IF(J3937="","",IF(AND(L3937=0,K3937=0),1,0)) -> 0 | P3937: =IF(L3937=1,J3937+ROW()/10^7,"") -> 11333.25 | Q3937: =IF(O3937=1,M3937,"") | R3937: =IF(K3937=1,ROW(),"") | S3937: =IF(D3937="","",TRIM(D3937)) -> TRANSPORTATION CHARGES
A3938: PJAMS0051/25 | B3938: 45991 | C3938: =IF(S3938="","",IFERROR(IF(INDEX('Ledger Codes'!$C$6:$C$205,MATCH(S3938,'Ledger Codes'!$B$6:$B$205,0))="","",INDEX('Ledger Codes'!$C$6:$C$205,MATCH(S3938,'Ledger Codes'!$B$6:$B$205,0))),"")) -> 10065 | D3938: TRANSPORTATION CHARGES | E3938: 3986 | F3938: PJ Ref:AMSLAP0023/25 ; INV 3986- CAPELINE- LOLO CHGS @ SAR 55 X 1 40RF TRANSPORTATION CHGS & FASAH APPOINTMENT CHGS | G3938: 270 | H3938: 0 | I3938: =IF(AND(G3938="",H3938=""),"",N(G3938)-N(H3938)) -> 270 | J3938: =IF(I3938="","",ABS(I3938)) -> 270 | K3938: =IF(S3938="","",0) -> 0 | L3938: =IF(J3938="","",IF(AND(J3938>'Revenue Testing'!$E$9,K3938=0),1,0)) -> 0 | M3938: 0.50235533 | N3938: =IF(OR(A3938="",I3938=""),"",IF(COUNTIFS($A$2:$A$4500,A3938,$D$2:$D$4500,D3938,$I$2:$I$4500,I3938)>1,"Possible duplicate","")) | O3938: =IF(J3938="","",IF(AND(L3938=0,K3938=0),1,0)) -> 1 | P3938: =IF(L3938=1,J3938+ROW()/10^7,"") | Q3938: =IF(O3938=1,M3938,"") -> 0.50235533 | R3938: =IF(K3938=1,ROW(),"") | S3938: =IF(D3938="","",TRIM(D3938)) -> TRANSPORTATION CHARGES
A3939: SJAMS0562/25 | B3939: 45991 | C3939: =IF(S3939="","",IFERROR(IF(INDEX('Ledger Codes'!$C$6:$C$205,MATCH(S3939,'Ledger Codes'!$B$6:$B$205,0))="","",INDEX('Ledger Codes'!$C$6:$C$205,MATCH(S3939,'Ledger Codes'!$B$6:$B$205,0))),"")) -> 10065 | D3939: TRANSPORTATION CHARGES | E3939: AMSLAS0019/25 | F3939: FREIGHT WORLD- TRANSPORTATION CHGS AND FASAH APPOINTMENT- ARAP REF - JSI-25-4037 | G3939: 0 | H3939: 2990 | I3939: =IF(AND(G3939="",H3939=""),"",N(G3939)-N(H3939)) -> -2990 | J3939: =IF(I3939="","",ABS(I3939)) -> 2990 | K3939: =IF(S3939="","",0) -> 0 | L3939: =IF(J3939="","",IF(AND(J3939>'Revenue Testing'!$E$9,K3939=0),1,0)) -> 0 | M3939: 0.21946914 | N3939: =IF(OR(A3939="",I3939=""),"",IF(COUNTIFS($A$2:$A$4500,A3939,$D$2:$D$4500,D3939,$I$2:$I$4500,I3939)>1,"Possible duplicate","")) | O3939: =IF(J3939="","",IF(AND(L3939=0,K3939=0),1,0)) -> 1 | P3939: =IF(L3939=1,J3939+ROW()/10^7,"") | Q3939: =IF(O3939=1,M3939,"") -> 0.21946914 | R3939: =IF(K3939=1,ROW(),"") | S3939: =IF(D3939="","",TRIM(D3939)) -> TRANSPORTATION CHARGES
A3940: PJAMS0048/25 | B3940: 45994 | C3940: =IF(S3940="","",IFERROR(IF(INDEX('Ledger Codes'!$C$6:$C$205,MATCH(S3940,'Ledger Codes'!$B$6:$B$205,0))="","",INDEX('Ledger Codes'!$C$6:$C$205,MATCH(S3940,'Ledger Codes'!$B$6:$B$205,0))),"")) -> 10065 | D3940: TRANSPORTATION CHARGES | E3940: 4053 | F3940: PJ Ref:AMSLAP0020/25 ; INV 4053- CAPELINE- TRANSPORTATION CHGS @ SAR 270 X 2 40 HC | G3940: 540 | H3940: 0 | I3940: =IF(AND(G3940="",H3940=""),"",N(G3940)-N(H3940)) -> 540 | J3940: =IF(I3940="","",ABS(I3940)) -> 540 | K3940: =IF(S3940="","",0) -> 0 | L3940: =IF(J3940="","",IF(AND(J3940>'Revenue Testing'!$E$9,K3940=0),1,0)) -> 0 | M3940: 0.93424855 | N3940: =IF(OR(A3940="",I3940=""),"",IF(COUNTIFS($A$2:$A$4500,A3940,$D$2:$D$4500,D3940,$I$2:$I$4500,I3940)>1,"Possible duplicate","")) | O3940: =IF(J3940="","",IF(AND(L3940=0,K3940=0),1,0)) -> 1 | P3940: =IF(L3940=1,J3940+ROW()/10^7,"") | Q3940: =IF(O3940=1,M3940,"") -> 0.93424855 | R3940: =IF(K3940=1,ROW(),"") | S3940: =IF(D3940="","",TRIM(D3940)) -> TRANSPORTATION CHARGES
A3941: PJAMS0043/25 | B3941: 45999 | C3941: =IF(S3941="","",IFERROR(IF(INDEX('Ledger Codes'!$C$6:$C$205,MATCH(S3941,'Ledger Codes'!$B$6:$B$205,0))="","",INDEX('Ledger Codes'!$C$6:$C$205,MATCH(S3941,'Ledger Codes'!$B$6:$B$205,0))),"")) -> 10065 | D3941: TRANSPORTATION CHARGES | E3941: 4037 | F3941: PJ Ref:AMSLAP0015/25 ; INV 4037- CSTAR LOCAL TRANSPORTATION CHARGES SAR 135 X 13 TRIPS - 20DV & SAR 270 X 1 TRIPS- 40HC & FASAH APPOINTMENT CHARGES | G3941: 1755 | H3941: 0 | I3941: =IF(AND(G3941="",H3941=""),"",N(G3941)-N(H3941)) -> 1755 | J3941: =IF(I3941="","",ABS(I3941)) -> 1755 | K3941: =IF(S3941="","",0) -> 0 | L3941: =IF(J3941="","",IF(AND(J3941>'Revenue Testing'!$E$9,K3941=0),1,0)) -> 0 | M3941: 0.76981566 | N3941: =IF(OR(A3941="",I3941=""),"",IF(COUNTIFS($A$2:$A$4500,A3941,$D$2:$D$4500,D3941,$I$2:$I$4500,I3941)>1,"Possible duplicate","")) | O3941: =IF(J3941="","",IF(AND(L3941=0,K3941=0),1,0)) -> 1 | P3941: =IF(L3941=1,J3941+ROW()/10^7,"") | Q3941: =IF(O3941=1,M3941,"") -> 0.76981566 | R3941: =IF(K3941=1,ROW(),"") | S3941: =IF(D3941="","",TRIM(D3941)) -> TRANSPORTATION CHARGES
A3942: PJAMS0043/25 | B3942: 45999 | C3942: =IF(S3942="","",IFERROR(IF(INDEX('Ledger Codes'!$C$6:$C$205,MATCH(S3942,'Ledger Codes'!$B$6:$B$205,0))="","",INDEX('Ledger Codes'!$C$6:$C$205,MATCH(S3942,'Ledger Codes'!$B$6:$B$205,0))),"")) -> 10065 | D3942: TRANSPORTATION CHARGES | E3942: 4037 | F3942: PJ Ref:AMSLAP0015/25 ; INV 4037- CSTAR LOCAL TRANSPORTATION CHARGES SAR 135 X 13 TRIPS - 20DV & SAR 270 X 1 TRIPS- 40HC & FASAH APPOINTMENT CHARGES | G3942: 270 | H3942: 0 | I3942: =IF(AND(G3942="",H3942=""),"",N(G3942)-N(H3942)) -> 270 | J3942: =IF(I3942="","",ABS(I3942)) -> 270 | K3942: =IF(S3942="","",0) -> 0 | L3942: =IF(J3942="","",IF(AND(J3942>'Revenue Testing'!$E$9,K3942=0),1,0)) -> 0 | M3942: 0.70418004 | N3942: =IF(OR(A3942="",I3942=""),"",IF(COUNTIFS($A$2:$A$4500,A3942,$D$2:$D$4500,D3942,$I$2:$I$4500,I3942)>1,"Possible duplicate","")) | O3942: =IF(J3942="","",IF(AND(L3942=0,K3942=0),1,0)) -> 1 | P3942: =IF(L3942=1,J3942+ROW()/10^7,"") | Q3942: =IF(O3942=1,M3942,"") -> 0.70418004 | R3942: =IF(K3942=1,ROW(),"") | S3942: =IF(D3942="","",TRIM(D3942)) -> TRANSPORTATION CHARGES
A3943: SJAMS0492/25 | B3943: 46008 | C3943: =IF(S3943="","",IFERROR(IF(INDEX('Ledger Codes'!$C$6:$C$205,MATCH(S3943,'Ledger Codes'!$B$6:$B$205,0))="","",INDEX('Ledger Codes'!$C$6:$C$205,MATCH(S3943,'Ledger Codes'!$B$6:$B$205,0))),"")) -> 10065 | D3943: TRANSPORTATION CHARGES | E3943: AMSLAS0002/25 | F3943: 4X40 HC UNITS CONTAINER RETURN TRANSPORTATION CHARGES AND LOLO TRLU7097332, DFSU6328691, CINU6863122, CCLU7236772 4*40HC SOFT DRINKS EXW JEDDAH. ARAP REF - ALMJDH/00009/202512 | G3943: 0 | H3943: 2000 | I3943: =IF(AND(G3943="",H3943=""),"",N(G3943)-N(H3943)) -> -2000 | J3943: =IF(I3943="","",ABS(I3943)) -> 2000 | K3943: =IF(S3943="","",0) -> 0 | L3943: =IF(J3943="","",IF(AND(J3943>'Revenue Testing'!$E$9,K3943=0),1,0)) -> 0 | M3943: 0.73066538 | N3943: =IF(OR(A3943="",I3943=""),"",IF(COUNTIFS($A$2:$A$4500,A3943,$D$2:$D$4500,D3943,$I$2:$I$4500,I3943)>1,"Possible duplicate","")) | O3943: =IF(J3943="","",IF(AND(L3943=0,K3943=0),1,0)) -> 1 | P3943: =IF(L3943=1,J3943+ROW()/10^7,"") | Q3943: =IF(O3943=1,M3943,"") -> 0.73066538 | R3943: =IF(K3943=1,ROW(),"") | S3943: =IF(D3943="","",TRIM(D3943)) -> TRANSPORTATION CHARGES
C3944: =IF(S3944="","",IFERROR(IF(INDEX('Ledger Codes'!$C$6:$C$205,MATCH(S3944,'Ledger Codes'!$B$6:$B$205,0))="","",INDEX('Ledger Codes'!$C$6:$C$205,MATCH(S3944,'Ledger Codes'!$B$6:$B$205,0))),"")) | I3944: =IF(AND(G3944="",H3944=""),"",N(G3944)-N(H3944)) | J3944: =IF(I3944="","",ABS(I3944)) | K3944: =IF(S3944="","",0) | L3944: =IF(J3944="","",IF(AND(J3944>'Revenue Testing'!$E$9,K3944=0),1,0)) | M3944: 0.84842368 | N3944: =IF(OR(A3944="",I3944=""),"",IF(COUNTIFS($A$2:$A$4500,A3944,$D$2:$D$4500,D3944,$I$2:$I$4500,I3944)>1,"Possible duplicate","")) | O3944: =IF(J3944="","",IF(AND(L3944=0,K3944=0),1,0)) | P3944: =IF(L3944=1,J3944+ROW()/10^7,"") | Q3944: =IF(O3944=1,M3944,"") | R3944: =IF(K3944=1,ROW(),"") | S3944: =IF(D3944="","",TRIM(D3944))
C3945: =IF(S3945="","",IFERROR(IF(INDEX('Ledger Codes'!$C$6:$C$205,MATCH(S3945,'Ledger Codes'!$B$6:$B$205,0))="","",INDEX('Ledger Codes'!$C$6:$C$205,MATCH(S3945,'Ledger Codes'!$B$6:$B$205,0))),"")) | I3945: =IF(AND(G3945="",H3945=""),"",N(G3945)-N(H3945)) | J3945: =IF(I3945="","",ABS(I3945)) | K3945: =IF(S3945="","",0) | L3945: =IF(J3945="","",IF(AND(J3945>'Revenue Testing'!$E$9,K3945=0),1,0)) | M3945: 0.49460069 | N3945: =IF(OR(A3945="",I3945=""),"",IF(COUNTIFS($A$2:$A$4500,A3945,$D$2:$D$4500,D3945,$I$2:$I$4500,I3945)>1,"Possible duplicate","")) | O3945: =IF(J3945="","",IF(AND(L3945=0,K3945=0),1,0)) | P3945: =IF(L3945=1,J3945+ROW()/10^7,"") | Q3945: =IF(O3945=1,M3945,"") | R3945: =IF(K3945=1,ROW(),"") | S3945: =IF(D3945="","",TRIM(D3945))
C3946: =IF(S3946="","",IFERROR(IF(INDEX('Ledger Codes'!$C$6:$C$205,MATCH(S3946,'Ledger Codes'!$B$6:$B$205,0))="","",INDEX('Ledger Codes'!$C$6:$C$205,MATCH(S3946,'Ledger Codes'!$B$6:$B$205,0))),"")) | I3946: =IF(AND(G3946="",H3946=""),"",N(G3946)-N(H3946)) | J3946: =IF(I3946="","",ABS(I3946)) | K3946: =IF(S3946="","",0) | L3946: =IF(J3946="","",IF(AND(J3946>'Revenue Testing'!$E$9,K3946=0),1,0)) | M3946: 0.37808068 | N3946: =IF(OR(A3946="",I3946=""),"",IF(COUNTIFS($A$2:$A$4500,A3946,$D$2:$D$4500,D3946,$I$2:$I$4500,I3946)>1,"Possible duplicate","")) | O3946: =IF(J3946="","",IF(AND(L3946=0,K3946=0),1,0)) | P3946: =IF(L3946=1,J3946+ROW()/10^7,"") | Q3946: =IF(O3946=1,M3946,"") | R3946: =IF(K3946=1,ROW(),"") | S3946: =IF(D3946="","",TRIM(D3946))
C3947: =IF(S3947="","",IFERROR(IF(INDEX('Ledger Codes'!$C$6:$C$205,MATCH(S3947,'Ledger Codes'!$B$6:$B$205,0))="","",INDEX('Ledger Codes'!$C$6:$C$205,MATCH(S3947,'Ledger Codes'!$B$6:$B$205,0))),"")) | I3947: =IF(AND(G3947="",H3947=""),"",N(G3947)-N(H3947)) | J3947: =IF(I3947="","",ABS(I3947)) | K3947: =IF(S3947="","",0) | L3947: =IF(J3947="","",IF(AND(J3947>'Revenue Testing'!$E$9,K3947=0),1,0)) | M3947: 0.47852985 | N3947: =IF(OR(A3947="",I3947=""),"",IF(COUNTIFS($A$2:$A$4500,A3947,$D$2:$D$4500,D3947,$I$2:$I$4500,I3947)>1,"Possible duplicate","")) | O3947: =IF(J3947="","",IF(AND(L3947=0,K3947=0),1,0)) | P3947: =IF(L3947=1,J3947+ROW()/10^7,"") | Q3947: =IF(O3947=1,M3947,"") | R3947: =IF(K3947=1,ROW(),"") | S3947: =IF(D3947="","",TRIM(D3947))
C3948: =IF(S3948="","",IFERROR(IF(INDEX('Ledger Codes'!$C$6:$C$205,MATCH(S3948,'Ledger Codes'!$B$6:$B$205,0))="","",INDEX('Ledger Codes'!$C$6:$C$205,MATCH(S3948,'Ledger Codes'!$B$6:$B$205,0))),"")) | I3948: =IF(AND(G3948="",H3948=""),"",N(G3948)-N(H3948)) | J3948: =IF(I3948="","",ABS(I3948)) | K3948: =IF(S3948="","",0) | L3948: =IF(J3948="","",IF(AND(J3948>'Revenue Testing'!$E$9,K3948=0),1,0)) | M3948: 0.79240832 | N3948: =IF(OR(A3948="",I3948=""),"",IF(COUNTIFS($A$2:$A$4500,A3948,$D$2:$D$4500,D3948,$I$2:$I$4500,I3948)>1,"Possible duplicate","")) | O3948: =IF(J3948="","",IF(AND(L3948=0,K3948=0),1,0)) | P3948: =IF(L3948=1,J3948+ROW()/10^7,"") | Q3948: =IF(O3948=1,M3948,"") | R3948: =IF(K3948=1,ROW(),"") | S3948: =IF(D3948="","",TRIM(D3948))
C3949: =IF(S3949="","",IFERROR(IF(INDEX('Ledger Codes'!$C$6:$C$205,MATCH(S3949,'Ledger Codes'!$B$6:$B$205,0))="","",INDEX('Ledger Codes'!$C$6:$C$205,MATCH(S3949,'Ledger Codes'!$B$6:$B$205,0))),"")) | I3949: =IF(AND(G3949="",H3949=""),"",N(G3949)-N(H3949)) | J3949: =IF(I3949="","",ABS(I3949)) | K3949: =IF(S3949="","",0) | L3949: =IF(J3949="","",IF(AND(J3949>'Revenue Testing'!$E$9,K3949=0),1,0)) | M3949: 0.50180542 | N3949: =IF(OR(A3949="",I3949=""),"",IF(COUNTIFS($A$2:$A$4500,A3949,$D$2:$D$4500,D3949,$I$2:$I$4500,I3949)>1,"Possible duplicate","")) | O3949: =IF(J3949="","",IF(AND(L3949=0,K3949=0),1,0)) | P3949: =IF(L3949=1,J3949+ROW()/10^7,"") | Q3949: =IF(O3949=1,M3949,"") | R3949: =IF(K3949=1,ROW(),"") | S3949: =IF(D3949="","",TRIM(D3949))
C3950: =IF(S3950="","",IFERROR(IF(INDEX('Ledger Codes'!$C$6:$C$205,MATCH(S3950,'Ledger Codes'!$B$6:$B$205,0))="","",INDEX('Ledger Codes'!$C$6:$C$205,MATCH(S3950,'Ledger Codes'!$B$6:$B$205,0))),"")) | I3950: =IF(AND(G3950="",H3950=""),"",N(G3950)-N(H3950)) | J3950: =IF(I3950="","",ABS(I3950)) | K3950: =IF(S3950="","",0) | L3950: =IF(J3950="","",IF(AND(J3950>'Revenue Testing'!$E$9,K3950=0),1,0)) | M3950: 0.27974667 | N3950: =IF(OR(A3950="",I3950=""),"",IF(COUNTIFS($A$2:$A$4500,A3950,$D$2:$D$4500,D3950,$I$2:$I$4500,I3950)>1,"Possible duplicate","")) | O3950: =IF(J3950="","",IF(AND(L3950=0,K3950=0),1,0)) | P3950: =IF(L3950=1,J3950+ROW()/10^7,"") | Q3950: =IF(O3950=1,M3950,"") | R3950: =IF(K3950=1,ROW(),"") | S3950: =IF(D3950="","",TRIM(D3950))
C3951: =IF(S3951="","",IFERROR(IF(INDEX('Ledger Codes'!$C$6:$C$205,MATCH(S3951,'Ledger Codes'!$B$6:$B$205,0))="","",INDEX('Ledger Codes'!$C$6:$C$205,MATCH(S3951,'Ledger Codes'!$B$6:$B$205,0))),"")) | I3951: =IF(AND(G3951="",H3951=""),"",N(G3951)-N(H3951)) | J3951: =IF(I3951="","",ABS(I3951)) | K3951: =IF(S3951="","",0) | L3951: =IF(J3951="","",IF(AND(J3951>'Revenue Testing'!$E$9,K3951=0),1,0)) | M3951: 0.13824534 | N3951: =IF(OR(A3951="",I3951=""),"",IF(COUNTIFS($A$2:$A$4500,A3951,$D$2:$D$4500,D3951,$I$2:$I$4500,I3951)>1,"Possible duplicate","")) | O3951: =IF(J3951="","",IF(AND(L3951=0,K3951=0),1,0)) | P3951: =IF(L3951=1,J3951+ROW()/10^7,"") | Q3951: =IF(O3951=1,M3951,"") | R3951: =IF(K3951=1,ROW(),"") | S3951: =IF(D3951="","",TRIM(D3951))
C3952: =IF(S3952="","",IFERROR(IF(INDEX('Ledger Codes'!$C$6:$C$205,MATCH(S3952,'Ledger Codes'!$B$6:$B$205,0))="","",INDEX('Ledger Codes'!$C$6:$C$205,MATCH(S3952,'Ledger Codes'!$B$6:$B$205,0))),"")) | I3952: =IF(AND(G3952="",H3952=""),"",N(G3952)-N(H3952)) | J3952: =IF(I3952="","",ABS(I3952)) | K3952: =IF(S3952="","",0) | L3952: =IF(J3952="","",IF(AND(J3952>'Revenue Testing'!$E$9,K3952=0),1,0)) | M3952: 0.162332 | N3952: =IF(OR(A3952="",I3952=""),"",IF(COUNTIFS($A$2:$A$4500,A3952,$D$2:$D$4500,D3952,$I$2:$I$4500,I3952)>1,"Possible duplicate","")) | O3952: =IF(J3952="","",IF(AND(L3952=0,K3952=0),1,0)) | P3952: =IF(L3952=1,J3952+ROW()/10^7,"") | Q3952: =IF(O3952=1,M3952,"") | R3952: =IF(K3952=1,ROW(),"") | S3952: =IF(D3952="","",TRIM(D3952))
C3953: =IF(S3953="","",IFERROR(IF(INDEX('Ledger Codes'!$C$6:$C$205,MATCH(S3953,'Ledger Codes'!$B$6:$B$205,0))="","",INDEX('Ledger Codes'!$C$6:$C$205,MATCH(S3953,'Ledger Codes'!$B$6:$B$205,0))),"")) | I3953: =IF(AND(G3953="",H3953=""),"",N(G3953)-N(H3953)) | J3953: =IF(I3953="","",ABS(I3953)) | K3953: =IF(S3953="","",0) | L3953: =IF(J3953="","",IF(AND(J3953>'Revenue Testing'!$E$9,K3953=0),1,0)) | M3953: 0.75686621 | N3953: =IF(OR(A3953="",I3953=""),"",IF(COUNTIFS($A$2:$A$4500,A3953,$D$2:$D$4500,D3953,$I$2:$I$4500,I3953)>1,"Possible duplicate","")) | O3953: =IF(J3953="","",IF(AND(L3953=0,K3953=0),1,0)) | P3953: =IF(L3953=1,J3953+ROW()/10^7,"") | Q3953: =IF(O3953=1,M3953,"") | R3953: =IF(K3953=1,ROW(),"") | S3953: =IF(D3953="","",TRIM(D3953))
C3954: =IF(S3954="","",IFERROR(IF(INDEX('Ledger Codes'!$C$6:$C$205,MATCH(S3954,'Ledger Codes'!$B$6:$B$205,0))="","",INDEX('Ledger Codes'!$C$6:$C$205,MATCH(S3954,'Ledger Codes'!$B$6:$B$205,0))),"")) | I3954: =IF(AND(G3954="",H3954=""),"",N(G3954)-N(H3954)) | J3954: =IF(I3954="","",ABS(I3954)) | K3954: =IF(S3954="","",0) | L3954: =IF(J3954="","",IF(AND(J3954>'Revenue Testing'!$E$9,K3954=0),1,0)) | M3954: 0.090472449 | N3954: =IF(OR(A3954="",I3954=""),"",IF(COUNTIFS($A$2:$A$4500,A3954,$D$2:$D$4500,D3954,$I$2:$I$4500,I3954)>1,"Possible duplicate","")) | O3954: =IF(J3954="","",IF(AND(L3954=0,K3954=0),1,0)) | P3954: =IF(L3954=1,J3954+ROW()/10^7,"") | Q3954: =IF(O3954=1,M3954,"") | R3954: =IF(K3954=1,ROW(),"") | S3954: =IF(D3954="","",TRIM(D3954))
C3955: =IF(S3955="","",IFERROR(IF(INDEX('Ledger Codes'!$C$6:$C$205,MATCH(S3955,'Ledger Codes'!$B$6:$B$205,0))="","",INDEX('Ledger Codes'!$C$6:$C$205,MATCH(S3955,'Ledger Codes'!$B$6:$B$205,0))),"")) | I3955: =IF(AND(G3955="",H3955=""),"",N(G3955)-N(H3955)) | J3955: =IF(I3955="","",ABS(I3955)) | K3955: =IF(S3955="","",0) | L3955: =IF(J3955="","",IF(AND(J3955>'Revenue Testing'!$E$9,K3955=0),1,0)) | M3955: 0.27375867 | N3955: =IF(OR(A3955="",I3955=""),"",IF(COUNTIFS($A$2:$A$4500,A3955,$D$2:$D$4500,D3955,$I$2:$I$4500,I3955)>1,"Possible duplicate","")) | O3955: =IF(J3955="","",IF(AND(L3955=0,K3955=0),1,0)) | P3955: =IF(L3955=1,J3955+ROW()/10^7,"") | Q3955: =IF(O3955=1,M3955,"") | R3955: =IF(K3955=1,ROW(),"") | S3955: =IF(D3955="","",TRIM(D3955))
... C4500: =IF(S4500="","",IFERROR(IF(INDEX('Ledger Codes'!$C$6:$C$205,MATCH(S4500,'Ledger Codes'!$B$6:$B$205,0))="","",INDEX('Ledger Codes'!$C$6:$C$205,MATCH(S4500,'Ledger Codes'!$B$6:$B$205,0))),"")) | I4500: =IF(AND(G4500="",H4500=""),"",N(G4500)-N(H4500)) | J4500: =IF(I4500="","",ABS(I4500)) | K4500: =IF(S4500="","",0) | L4500: =IF(J4500="","",IF(AND(J4500>'Revenue Testing'!$E$9,K4500=0),1,0)) | M4500: 0.86754101 | N4500: =IF(OR(A4500="",I4500=""),"",IF(COUNTIFS($A$2:$A$4500,A4500,$D$2:$D$4500,D4500,$I$2:$I$4500,I4500)>1,"Possible duplicate","")) | O4500: =IF(J4500="","",IF(AND(L4500=0,K4500=0),1,0)) | P4500: =IF(L4500=1,J4500+ROW()/10^7,"") | Q4500: =IF(O4500=1,M4500,"") | R4500: =IF(K4500=1,ROW(),"") | S4500: =IF(D4500="","",TRIM(D4500))

Sheet Revenue Testing
A1: Revenue – test of details: audit sample selection
A2: ="Client: "&Materiality!E3&" | Reporting date: "&Materiality!E5 -> Client: LRC | Reporting date: 31 March 2026
A4: MATERIALITY AND SETUP
C5: Test area | E5: Revenue
C6: Sales / revenue considered (SR) | E6: =Materiality!F29 -> 1000000
C7: Materiality percentage applied | E7: =Materiality!G37/100 -> 0.005
C8: Calculated materiality = revenue × % (SR) | E8: =Materiality!H37 -> 5000
C9: Materiality used for sampling (SR) – per Materiality sheet | E9: =Materiality!H42 -> 4000
C10: Risk level for this test (drives the below-materiality sample size) | E10: Low to Moderate (2)
C11: Entity size (drives the maximum sample size) | E11: Medium
C12: Sample size override – leave blank to use the calculated size
A15: BELOW-MATERIALITY SAMPLE SIZE – formula from the 732 template | I15: Maximum sample size table (from 732 template)
C16: Remaining population = eligible items not above materiality (absolute value, SR) | E16: =SUMIF('Revenue Ledger'!$O$2:$O$4500,1,'Revenue Ledger'!$J$2:$J$4500) -> 869423.33 | I16: Risk level \ Entity size | J16: Small | K16: Medium | L16: Large
C17: Planning materiality (SR) | E17: =E9 -> 4000 | I17: Significant (4) | J17: 40 | K17: 50 | L17: 60
C18: Confidence factor (Low 0.25 / Low-Moderate 0.5 / Moderate 0.75 / Significant ~1) | E18: =IF(E10="Low (1)",0.25,IF(E10="Low to Moderate (2)",0.5,IF(E10="Moderate (3)",0.75,IF(E10="Significant (4)",0.999999,0.00001)))) -> 0.5 | I18: Moderate (3) | J18: 30 | K18: 40 | L18: 50
C19: Sampling interval = materiality ÷ confidence factor (SR) | E19: =IFERROR(E17/E18,0) -> 8000 | I19: Low to Moderate (2) | J19: 20 | K19: 30 | L19: 40
C20: Calculated sample size = ROUND(remaining population ÷ interval) | E20: =IFERROR(ROUND(E16/E19,0),0) -> 109 | I20: Low (1) | J20: 15 | K20: 25 | L20: 35
C21: Maximum sample size (risk level × entity size) | E21: =INDEX($J$17:$L$20,MATCH(E10,$I$17:$I$20,0),MATCH(E11,$J$16:$L$16,0)) -> 30
C22: Sample size per template = lower of calculated and maximum | E22: =MIN(E20,E21) -> 30
C23: SAMPLE SIZE USED | E23: =IF(E12<>"",E12,E22) -> 30
A25: SAMPLE SELECTION SUMMARY
C26: Total ledger transactions | E26: =COUNT('Revenue Ledger'!$I$2:$I$4500) -> 3942
C27: Total ledger net amount – original signs (SR) | E27: =SUM('Revenue Ledger'!$I$2:$I$4500) -> -1817812.3
C28: Lines excluded – accounts set to Exclude (already tested) | E28: =COUNTIFS('Revenue Ledger'!$K$2:$K$4500,1) -> 0
C29: Excluded lines – absolute value (SR) | E29: =SUMIF('Revenue Ledger'!$K$2:$K$4500,1,'Revenue Ledger'!$J$2:$J$4500) -> 0
C30: Total eligible transactions | E30: =E26-E28 -> 3942
C31: ABOVE MATERIALITY – items selected, 100% tested | E31: =SUM('Revenue Ledger'!$L$2:$L$4500) -> 34 | G31: View list →
C32: ABOVE MATERIALITY – absolute value (SR) | E32: =SUMIF('Revenue Ledger'!$L$2:$L$4500,1,'Revenue Ledger'!$J$2:$J$4500) -> 982047
C33: BELOW MATERIALITY – eligible population (items) | E33: =SUM('Revenue Ledger'!$O$2:$O$4500) -> 3908
C34: BELOW MATERIALITY – eligible population (absolute value, SR) | E34: =E16 -> 869423.33
C35: BELOW MATERIALITY – sample size used | E35: =E23 -> 30
C36: BELOW MATERIALITY – random samples selected | E36: =MIN(E35,E33) -> 30 | G36: View list →
C37: BELOW MATERIALITY – eligible items not selected | E37: =E33-E36 -> 3878
C38: Above materiality: ABS(amount) > materiality → selected automatically (equal to materiality counts as below).
C39: Below materiality: eligible items → fixed random no. (ledger column M) → sorted high to low → top N. Numbers do not change on recalculation.
A41: VALIDATION CHECKS
C42: 1. Above-materiality completeness (eligible items above materiality = items listed) | E42: =IF(COUNT('Revenue Above'!$A$5:$A$504)=COUNTIFS('Revenue Ledger'!$J$2:$J$4500,">"&$E$9,'Revenue Ledger'!$K$2:$K$4500,0),"PASS","FAIL") -> PASS | F42: ="Expected "&(COUNTIFS('Revenue Ledger'!$J$2:$J$4500,">"&$E$9,'Revenue Ledger'!$K$2:$K$4500,0))&", listed "&COUNT('Revenue Above'!$A$5:$A$504) -> Expected 34, listed 34
C43: 2. Random population = eligible − above materiality | E43: =IF(E33=E30-E31,"PASS","FAIL") -> PASS
C44: 3. No item selected as both above-materiality and random | E44: =IF(COUNTIFS('Revenue Ledger'!$L$2:$L$4500,1,'Revenue Ledger'!$O$2:$O$4500,1)=0,"PASS","FAIL") -> PASS
C45: 4. Excluded accounts appear in neither list | E45: =IF(COUNTIFS('Revenue Ledger'!$K$2:$K$4500,1,'Revenue Ledger'!$L$2:$L$4500,1)+COUNTIFS('Revenue Ledger'!$K$2:$K$4500,1,'Revenue Ledger'!$O$2:$O$4500,1)=0,"PASS","FAIL") -> PASS
C46: 5. Missing data (date / account / amount / description) | E46: =IF((SUMPRODUCT(ISNUMBER('Revenue Ledger'!$I$2:$I$4500)*NOT(ISNUMBER('Revenue Ledger'!$B$2:$B$4500)))+SUMPRODUCT(ISNUMBER('Revenue Ledger'!$I$2:$I$4500)*('Revenue Ledger'!$D$2:$D$4500=""))+SUMPRODUCT(('Revenue Ledger'!$I$2:$I$4500="")*('Revenue Ledger'!$D$2:$D$4500<>""))+SUMPRODUCT(ISNUMBER('Revenue Ledger'!$I$2:$I$4500)*('Revenue Ledger'!$F$2:$F$4500="")))=0,"PASS","REVIEW") -> PASS | F46: ="Date: "&SUMPRODUCT(ISNUMBER('Revenue Ledger'!$I$2:$I$4500)*NOT(ISNUMBER('Revenue Ledger'!$B$2:$B$4500)))&" Account: "&SUMPRODUCT(ISNUMBER('Revenue Ledger'!$I$2:$I$4500)*('Revenue Ledger'!$D$2:$D$4500=""))&" Amount: "&SUMPRODUCT(('Revenue Ledger'!$I$2:$I$4500="")*('Revenue Ledger'!$D$2:$D$4500<>""))&" Description: "&SUMPRODUCT(ISNUMBER('Revenue Ledger'!$I$2:$I$4500)*('Revenue Ledger'!$F$2:$F$4500="")) -> Date: 0 Account: 0 Amount: 0 Description: 0
C47: 6. Source-data integrity (net amount = Σ debit − Σ credit) | E47: =IF(ROUND(SUM('Revenue Ledger'!$I$2:$I$4500)-(SUM('Revenue Ledger'!$G$2:$G$4500)-SUM('Revenue Ledger'!$H$2:$H$4500)),2)=0,"PASS","FAIL") -> PASS
C48: 7. Above-materiality list capacity | E48: =IF(E31<=500,"PASS","FAIL – extend list") -> PASS
C49: 8. Sample size does not exceed eligible population | E49: =IF(E35<=E33,"PASS","REVIEW") -> PASS | F49: =IF(E35>E33,"Sample size capped at the eligible population","")
C50: 9. Below-materiality list capacity | E50: =IF(E36<=100,"PASS","FAIL – extend list") -> PASS
C51: 10. Every ledger line has a ledger code | E51: =IF(SUMPRODUCT(('Revenue Ledger'!$S$2:$S$4500<>"")*('Revenue Ledger'!$C$2:$C$4500=""))=0,"PASS","REVIEW") -> PASS | F51: =SUMPRODUCT(('Revenue Ledger'!$S$2:$S$4500<>"")*('Revenue Ledger'!$C$2:$C$4500=""))&" line(s) without a ledger code – see Ledger Codes sheet" -> 0 line(s) without a ledger code – see Ledger Codes sheet

Sheet Revenue Above
A1: REVENUE – ABOVE MATERIALITY: ALL ITEMS TESTED (100%)
A2: ="Materiality used: SR "&TEXT('Revenue Testing'!E9,"#,##0")&" | Items selected: "&'Revenue Testing'!E31&" | Absolute value: SR "&TEXT('Revenue Testing'!E32,"#,##0.00")&" | Largest to smallest" -> Materiality used: SR 4,000 | Items selected: 34 | Absolute value: SR 982,047.00 | Largest to smallest
A3: Back to summary: Revenue Testing
A4: Sample No. | B4: Date | C4: Ledger Code | D4: Ledger / Account | E4: Description | F4: Original Amount | G4: Absolute Amount | H4: Materiality | I4: Selection Basis | J4: Ledger row | K4: Voucher Ref | L4: Test result | M4: Comments
A5: =IF(ROWS($A$5:A5)<='Revenue Testing'!$E$31,ROWS($A$5:A5),"") -> 1 | B5: =IF($A5="","",INDEX('Revenue Ledger'!$B$1:$B$4500,$J5)) -> 45991 | C5: =IF($A5="","",INDEX('Revenue Ledger'!$C$1:$C$4500,$J5)) -> 10077 | D5: =IF($A5="","",INDEX('Revenue Ledger'!$D$1:$D$4500,$J5)) -> SLOT CHARGES- INC | E5: =IF($A5="","",INDEX('Revenue Ledger'!$F$1:$F$4500,$J5)&"") -> 2601002-SLOT CHARGES- SOA NOV 2025- CSTAR ARAP REF - 2601002 | F5: =IF($A5="","",INDEX('Revenue Ledger'!$I$1:$I$4500,$J5)) -> -377812.5 | G5: =IF($A5="","",INDEX('Revenue Ledger'!$J$1:$J$4500,$J5)) -> 377812.5 | H5: =IF($A5="","",'Revenue Testing'!$E$9) -> 4000 | I5: =IF($A5="","","Above materiality – automatically selected") -> Above materiality – automatically selected | J5: =IF($A5="","",MATCH(LARGE('Revenue Ledger'!$P$2:$P$4500,$A5),'Revenue Ledger'!$P$2:$P$4500,0)+1) -> 3906 | K5: =IF($A5="","",INDEX('Revenue Ledger'!$A$1:$A$4500,$J5)&"") -> SJAMS0552/25
A6: =IF(ROWS($A$5:A6)<='Revenue Testing'!$E$31,ROWS($A$5:A6),"") -> 2 | B6: =IF($A6="","",INDEX('Revenue Ledger'!$B$1:$B$4500,$J6)) -> 46022 | C6: =IF($A6="","",INDEX('Revenue Ledger'!$C$1:$C$4500,$J6)) -> 10059 | D6: =IF($A6="","",INDEX('Revenue Ledger'!$D$1:$D$4500,$J6)) -> INCOME-SEA FREIGHT EXPORT FCL | E6: =IF($A6="","",INDEX('Revenue Ledger'!$F$1:$F$4500,$J6)&"") -> Service : SEA FREIGHT EXPORT FCL | F6: =IF($A6="","",INDEX('Revenue Ledger'!$I$1:$I$4500,$J6)) -> -165750 | G6: =IF($A6="","",INDEX('Revenue Ledger'!$J$1:$J$4500,$J6)) -> 165750 | H6: =IF($A6="","",'Revenue Testing'!$E$9) -> 4000 | I6: =IF($A6="","","Above materiality – automatically selected") -> Above materiality – automatically selected | J6: =IF($A6="","",MATCH(LARGE('Revenue Ledger'!$P$2:$P$4500,$A6),'Revenue Ledger'!$P$2:$P$4500,0)+1) -> 3915 | K6: =IF($A6="","",INDEX('Revenue Ledger'!$A$1:$A$4500,$J6)&"") -> GJAMS0089/25
A7: =IF(ROWS($A$5:A7)<='Revenue Testing'!$E$31,ROWS($A$5:A7),"") -> 3 | B7: =IF($A7="","",INDEX('Revenue Ledger'!$B$1:$B$4500,$J7)) -> 45909 | C7: =IF($A7="","",INDEX('Revenue Ledger'!$C$1:$C$4500,$J7)) -> 10056 | D7: =IF($A7="","",INDEX('Revenue Ledger'!$D$1:$D$4500,$J7)) -> RESTOW CHARGES - INC | E7: =IF($A7="","",INDEX('Revenue Ledger'!$F$1:$F$4500,$J7)&"") -> RSGT- 2331988- CSTAR VOYAGER FRS01W- RESTOW CHARGES- DISCH RESTOW- 30X20 @ SAR 200 & 242X40 @ SAR 300 LOAD RESTOW 30X20 @ SAR 200 & 242X40 @ SAR 300 ARAP REF - 2331988 | F7: =IF($A7="","",INDEX('Revenue Ledger'!$I$1:$I$4500,$J7)) -> -157200 | G7: =IF($A7="","",INDEX('Revenue Ledger'!$J$1:$J$4500,$J7)) -> 157200 | H7: =IF($A7="","",'Revenue Testing'!$E$9) -> 4000 | I7: =IF($A7="","","Above materiality – automatically selected") -> Above materiality – automatically selected | J7: =IF($A7="","",MATCH(LARGE('Revenue Ledger'!$P$2:$P$4500,$A7),'Revenue Ledger'!$P$2:$P$4500,0)+1) -> 3904 | K7: =IF($A7="","",INDEX('Revenue Ledger'!$A$1:$A$4500,$J7)&"") -> SJAMS0543/25
A8: =IF(ROWS($A$5:A8)<='Revenue Testing'!$E$31,ROWS($A$5:A8),"") -> 4 | B8: =IF($A8="","",INDEX('Revenue Ledger'!$B$1:$B$4500,$J8)) -> 45914 | C8: =IF($A8="","",INDEX('Revenue Ledger'!$C$1:$C$4500,$J8)) -> 10047 | D8: =IF($A8="","",INDEX('Revenue Ledger'!$D$1:$D$4500,$J8)) -> BERTHING & UNBERTHING CHARGES- INC | E8: =IF($A8="","",INDEX('Revenue Ledger'!$F$1:$F$4500,$J8)&"") -> WESTERN COAST -1025013361- BERTHING & UNBERTHING CHGS- SAR 8228.2X2 & SAR 4000 BERTH DUES- CSTAR VOYAGER FRS01W ARAP REF - 1025013361 | F8: =IF($A8="","",INDEX('Revenue Ledger'!$I$1:$I$4500,$J8)) -> -20456.4 | G8: =IF($A8="","",INDEX('Revenue Ledger'!$J$1:$J$4500,$J8)) -> 20456.4 | H8: =IF($A8="","",'Revenue Testing'!$E$9) -> 4000 | I8: =IF($A8="","","Above materiality – automatically selected") -> Above materiality – automatically selected | J8: =IF($A8="","",MATCH(LARGE('Revenue Ledger'!$P$2:$P$4500,$A8),'Revenue Ledger'!$P$2:$P$4500,0)+1) -> 21 | K8: =IF($A8="","",INDEX('Revenue Ledger'!$A$1:$A$4500,$J8)&"") -> SJAMS0545/25
A9: =IF(ROWS($A$5:A9)<='Revenue Testing'!$E$31,ROWS($A$5:A9),"") -> 5 | B9: =IF($A9="","",INDEX('Revenue Ledger'!$B$1:$B$4500,$J9)) -> 45959 | C9: =IF($A9="","",INDEX('Revenue Ledger'!$C$1:$C$4500,$J9)) -> 10047 | D9: =IF($A9="","",INDEX('Revenue Ledger'!$D$1:$D$4500,$J9)) -> BERTHING & UNBERTHING CHARGES- INC | E9: =IF($A9="","",INDEX('Revenue Ledger'!$F$1:$F$4500,$J9)&"") -> WESTERN COAST- 1025014651- BERTHING AND UNBERTHING CHGS- NZ SUZHOU FRS04E ARAP REF - 1025014651 | F9: =IF($A9="","",INDEX('Revenue Ledger'!$I$1:$I$4500,$J9)) -> -18755.2 | G9: =IF($A9="","",INDEX('Revenue Ledger'!$J$1:$J$4500,$J9)) -> 18755.2 | H9: =IF($A9="","",'Revenue Testing'!$E$9) -> 4000 | I9: =IF($A9="","","Above materiality – automatically selected") -> Above materiality – automatically selected | J9: =IF($A9="","",MATCH(LARGE('Revenue Ledger'!$P$2:$P$4500,$A9),'Revenue Ledger'!$P$2:$P$4500,0)+1) -> 25 | K9: =IF($A9="","",INDEX('Revenue Ledger'!$A$1:$A$4500,$J9)&"") -> SJAMS0559/25
A10: =IF(ROWS($A$5:A10)<='Revenue Testing'!$E$31,ROWS($A$5:A10),"") -> 6 | B10: =IF($A10="","",INDEX('Revenue Ledger'!$B$1:$B$4500,$J10)) -> 45929 | C10: =IF($A10="","",INDEX('Revenue Ledger'!$C$1:$C$4500,$J10)) -> 10047 | D10: =IF($A10="","",INDEX('Revenue Ledger'!$D$1:$D$4500,$J10)) -> BERTHING & UNBERTHING CHARGES- INC | E10: =IF($A10="","",INDEX('Revenue Ledger'!$F$1:$F$4500,$J10)&"") -> WESTERN COAST- 1025013889- BERHTING AND UNBERTHING CHGS- CSTAR VOYAGER OCT SOA ARAP REF - 1025013889 | F10: =IF($A10="","",INDEX('Revenue Ledger'!$I$1:$I$4500,$J10)) -> -18456.4 | G10: =IF($A10="","",INDEX('Revenue Ledger'!$J$1:$J$4500,$J10)) -> 18456.4 | H10: =IF($A10="","",'Revenue Testing'!$E$9) -> 4000 | I10: =IF($A10="","","Above materiality – automatically selected") -> Above materiality – automatically selected | J10: =IF($A10="","",MATCH(LARGE('Revenue Ledger'!$P$2:$P$4500,$A10),'Revenue Ledger'!$P$2:$P$4500,0)+1) -> 24 | K10: =IF($A10="","",INDEX('Revenue Ledger'!$A$1:$A$4500,$J10)&"") -> SJAMS0558/25
A11: =IF(ROWS($A$5:A11)<='Revenue Testing'!$E$31,ROWS($A$5:A11),"") -> 7 | B11: =IF($A11="","",INDEX('Revenue Ledger'!$B$1:$B$4500,$J11)) -> 45918 | C11: =IF($A11="","",INDEX('Revenue Ledger'!$C$1:$C$4500,$J11)) -> 10047 | D11: =IF($A11="","",INDEX('Revenue Ledger'!$D$1:$D$4500,$J11)) -> BERTHING & UNBERTHING CHARGES- INC | E11: =IF($A11="","",INDEX('Revenue Ledger'!$F$1:$F$4500,$J11)&"") -> WEST COAST- 1025013568- NZ SUZHOU FRS03W- BERTHING & UNBERTHING CHGS SAR 7934X2 & SAR 2000 BERTH DUES ARAP REF - 1025013568 | F11: =IF($A11="","",INDEX('Revenue Ledger'!$I$1:$I$4500,$J11)) -> -17868 | G11: =IF($A11="","",INDEX('Revenue Ledger'!$J$1:$J$4500,$J11)) -> 17868 | H11: =IF($A11="","",'Revenue Testing'!$E$9) -> 4000 | I11: =IF($A11="","","Above materiality – automatically selected") -> Above materiality – automatically selected | J11: =IF($A11="","",MATCH(LARGE('Revenue Ledger'!$P$2:$P$4500,$A11),'Revenue Ledger'!$P$2:$P$4500,0)+1) -> 23 | K11: =IF($A11="","",INDEX('Revenue Ledger'!$A$1:$A$4500,$J11)&"") -> SJAMS0544/25
A12: =IF(ROWS($A$5:A12)<='Revenue Testing'!$E$31,ROWS($A$5:A12),"") -> 8 | B12: =IF($A12="","",INDEX('Revenue Ledger'!$B$1:$B$4500,$J12)) -> 45914 | C12: =IF($A12="","",INDEX('Revenue Ledger'!$C$1:$C$4500,$J12)) -> 10047 | D12: =IF($A12="","",INDEX('Revenue Ledger'!$D$1:$D$4500,$J12)) -> BERTHING & UNBERTHING CHARGES- INC | E12: =IF($A12="","",INDEX('Revenue Ledger'!$F$1:$F$4500,$J12)&"") -> WESTERN COAST- 1025013362- BERTHING & UNBERTHING- NZ SUZHOU FRS01E- SAR 7934X2 & SAR 2000 BERTH DUES ARAP REF - 1025013362 | F12: =IF($A12="","",INDEX('Revenue Ledger'!$I$1:$I$4500,$J12)) -> -17868 | G12: =IF($A12="","",INDEX('Revenue Ledger'!$J$1:$J$4500,$J12)) -> 17868 | H12: =IF($A12="","",'Revenue Testing'!$E$9) -> 4000 | I12: =IF($A12="","","Above materiality – automatically selected") -> Above materiality – automatically selected | J12: =IF($A12="","",MATCH(LARGE('Revenue Ledger'!$P$2:$P$4500,$A12),'Revenue Ledger'!$P$2:$P$4500,0)+1) -> 22 | K12: =IF($A12="","",INDEX('Revenue Ledger'!$A$1:$A$4500,$J12)&"") -> SJAMS0546/25
A13: =IF(ROWS($A$5:A13)<='Revenue Testing'!$E$31,ROWS($A$5:A13),"") -> 9 | B13: =IF($A13="","",INDEX('Revenue Ledger'!$B$1:$B$4500,$J13)) -> 45930 | C13: =IF($A13="","",INDEX('Revenue Ledger'!$C$1:$C$4500,$J13)) -> 10069 | D13: =IF($A13="","",INDEX('Revenue Ledger'!$D$1:$D$4500,$J13)) -> AGENCY COMMISSION IMPORT- INC | E13: =IF($A13="","",INDEX('Revenue Ledger'!$F$1:$F$4500,$J13)&"") -> IMPORT AGENCY COMMISSION- SEP 2025- CSTAR | F13: =IF($A13="","",INDEX('Revenue Ledger'!$I$1:$I$4500,$J13)) -> -15525 | G13: =IF($A13="","",INDEX('Revenue Ledger'!$J$1:$J$4500,$J13)) -> 15525 | H13: =IF($A13="","",'Revenue Testing'!$E$9) -> 4000 | I13: =IF($A13="","","Above materiality – automatically selected") -> Above materiality – automatically selected | J13: =IF($A13="","",MATCH(LARGE('Revenue Ledger'!$P$2:$P$4500,$A13),'Revenue Ledger'!$P$2:$P$4500,0)+1) -> 7 | K13: =IF($A13="","",INDEX('Revenue Ledger'!$A$1:$A$4500,$J13)&"") -> DNAMS0012/25
A14: =IF(ROWS($A$5:A14)<='Revenue Testing'!$E$31,ROWS($A$5:A14),"") -> 10 | B14: =IF($A14="","",INDEX('Revenue Ledger'!$B$1:$B$4500,$J14)) -> 45961 | C14: =IF($A14="","",INDEX('Revenue Ledger'!$C$1:$C$4500,$J14)) -> 10069 | D14: =IF($A14="","",INDEX('Revenue Ledger'!$D$1:$D$4500,$J14)) -> AGENCY COMMISSION IMPORT- INC | E14: =IF($A14="","",INDEX('Revenue Ledger'!$F$1:$F$4500,$J14)&"") -> IMPORT AGENCY COMMISSION- OCT 2025- CSTAR | F14: =IF($A14="","",INDEX('Revenue Ledger'!$I$1:$I$4500,$J14)) -> -14250 | G14: =IF($A14="","",INDEX('Revenue Ledger'!$J$1:$J$4500,$J14)) -> 14250 | H14: =IF($A14="","",'Revenue Testing'!$E$9) -> 4000 | I14: =IF($A14="","","Above materiality – automatically selected") -> Above materiality – automatically selected | J14: =IF($A14="","",MATCH(LARGE('Revenue Ledger'!$P$2:$P$4500,$A14),'Revenue Ledger'!$P$2:$P$4500,0)+1) -> 9 | K14: =IF($A14="","",INDEX('Revenue Ledger'!$A$1:$A$4500,$J14)&"") -> DNAMS0014/25
A15: =IF(ROWS($A$5:A15)<='Revenue Testing'!$E$31,ROWS($A$5:A15),"") -> 11 | B15: =IF($A15="","",INDEX('Revenue Ledger'!$B$1:$B$4500,$J15)) -> 45930 | C15: =IF($A15="","",INDEX('Revenue Ledger'!$C$1:$C$4500,$J15)) -> 10070 | D15: =IF($A15="","",INDEX('Revenue Ledger'!$D$1:$D$4500,$J15)) -> AGENCY COMMISSION- T/S HANDLING | E15: =IF($A15="","",INDEX('Revenue Ledger'!$F$1:$F$4500,$J15)&"") -> T/S AGENCY COMMISSION- SEP 2025- CSTAR | F15: =IF($A15="","",INDEX('Revenue Ledger'!$I$1:$I$4500,$J15)) -> -11756.25 | G15: =IF($A15="","",INDEX('Revenue Ledger'!$J$1:$J$4500,$J15)) -> 11756.25 | H15: =IF($A15="","",'Revenue Testing'!$E$9) -> 4000 | I15: =IF($A15="","","Above materiality – automatically selected") -> Above materiality – automatically selected | J15: =IF($A15="","",MATCH(LARGE('Revenue Ledger'!$P$2:$P$4500,$A15),'Revenue Ledger'!$P$2:$P$4500,0)+1) -> 13 | K15: =IF($A15="","",INDEX('Revenue Ledger'!$A$1:$A$4500,$J15)&"") -> DNAMS0013/25
A16: =IF(ROWS($A$5:A16)<='Revenue Testing'!$E$31,ROWS($A$5:A16),"") -> 12 | B16: =IF($A16="","",INDEX('Revenue Ledger'!$B$1:$B$4500,$J16)) -> 45963 | C16: =IF($A16="","",INDEX('Revenue Ledger'!$C$1:$C$4500,$J16)) -> 10065 | D16: =IF($A16="","",INDEX('Revenue Ledger'!$D$1:$D$4500,$J16)) -> TRANSPORTATION CHARGES | E16: =IF($A16="","",INDEX('Revenue Ledger'!$F$1:$F$4500,$J16)&"") -> FREIGHT WORLD- JSI-25-3574- TRANSPORTATION CHARGES ARAP REF - JSI-25-3574 | F16: =IF($A16="","",INDEX('Revenue Ledger'!$I$1:$I$4500,$J16)) -> -11333.25 | G16: =IF($A16="","",INDEX('Revenue Ledger'!$J$1:$J$4500,$J16)) -> 11333.25 | H16: =IF($A16="","",'Revenue Testing'!$E$9) -> 4000 | I16: =IF($A16="","","Above materiality – automatically selected") -> Above materiality – automatically selected | J16: =IF($A16="","",MATCH(LARGE('Revenue Ledger'!$P$2:$P$4500,$A16),'Revenue Ledger'!$P$2:$P$4500,0)+1) -> 3937 | K16: =IF($A16="","",INDEX('Revenue Ledger'!$A$1:$A$4500,$J16)&"") -> SJAMS0565/25
... A504: =IF(ROWS($A$5:A504)<='Revenue Testing'!$E$31,ROWS($A$5:A504),"") | B504: =IF($A504="","",INDEX('Revenue Ledger'!$B$1:$B$4500,$J504)) | C504: =IF($A504="","",INDEX('Revenue Ledger'!$C$1:$C$4500,$J504)) | D504: =IF($A504="","",INDEX('Revenue Ledger'!$D$1:$D$4500,$J504)) | E504: =IF($A504="","",INDEX('Revenue Ledger'!$F$1:$F$4500,$J504)&"") | F504: =IF($A504="","",INDEX('Revenue Ledger'!$I$1:$I$4500,$J504)) | G504: =IF($A504="","",INDEX('Revenue Ledger'!$J$1:$J$4500,$J504)) | H504: =IF($A504="","",'Revenue Testing'!$E$9) | I504: =IF($A504="","","Above materiality – automatically selected") | J504: =IF($A504="","",MATCH(LARGE('Revenue Ledger'!$P$2:$P$4500,$A504),'Revenue Ledger'!$P$2:$P$4500,0)+1) | K504: =IF($A504="","",INDEX('Revenue Ledger'!$A$1:$A$4500,$J504)&"")
E505: Total | F505: =SUM(F5:F504) -> -966387 | G505: =SUM(G5:G504) -> 982047

Sheet Revenue Below
A1: REVENUE – BELOW MATERIALITY: RANDOM SAMPLE
A2: ="Sample: "&'Revenue Testing'!E36&" of "&'Revenue Testing'!E33&" eligible items | Risk level: "&'Revenue Testing'!E10&" / "&'Revenue Testing'!E11&" entity | Population value: SR "&TEXT('Revenue Testing'!E34,"#,##0.00")&" | Random number high to low" -> Sample: 30 of 3908 eligible items | Risk level: Low to Moderate (2) / Medium entity | Population value: SR 869,423.33 | Random number high to low
A3: Back to summary: Revenue Testing
A4: Sample No. | B4: Date | C4: Ledger Code | D4: Ledger / Account | E4: Description | F4: Original Amount | G4: Absolute Amount | H4: Random Number | I4: Materiality | J4: Selection Basis | K4: Ledger row | L4: Voucher Ref | M4: Test result | N4: Comments
A5: =IF(ROWS($A$5:A5)<='Revenue Testing'!$E$36,ROWS($A$5:A5),"") -> 1 | B5: =IF($A5="","",INDEX('Revenue Ledger'!$B$1:$B$4500,$K5)) -> 45905 | C5: =IF($A5="","",INDEX('Revenue Ledger'!$C$1:$C$4500,$K5)) -> 10049 | D5: =IF($A5="","",INDEX('Revenue Ledger'!$D$1:$D$4500,$K5)) -> CONTAINER GATE PASS FEE- INC | E5: =IF($A5="","",INDEX('Revenue Ledger'!$F$1:$F$4500,$K5)&"") -> NVOIMP Against the IMP BOL - CSDSHA033050; Customer Ref: ;Remarks: | F5: =IF($A5="","",INDEX('Revenue Ledger'!$I$1:$I$4500,$K5)) -> -600 | G5: =IF($A5="","",INDEX('Revenue Ledger'!$J$1:$J$4500,$K5)) -> 600 | H5: =IF($A5="","",INDEX('Revenue Ledger'!$M$1:$M$4500,$K5)) -> 0.99995915 | I5: =IF($A5="","",'Revenue Testing'!$E$9) -> 4000 | J5: =IF($A5="","","Below materiality – randomly selected") -> Below materiality – randomly selected | K5: =IF($A5="","",MATCH(LARGE('Revenue Ledger'!$Q$2:$Q$4500,$A5),'Revenue Ledger'!$Q$2:$Q$4500,0)+1) -> 229 | L5: =IF($A5="","",INDEX('Revenue Ledger'!$A$1:$A$4500,$K5)&"") -> SJAMS0073/25
A6: =IF(ROWS($A$5:A6)<='Revenue Testing'!$E$36,ROWS($A$5:A6),"") -> 2 | B6: =IF($A6="","",INDEX('Revenue Ledger'!$B$1:$B$4500,$K6)) -> 45922 | C6: =IF($A6="","",INDEX('Revenue Ledger'!$C$1:$C$4500,$K6)) -> 10068 | D6: =IF($A6="","",INDEX('Revenue Ledger'!$D$1:$D$4500,$K6)) -> EDI CHARGES- INC | E6: =IF($A6="","",INDEX('Revenue Ledger'!$F$1:$F$4500,$K6)&"") -> NVOIMP Against the IMP BOL - CCJEAJED25099079; Customer Ref: ;Remarks: | F6: =IF($A6="","",INDEX('Revenue Ledger'!$I$1:$I$4500,$K6)) -> -30 | G6: =IF($A6="","",INDEX('Revenue Ledger'!$J$1:$J$4500,$K6)) -> 30 | H6: =IF($A6="","",INDEX('Revenue Ledger'!$M$1:$M$4500,$K6)) -> 0.99965092 | I6: =IF($A6="","",'Revenue Testing'!$E$9) -> 4000 | J6: =IF($A6="","","Below materiality – randomly selected") -> Below materiality – randomly selected | K6: =IF($A6="","",MATCH(LARGE('Revenue Ledger'!$Q$2:$Q$4500,$A6),'Revenue Ledger'!$Q$2:$Q$4500,0)+1) -> 1375 | L6: =IF($A6="","",INDEX('Revenue Ledger'!$A$1:$A$4500,$K6)&"") -> SJAMS0269/25
A7: =IF(ROWS($A$5:A7)<='Revenue Testing'!$E$36,ROWS($A$5:A7),"") -> 3 | B7: =IF($A7="","",INDEX('Revenue Ledger'!$B$1:$B$4500,$K7)) -> 45952 | C7: =IF($A7="","",INDEX('Revenue Ledger'!$C$1:$C$4500,$K7)) -> 10054 | D7: =IF($A7="","",INDEX('Revenue Ledger'!$D$1:$D$4500,$K7)) -> PHOTO CHARGES- INC | E7: =IF($A7="","",INDEX('Revenue Ledger'!$F$1:$F$4500,$K7)&"") -> NVOIMP Against the IMP BOL - CSDSHA034141; Customer Ref: ;Remarks: | F7: =IF($A7="","",INDEX('Revenue Ledger'!$I$1:$I$4500,$K7)) -> -20 | G7: =IF($A7="","",INDEX('Revenue Ledger'!$J$1:$J$4500,$K7)) -> 20 | H7: =IF($A7="","",INDEX('Revenue Ledger'!$M$1:$M$4500,$K7)) -> 0.99956449 | I7: =IF($A7="","",'Revenue Testing'!$E$9) -> 4000 | J7: =IF($A7="","","Below materiality – randomly selected") -> Below materiality – randomly selected | K7: =IF($A7="","",MATCH(LARGE('Revenue Ledger'!$Q$2:$Q$4500,$A7),'Revenue Ledger'!$Q$2:$Q$4500,0)+1) -> 3708 | L7: =IF($A7="","",INDEX('Revenue Ledger'!$A$1:$A$4500,$K7)&"") -> SJAMS0332/25
A8: =IF(ROWS($A$5:A8)<='Revenue Testing'!$E$36,ROWS($A$5:A8),"") -> 4 | B8: =IF($A8="","",INDEX('Revenue Ledger'!$B$1:$B$4500,$K8)) -> 45904 | C8: =IF($A8="","",INDEX('Revenue Ledger'!$C$1:$C$4500,$K8)) -> 10066 | D8: =IF($A8="","",INDEX('Revenue Ledger'!$D$1:$D$4500,$K8)) -> FASAH CHARGES- INC | E8: =IF($A8="","",INDEX('Revenue Ledger'!$F$1:$F$4500,$K8)&"") -> NVOIMP Against the IMP BOL - CSDSHA032811; Customer Ref: ;Remarks: | F8: =IF($A8="","",INDEX('Revenue Ledger'!$I$1:$I$4500,$K8)) -> -8.63 | G8: =IF($A8="","",INDEX('Revenue Ledger'!$J$1:$J$4500,$K8)) -> 8.63 | H8: =IF($A8="","",INDEX('Revenue Ledger'!$M$1:$M$4500,$K8)) -> 0.99937593 | I8: =IF($A8="","",'Revenue Testing'!$E$9) -> 4000 | J8: =IF($A8="","","Below materiality – randomly selected") -> Below materiality – randomly selected | K8: =IF($A8="","",MATCH(LARGE('Revenue Ledger'!$Q$2:$Q$4500,$A8),'Revenue Ledger'!$Q$2:$Q$4500,0)+1) -> 1803 | L8: =IF($A8="","",INDEX('Revenue Ledger'!$A$1:$A$4500,$K8)&"") -> SJAMS0404/25
A9: =IF(ROWS($A$5:A9)<='Revenue Testing'!$E$36,ROWS($A$5:A9),"") -> 5 | B9: =IF($A9="","",INDEX('Revenue Ledger'!$B$1:$B$4500,$K9)) -> 45944 | C9: =IF($A9="","",INDEX('Revenue Ledger'!$C$1:$C$4500,$K9)) -> 10049 | D9: =IF($A9="","",INDEX('Revenue Ledger'!$D$1:$D$4500,$K9)) -> CONTAINER GATE PASS FEE- INC | E9: =IF($A9="","",INDEX('Revenue Ledger'!$F$1:$F$4500,$K9)&"") -> NVOIMP Against the IMP BOL - CSDSHA033229; Customer Ref: ;Remarks: | F9: =IF($A9="","",INDEX('Revenue Ledger'!$I$1:$I$4500,$K9)) -> -120 | G9: =IF($A9="","",INDEX('Revenue Ledger'!$J$1:$J$4500,$K9)) -> 120 | H9: =IF($A9="","",INDEX('Revenue Ledger'!$M$1:$M$4500,$K9)) -> 0.99920498 | I9: =IF($A9="","",'Revenue Testing'!$E$9) -> 4000 | J9: =IF($A9="","","Below materiality – randomly selected") -> Below materiality – randomly selected | K9: =IF($A9="","",MATCH(LARGE('Revenue Ledger'!$Q$2:$Q$4500,$A9),'Revenue Ledger'!$Q$2:$Q$4500,0)+1) -> 320 | L9: =IF($A9="","",INDEX('Revenue Ledger'!$A$1:$A$4500,$K9)&"") -> SJAMS0096/25
A10: =IF(ROWS($A$5:A10)<='Revenue Testing'!$E$36,ROWS($A$5:A10),"") -> 6 | B10: =IF($A10="","",INDEX('Revenue Ledger'!$B$1:$B$4500,$K10)) -> 45960 | C10: =IF($A10="","",INDEX('Revenue Ledger'!$C$1:$C$4500,$K10)) -> 10068 | D10: =IF($A10="","",INDEX('Revenue Ledger'!$D$1:$D$4500,$K10)) -> EDI CHARGES- INC | E10: =IF($A10="","",INDEX('Revenue Ledger'!$F$1:$F$4500,$K10)&"") -> NVOIMP Against the IMP BOL - CSDIST002925; Customer Ref: ;Remarks: | F10: =IF($A10="","",INDEX('Revenue Ledger'!$I$1:$I$4500,$K10)) -> -30 | G10: =IF($A10="","",INDEX('Revenue Ledger'!$J$1:$J$4500,$K10)) -> 30 | H10: =IF($A10="","",INDEX('Revenue Ledger'!$M$1:$M$4500,$K10)) -> 0.99884957 | I10: =IF($A10="","",'Revenue Testing'!$E$9) -> 4000 | J10: =IF($A10="","","Below materiality – randomly selected") -> Below materiality – randomly selected | K10: =IF($A10="","",MATCH(LARGE('Revenue Ledger'!$Q$2:$Q$4500,$A10),'Revenue Ledger'!$Q$2:$Q$4500,0)+1) -> 1621 | L10: =IF($A10="","",INDEX('Revenue Ledger'!$A$1:$A$4500,$K10)&"") -> SJAMS0579/25
A11: =IF(ROWS($A$5:A11)<='Revenue Testing'!$E$36,ROWS($A$5:A11),"") -> 7 | B11: =IF($A11="","",INDEX('Revenue Ledger'!$B$1:$B$4500,$K11)) -> 45953 | C11: =IF($A11="","",INDEX('Revenue Ledger'!$C$1:$C$4500,$K11)) -> 10066 | D11: =IF($A11="","",INDEX('Revenue Ledger'!$D$1:$D$4500,$K11)) -> FASAH CHARGES- INC | E11: =IF($A11="","",INDEX('Revenue Ledger'!$F$1:$F$4500,$K11)&"") -> NVOIMP Against the IMP BOL - CSDSHA033757; Customer Ref: ;Remarks: | F11: =IF($A11="","",INDEX('Revenue Ledger'!$I$1:$I$4500,$K11)) -> -8.63 | G11: =IF($A11="","",INDEX('Revenue Ledger'!$J$1:$J$4500,$K11)) -> 8.63 | H11: =IF($A11="","",INDEX('Revenue Ledger'!$M$1:$M$4500,$K11)) -> 0.99867403 | I11: =IF($A11="","",'Revenue Testing'!$E$9) -> 4000 | J11: =IF($A11="","","Below materiality – randomly selected") -> Below materiality – randomly selected | K11: =IF($A11="","",MATCH(LARGE('Revenue Ledger'!$Q$2:$Q$4500,$A11),'Revenue Ledger'!$Q$2:$Q$4500,0)+1) -> 2073 | L11: =IF($A11="","",INDEX('Revenue Ledger'!$A$1:$A$4500,$K11)&"") -> SJAMS0194/25
A12: =IF(ROWS($A$5:A12)<='Revenue Testing'!$E$36,ROWS($A$5:A12),"") -> 8 | B12: =IF($A12="","",INDEX('Revenue Ledger'!$B$1:$B$4500,$K12)) -> 45905 | C12: =IF($A12="","",INDEX('Revenue Ledger'!$C$1:$C$4500,$K12)) -> 10066 | D12: =IF($A12="","",INDEX('Revenue Ledger'!$D$1:$D$4500,$K12)) -> FASAH CHARGES- INC | E12: =IF($A12="","",INDEX('Revenue Ledger'!$F$1:$F$4500,$K12)&"") -> NVOIMP Against the IMP BOL - CSDSHA033554; Customer Ref: ;Remarks: | F12: =IF($A12="","",INDEX('Revenue Ledger'!$I$1:$I$4500,$K12)) -> -8.63 | G12: =IF($A12="","",INDEX('Revenue Ledger'!$J$1:$J$4500,$K12)) -> 8.63 | H12: =IF($A12="","",INDEX('Revenue Ledger'!$M$1:$M$4500,$K12)) -> 0.99846781 | I12: =IF($A12="","",'Revenue Testing'!$E$9) -> 4000 | J12: =IF($A12="","","Below materiality – randomly selected") -> Below materiality – randomly selected | K12: =IF($A12="","",MATCH(LARGE('Revenue Ledger'!$Q$2:$Q$4500,$A12),'Revenue Ledger'!$Q$2:$Q$4500,0)+1) -> 1829 | L12: =IF($A12="","",INDEX('Revenue Ledger'!$A$1:$A$4500,$K12)&"") -> SJAMS0419/25
A13: =IF(ROWS($A$5:A13)<='Revenue Testing'!$E$36,ROWS($A$5:A13),"") -> 9 | B13: =IF($A13="","",INDEX('Revenue Ledger'!$B$1:$B$4500,$K13)) -> 45953 | C13: =IF($A13="","",INDEX('Revenue Ledger'!$C$1:$C$4500,$K13)) -> 10066 | D13: =IF($A13="","",INDEX('Revenue Ledger'!$D$1:$D$4500,$K13)) -> FASAH CHARGES- INC | E13: =IF($A13="","",INDEX('Revenue Ledger'!$F$1:$F$4500,$K13)&"") -> NVOIMP Against the IMP BOL - CSDSHA033984; Customer Ref: ;Remarks: | F13: =IF($A13="","",INDEX('Revenue Ledger'!$I$1:$I$4500,$K13)) -> -8.63 | G13: =IF($A13="","",INDEX('Revenue Ledger'!$J$1:$J$4500,$K13)) -> 8.63 | H13: =IF($A13="","",INDEX('Revenue Ledger'!$M$1:$M$4500,$K13)) -> 0.99839422 | I13: =IF($A13="","",'Revenue Testing'!$E$9) -> 4000 | J13: =IF($A13="","","Below materiality – randomly selected") -> Below materiality – randomly selected | K13: =IF($A13="","",MATCH(LARGE('Revenue Ledger'!$Q$2:$Q$4500,$A13),'Revenue Ledger'!$Q$2:$Q$4500,0)+1) -> 2090 | L13: =IF($A13="","",INDEX('Revenue Ledger'!$A$1:$A$4500,$K13)&"") -> SJAMS0263/25
A14: =IF(ROWS($A$5:A14)<='Revenue Testing'!$E$36,ROWS($A$5:A14),"") -> 10 | B14: =IF($A14="","",INDEX('Revenue Ledger'!$B$1:$B$4500,$K14)) -> 45952 | C14: =IF($A14="","",INDEX('Revenue Ledger'!$C$1:$C$4500,$K14)) -> 10068 | D14: =IF($A14="","",INDEX('Revenue Ledger'!$D$1:$D$4500,$K14)) -> EDI CHARGES- INC | E14: =IF($A14="","",INDEX('Revenue Ledger'!$F$1:$F$4500,$K14)&"") -> NVOIMP Against the IMP BOL - CSDSHA034029; Customer Ref: ;Remarks: | F14: =IF($A14="","",INDEX('Revenue Ledger'!$I$1:$I$4500,$K14)) -> -30 | G14: =IF($A14="","",INDEX('Revenue Ledger'!$J$1:$J$4500,$K14)) -> 30 | H14: =IF($A14="","",INDEX('Revenue Ledger'!$M$1:$M$4500,$K14)) -> 0.99832349 | I14: =IF($A14="","",'Revenue Testing'!$E$9) -> 4000 | J14: =IF($A14="","","Below materiality – randomly selected") -> Below materiality – randomly selected | K14: =IF($A14="","",MATCH(LARGE('Revenue Ledger'!$Q$2:$Q$4500,$A14),'Revenue Ledger'!$Q$2:$Q$4500,0)+1) -> 1510 | L14: =IF($A14="","",INDEX('Revenue Ledger'!$A$1:$A$4500,$K14)&"") -> SJAMS0294/25
A15: =IF(ROWS($A$5:A15)<='Revenue Testing'!$E$36,ROWS($A$5:A15),"") -> 11 | B15: =IF($A15="","",INDEX('Revenue Ledger'!$B$1:$B$4500,$K15)) -> 45952 | C15: =IF($A15="","",INDEX('Revenue Ledger'!$C$1:$C$4500,$K15)) -> 10054 | D15: =IF($A15="","",INDEX('Revenue Ledger'!$D$1:$D$4500,$K15)) -> PHOTO CHARGES- INC | E15: =IF($A15="","",INDEX('Revenue Ledger'!$F$1:$F$4500,$K15)&"") -> NVOIMP Against the IMP BOL - CSDSHA034052; Customer Ref: ;Remarks: | F15: =IF($A15="","",INDEX('Revenue Ledger'!$I$1:$I$4500,$K15)) -> -20 | G15: =IF($A15="","",INDEX('Revenue Ledger'!$J$1:$J$4500,$K15)) -> 20 | H15: =IF($A15="","",INDEX('Revenue Ledger'!$M$1:$M$4500,$K15)) -> 0.9982602 | I15: =IF($A15="","",'Revenue Testing'!$E$9) -> 4000 | J15: =IF($A15="","","Below materiality – randomly selected") -> Below materiality – randomly selected | K15: =IF($A15="","",MATCH(LARGE('Revenue Ledger'!$Q$2:$Q$4500,$A15),'Revenue Ledger'!$Q$2:$Q$4500,0)+1) -> 3690 | L15: =IF($A15="","",INDEX('Revenue Ledger'!$A$1:$A$4500,$K15)&"") -> SJAMS0304/25
A16: =IF(ROWS($A$5:A16)<='Revenue Testing'!$E$36,ROWS($A$5:A16),"") -> 12 | B16: =IF($A16="","",INDEX('Revenue Ledger'!$B$1:$B$4500,$K16)) -> 45952 | C16: =IF($A16="","",INDEX('Revenue Ledger'!$C$1:$C$4500,$K16)) -> 10049 | D16: =IF($A16="","",INDEX('Revenue Ledger'!$D$1:$D$4500,$K16)) -> CONTAINER GATE PASS FEE- INC | E16: =IF($A16="","",INDEX('Revenue Ledger'!$F$1:$F$4500,$K16)&"") -> NVOIMP Against the IMP BOL - CSDSHA033762; Customer Ref: ;Remarks: | F16: =IF($A16="","",INDEX('Revenue Ledger'!$I$1:$I$4500,$K16)) -> -120 | G16: =IF($A16="","",INDEX('Revenue Ledger'!$J$1:$J$4500,$K16)) -> 120 | H16: =IF($A16="","",INDEX('Revenue Ledger'!$M$1:$M$4500,$K16)) -> 0.99825332 | I16: =IF($A16="","",'Revenue Testing'!$E$9) -> 4000 | J16: =IF($A16="","","Below materiality – randomly selected") -> Below materiality – randomly selected | K16: =IF($A16="","",MATCH(LARGE('Revenue Ledger'!$Q$2:$Q$4500,$A16),'Revenue Ledger'!$Q$2:$Q$4500,0)+1) -> 407 | L16: =IF($A16="","",INDEX('Revenue Ledger'!$A$1:$A$4500,$K16)&"") -> SJAMS0199/25
... A104: =IF(ROWS($A$5:A104)<='Revenue Testing'!$E$36,ROWS($A$5:A104),"") | B104: =IF($A104="","",INDEX('Revenue Ledger'!$B$1:$B$4500,$K104)) | C104: =IF($A104="","",INDEX('Revenue Ledger'!$C$1:$C$4500,$K104)) | D104: =IF($A104="","",INDEX('Revenue Ledger'!$D$1:$D$4500,$K104)) | E104: =IF($A104="","",INDEX('Revenue Ledger'!$F$1:$F$4500,$K104)&"") | F104: =IF($A104="","",INDEX('Revenue Ledger'!$I$1:$I$4500,$K104)) | G104: =IF($A104="","",INDEX('Revenue Ledger'!$J$1:$J$4500,$K104)) | H104: =IF($A104="","",INDEX('Revenue Ledger'!$M$1:$M$4500,$K104)) | I104: =IF($A104="","",'Revenue Testing'!$E$9) | J104: =IF($A104="","","Below materiality – randomly selected") | K104: =IF($A104="","",MATCH(LARGE('Revenue Ledger'!$Q$2:$Q$4500,$A104),'Revenue Ledger'!$Q$2:$Q$4500,0)+1) | L104: =IF($A104="","",INDEX('Revenue Ledger'!$A$1:$A$4500,$K104)&"")
E105: Total | F105: =SUM(F5:F104) -> -4500.15 | G105: =SUM(G5:G104) -> 4500.15

Sheet COGS Ledger
A1: Voucher Ref | B1: Date | C1: Ledger Code | D1: Ledger Name | E1: ArAp Ref | F1: Description (Remarks) | G1: Debit | H1: Credit | I1: Original Amount (Dr − Cr) | J1: Absolute Amount | K1: Excluded – account set to Exclude (1 = yes) | L1: Above materiality – selected (1 = yes) | M1: Random No. (fixed) | N1: Possible duplicate | O1: Below-materiality eligible pop. (1 = yes) | P1: Rank key – above | Q1: Rank key – random | R1: Excluded-record key | S1: Account key (trimmed)
A2: PJAMS0031/25 | B2: 45914 | C2: =IF(S2="","",IFERROR(IF(INDEX('Ledger Codes'!$C$6:$C$205,MATCH(S2,'Ledger Codes'!$B$6:$B$205,0))="","",INDEX('Ledger Codes'!$C$6:$C$205,MATCH(S2,'Ledger Codes'!$B$6:$B$205,0))),"")) -> 10047 | D2: BERTHING & UNBERTHING CHARGES- EXP | E2: 1025013361 | F2: PJ Ref:AMSLAP0006/25 ; WESTERN COAST -1025013361- BERTHING & UNBERTHING CHGS- SAR 8228.2X2 & SAR 4000 BERTH DUES | G2: 20456.4 | H2: 0 | I2: =IF(AND(G2="",H2=""),"",N(G2)-N(H2)) -> 20456.4 | J2: =IF(I2="","",ABS(I2)) -> 20456.4 | K2: =IF(S2="","",0) -> 0 | L2: =IF(J2="","",IF(AND(J2>'COGS Testing'!$E$9,K2=0),1,0)) -> 1 | M2: 0.76536615 | N2: =IF(OR(A2="",I2=""),"",IF(COUNTIFS($A$2:$A$400,A2,$D$2:$D$400,D2,$I$2:$I$400,I2)>1,"Possible duplicate","")) | O2: =IF(J2="","",IF(AND(L2=0,K2=0),1,0)) -> 0 | P2: =IF(L2=1,J2+ROW()/10^7,"") -> 20456.4 | Q2: =IF(O2=1,M2,"") | R2: =IF(K2=1,ROW(),"") | S2: =IF(D2="","",TRIM(D2)) -> BERTHING & UNBERTHING CHARGES- EXP
A3: PJAMS0032/25 | B3: 45914 | C3: =IF(S3="","",IFERROR(IF(INDEX('Ledger Codes'!$C$6:$C$205,MATCH(S3,'Ledger Codes'!$B$6:$B$205,0))="","",INDEX('Ledger Codes'!$C$6:$C$205,MATCH(S3,'Ledger Codes'!$B$6:$B$205,0))),"")) -> 10047 | D3: BERTHING & UNBERTHING CHARGES- EXP | E3: 1025013362 | F3: PJ Ref:AMSLAP0007/25 ; WESTERN COAST- 1025013362- BERTHING & UNBERTHING- NZ SUZHOU FRS01E- SAR 7934X2 & SAR 2000 BERTH DUES | G3: 17868 | H3: 0 | I3: =IF(AND(G3="",H3=""),"",N(G3)-N(H3)) -> 17868 | J3: =IF(I3="","",ABS(I3)) -> 17868 | K3: =IF(S3="","",0) -> 0 | L3: =IF(J3="","",IF(AND(J3>'COGS Testing'!$E$9,K3=0),1,0)) -> 1 | M3: 0.79296822 | N3: =IF(OR(A3="",I3=""),"",IF(COUNTIFS($A$2:$A$400,A3,$D$2:$D$400,D3,$I$2:$I$400,I3)>1,"Possible duplicate","")) | O3: =IF(J3="","",IF(AND(L3=0,K3=0),1,0)) -> 0 | P3: =IF(L3=1,J3+ROW()/10^7,"") -> 17868 | Q3: =IF(O3=1,M3,"") | R3: =IF(K3=1,ROW(),"") | S3: =IF(D3="","",TRIM(D3)) -> BERTHING & UNBERTHING CHARGES- EXP
A4: PJAMS0030/25 | B4: 45918 | C4: =IF(S4="","",IFERROR(IF(INDEX('Ledger Codes'!$C$6:$C$205,MATCH(S4,'Ledger Codes'!$B$6:$B$205,0))="","",INDEX('Ledger Codes'!$C$6:$C$205,MATCH(S4,'Ledger Codes'!$B$6:$B$205,0))),"")) -> 10047 | D4: BERTHING & UNBERTHING CHARGES- EXP | E4: 1025013568 | F4: PJ Ref:AMSLAP0005/25 ; WEST COAST- 1025013568- NZ SUZHOU FRS03W- BERTHING & UNBERTHING CHGS SAR 7934X2 & SAR 2000 BERTH DUES | G4: 17868 | H4: 0 | I4: =IF(AND(G4="",H4=""),"",N(G4)-N(H4)) -> 17868 | J4: =IF(I4="","",ABS(I4)) -> 17868 | K4: =IF(S4="","",0) -> 0 | L4: =IF(J4="","",IF(AND(J4>'COGS Testing'!$E$9,K4=0),1,0)) -> 1 | M4: 0.13618994 | N4: =IF(OR(A4="",I4=""),"",IF(COUNTIFS($A$2:$A$400,A4,$D$2:$D$400,D4,$I$2:$I$400,I4)>1,"Possible duplicate","")) | O4: =IF(J4="","",IF(AND(L4=0,K4=0),1,0)) -> 0 | P4: =IF(L4=1,J4+ROW()/10^7,"") -> 17868 | Q4: =IF(O4=1,M4,"") | R4: =IF(K4=1,ROW(),"") | S4: =IF(D4="","",TRIM(D4)) -> BERTHING & UNBERTHING CHARGES- EXP
A5: PJAMS0102/25 | B5: 45929 | C5: =IF(S5="","",IFERROR(IF(INDEX('Ledger Codes'!$C$6:$C$205,MATCH(S5,'Ledger Codes'!$B$6:$B$205,0))="","",INDEX('Ledger Codes'!$C$6:$C$205,MATCH(S5,'Ledger Codes'!$B$6:$B$205,0))),"")) -> 10047 | D5: BERTHING & UNBERTHING CHARGES- EXP | E5: 1025013889 | F5: PJ Ref:AMSLAP0038/25 ; WESTERN COAST- 1025013889- BERTHING & UNBERTHING CHGS- CSTAR VOYAGER | G5: 18456 | H5: 0 | I5: =IF(AND(G5="",H5=""),"",N(G5)-N(H5)) -> 18456 | J5: =IF(I5="","",ABS(I5)) -> 18456 | K5: =IF(S5="","",0) -> 0 | L5: =IF(J5="","",IF(AND(J5>'COGS Testing'!$E$9,K5=0),1,0)) -> 1 | M5: 0.89287869 | N5: =IF(OR(A5="",I5=""),"",IF(COUNTIFS($A$2:$A$400,A5,$D$2:$D$400,D5,$I$2:$I$400,I5)>1,"Possible duplicate","")) | O5: =IF(J5="","",IF(AND(L5=0,K5=0),1,0)) -> 0 | P5: =IF(L5=1,J5+ROW()/10^7,"") -> 18456 | Q5: =IF(O5=1,M5,"") | R5: =IF(K5=1,ROW(),"") | S5: =IF(D5="","",TRIM(D5)) -> BERTHING & UNBERTHING CHARGES- EXP
A6: PJAMS0103/25 | B6: 45959 | C6: =IF(S6="","",IFERROR(IF(INDEX('Ledger Codes'!$C$6:$C$205,MATCH(S6,'Ledger Codes'!$B$6:$B$205,0))="","",INDEX('Ledger Codes'!$C$6:$C$205,MATCH(S6,'Ledger Codes'!$B$6:$B$205,0))),"")) -> 10047 | D6: BERTHING & UNBERTHING CHARGES- EXP | E6: 1025014651 | F6: PJ Ref:AMSLAP0039/25 ; WESTERN COAST- 1025014651- BERTHING AND UNBERTHING CHARGES- NZ SZUHOU FRS04E | G6: 18755.2 | H6: 0 | I6: =IF(AND(G6="",H6=""),"",N(G6)-N(H6)) -> 18755.2 | J6: =IF(I6="","",ABS(I6)) -> 18755.2 | K6: =IF(S6="","",0) -> 0 | L6: =IF(J6="","",IF(AND(J6>'COGS Testing'!$E$9,K6=0),1,0)) -> 1 | M6: 0.83254524 | N6: =IF(OR(A6="",I6=""),"",IF(COUNTIFS($A$2:$A$400,A6,$D$2:$D$400,D6,$I$2:$I$400,I6)>1,"Possible duplicate","")) | O6: =IF(J6="","",IF(AND(L6=0,K6=0),1,0)) -> 0 | P6: =IF(L6=1,J6+ROW()/10^7,"") -> 18755.2 | Q6: =IF(O6=1,M6,"") | R6: =IF(K6=1,ROW(),"") | S6: =IF(D6="","",TRIM(D6)) -> BERTHING & UNBERTHING CHARGES- EXP
A7: PJAMS0174/25 | B7: 45988 | C7: =IF(S7="","",IFERROR(IF(INDEX('Ledger Codes'!$C$6:$C$205,MATCH(S7,'Ledger Codes'!$B$6:$B$205,0))="","",INDEX('Ledger Codes'!$C$6:$C$205,MATCH(S7,'Ledger Codes'!$B$6:$B$205,0))),"")) -> 10047 | D7: BERTHING & UNBERTHING CHARGES- EXP | E7: JD-11196- 1025015309 | F7: PJ Ref:AMSLAP0054/25 ; WESTERN COAST- INV 1025015309- JD- 11196- SAVI SHIPPING DEPARTURE, BERTHING AND UNBERTHING CHARGES | G7: 13685.14 | H7: 0 | I7: =IF(AND(G7="",H7=""),"",N(G7)-N(H7)) -> 13685.14 | J7: =IF(I7="","",ABS(I7)) -> 13685.14 | K7: =IF(S7="","",0) -> 0 | L7: =IF(J7="","",IF(AND(J7>'COGS Testing'!$E$9,K7=0),1,0)) -> 1 | M7: 0.82827586 | N7: =IF(OR(A7="",I7=""),"",IF(COUNTIFS($A$2:$A$400,A7,$D$2:$D$400,D7,$I$2:$I$400,I7)>1,"Possible duplicate","")) | O7: =IF(J7="","",IF(AND(L7=0,K7=0),1,0)) -> 0 | P7: =IF(L7=1,J7+ROW()/10^7,"") -> 13685.14 | Q7: =IF(O7=1,M7,"") | R7: =IF(K7=1,ROW(),"") | S7: =IF(D7="","",TRIM(D7)) -> BERTHING & UNBERTHING CHARGES- EXP
A8: SJAMS0139/25 | B8: 45995 | C8: =IF(S8="","",IFERROR(IF(INDEX('Ledger Codes'!$C$6:$C$205,MATCH(S8,'Ledger Codes'!$B$6:$B$205,0))="","",INDEX('Ledger Codes'!$C$6:$C$205,MATCH(S8,'Ledger Codes'!$B$6:$B$205,0))),"")) -> 10047 | D8: BERTHING & UNBERTHING CHARGES- EXP | E8: ALMJDH/00005/202512 | F8: AN YANG 2514W- BERTHING, UNBERTHING, DEPARTURE & HANDLING CHARGES | G8: 0 | H8: 13685.14 | I8: =IF(AND(G8="",H8=""),"",N(G8)-N(H8)) -> -13685.14 | J8: =IF(I8="","",ABS(I8)) -> 13685.14 | K8: =IF(S8="","",0) -> 0 | L8: =IF(J8="","",IF(AND(J8>'COGS Testing'!$E$9,K8=0),1,0)) -> 1 | M8: 0.70794879 | N8: =IF(OR(A8="",I8=""),"",IF(COUNTIFS($A$2:$A$400,A8,$D$2:$D$400,D8,$I$2:$I$400,I8)>1,"Possible duplicate","")) | O8: =IF(J8="","",IF(AND(L8=0,K8=0),1,0)) -> 0 | P8: =IF(L8=1,J8+ROW()/10^7,"") -> 13685.14 | Q8: =IF(O8=1,M8,"") | R8: =IF(K8=1,ROW(),"") | S8: =IF(D8="","",TRIM(D8)) -> BERTHING & UNBERTHING CHARGES- EXP
A9: PJAMS0054/25 | B9: 45935 | C9: =IF(S9="","",IFERROR(IF(INDEX('Ledger Codes'!$C$6:$C$205,MATCH(S9,'Ledger Codes'!$B$6:$B$205,0))="","",INDEX('Ledger Codes'!$C$6:$C$205,MATCH(S9,'Ledger Codes'!$B$6:$B$205,0))),"")) -> 10048 | D9: CONTAINER DAMAGE CHARGES- COST | E9: 3217 | F9: PJ Ref:AMSLAP0026/25 ; CNTR DMG CHARGES- EMCU3778261 | G9: 150 | H9: 0 | I9: =IF(AND(G9="",H9=""),"",N(G9)-N(H9)) -> 150 | J9: =IF(I9="","",ABS(I9)) -> 150 | K9: =IF(S9="","",0) -> 0 | L9: =IF(J9="","",IF(AND(J9>'COGS Testing'!$E$9,K9=0),1,0)) -> 0 | M9: 0.96811716 | N9: =IF(OR(A9="",I9=""),"",IF(COUNTIFS($A$2:$A$400,A9,$D$2:$D$400,D9,$I$2:$I$400,I9)>1,"Possible duplicate","")) | O9: =IF(J9="","",IF(AND(L9=0,K9=0),1,0)) -> 1 | P9: =IF(L9=1,J9+ROW()/10^7,"") | Q9: =IF(O9=1,M9,"") -> 0.96811716 | R9: =IF(K9=1,ROW(),"") | S9: =IF(D9="","",TRIM(D9)) -> CONTAINER DAMAGE CHARGES- COST
A10: PJAMS0055/25 | B10: 45935 | C10: =IF(S10="","",IFERROR(IF(INDEX('Ledger Codes'!$C$6:$C$205,MATCH(S10,'Ledger Codes'!$B$6:$B$205,0))="","",INDEX('Ledger Codes'!$C$6:$C$205,MATCH(S10,'Ledger Codes'!$B$6:$B$205,0))),"")) -> 10048 | D10: CONTAINER DAMAGE CHARGES- COST | E10: 3220 | F10: PJ Ref:AMSLAP0027/25 ; INV 3220- CNTR DMG CHGS | G10: 6050 | H10: 0 | I10: =IF(AND(G10="",H10=""),"",N(G10)-N(H10)) -> 6050 | J10: =IF(I10="","",ABS(I10)) -> 6050 | K10: =IF(S10="","",0) -> 0 | L10: =IF(J10="","",IF(AND(J10>'COGS Testing'!$E$9,K10=0),1,0)) -> 1 | M10: 0.81709471 | N10: =IF(OR(A10="",I10=""),"",IF(COUNTIFS($A$2:$A$400,A10,$D$2:$D$400,D10,$I$2:$I$400,I10)>1,"Possible duplicate","")) | O10: =IF(J10="","",IF(AND(L10=0,K10=0),1,0)) -> 0 | P10: =IF(L10=1,J10+ROW()/10^7,"") -> 6050 | Q10: =IF(O10=1,M10,"") | R10: =IF(K10=1,ROW(),"") | S10: =IF(D10="","",TRIM(D10)) -> CONTAINER DAMAGE CHARGES- COST
A11: PJAMS0045/25 | B11: 45963 | C11: =IF(S11="","",IFERROR(IF(INDEX('Ledger Codes'!$C$6:$C$205,MATCH(S11,'Ledger Codes'!$B$6:$B$205,0))="","",INDEX('Ledger Codes'!$C$6:$C$205,MATCH(S11,'Ledger Codes'!$B$6:$B$205,0))),"")) -> 10048 | D11: CONTAINER DAMAGE CHARGES- COST | E11: 3573 | F11: PJ Ref:AMSLAP0017/25 ; CONTAINER DAMAGE CHARGES CSTAR | G11: 3350 | H11: 0 | I11: =IF(AND(G11="",H11=""),"",N(G11)-N(H11)) -> 3350 | J11: =IF(I11="","",ABS(I11)) -> 3350 | K11: =IF(S11="","",0) -> 0 | L11: =IF(J11="","",IF(AND(J11>'COGS Testing'!$E$9,K11=0),1,0)) -> 0 | M11: 0.90164602 | N11: =IF(OR(A11="",I11=""),"",IF(COUNTIFS($A$2:$A$400,A11,$D$2:$D$400,D11,$I$2:$I$400,I11)>1,"Possible duplicate","")) | O11: =IF(J11="","",IF(AND(L11=0,K11=0),1,0)) -> 1 | P11: =IF(L11=1,J11+ROW()/10^7,"") | Q11: =IF(O11=1,M11,"") -> 0.90164602 | R11: =IF(K11=1,ROW(),"") | S11: =IF(D11="","",TRIM(D11)) -> CONTAINER DAMAGE CHARGES- COST
A12: PJAMS0056/25 | B12: 45994 | C12: =IF(S12="","",IFERROR(IF(INDEX('Ledger Codes'!$C$6:$C$205,MATCH(S12,'Ledger Codes'!$B$6:$B$205,0))="","",INDEX('Ledger Codes'!$C$6:$C$205,MATCH(S12,'Ledger Codes'!$B$6:$B$205,0))),"")) -> 10048 | D12: CONTAINER DAMAGE CHARGES- COST | E12: 4049 | F12: PJ Ref:AMSLAP0028/25 ; INV 4049- CNTR DMG CHARGES | G12: 5850 | H12: 0 | I12: =IF(AND(G12="",H12=""),"",N(G12)-N(H12)) -> 5850 | J12: =IF(I12="","",ABS(I12)) -> 5850 | K12: =IF(S12="","",0) -> 0 | L12: =IF(J12="","",IF(AND(J12>'COGS Testing'!$E$9,K12=0),1,0)) -> 1 | M12: 0.41817664 | N12: =IF(OR(A12="",I12=""),"",IF(COUNTIFS($A$2:$A$400,A12,$D$2:$D$400,D12,$I$2:$I$400,I12)>1,"Possible duplicate","")) | O12: =IF(J12="","",IF(AND(L12=0,K12=0),1,0)) -> 0 | P12: =IF(L12=1,J12+ROW()/10^7,"") -> 5850 | Q12: =IF(O12=1,M12,"") | R12: =IF(K12=1,ROW(),"") | S12: =IF(D12="","",TRIM(D12)) -> CONTAINER DAMAGE CHARGES- COST
A13: PJAMS0145/25 | B13: 45928 | C13: =IF(S13="","",IFERROR(IF(INDEX('Ledger Codes'!$C$6:$C$205,MATCH(S13,'Ledger Codes'!$B$6:$B$205,0))="","",INDEX('Ledger Codes'!$C$6:$C$205,MATCH(S13,'Ledger Codes'!$B$6:$B$205,0))),"")) -> 10049 | D13: CONTAINER GATE PASS FEE- EXP | E13: 2346718 | F13: RSGT- 2346718- GFS PERFECT - GFPT0069E- CAPELINE CONTAINERS GATE CHARGES- 1X40'- SAR 120 LOAD EXPORT LADEN DG- 1X40'- SAR 525- THC OCR PHOTO- SAR 20 RENOMINATION- SAR 35 | G13: 120 | H13: 0 | I13: =IF(AND(G13="",H13=""),"",N(G13)-N(H13)) -> 120 | J13: =IF(I13="","",ABS(I13)) -> 120 | K13: =IF(S13="","",0) -> 0 | L13: =IF(J13="","",IF(AND(J13>'COGS Testing'!$E$9,K13=0),1,0)) -> 0 | M13: 0.077895017 | N13: =IF(OR(A13="",I13=""),"",IF(COUNTIFS($A$2:$A$400,A13,$D$2:$D$400,D13,$I$2:$I$400,I13)>1,"Possible duplicate","")) | O13: =IF(J13="","",IF(AND(L13=0,K13=0),1,0)) -> 1 | P13: =IF(L13=1,J13+ROW()/10^7,"") | Q13: =IF(O13=1,M13,"") -> 0.077895017 | R13: =IF(K13=1,ROW(),"") | S13: =IF(D13="","",TRIM(D13)) -> CONTAINER GATE PASS FEE- EXP
... A159: SJAMS0560/25 | B159: 45958 | C159: =IF(S159="","",IFERROR(IF(INDEX('Ledger Codes'!$C$6:$C$205,MATCH(S159,'Ledger Codes'!$B$6:$B$205,0))="","",INDEX('Ledger Codes'!$C$6:$C$205,MATCH(S159,'Ledger Codes'!$B$6:$B$205,0))),"")) -> 10082 | D159: SURVEY CHARGES | E159: AMSLAS0017/25 | F159: MARINE SERVICES- SSI-JED08-10-25-96- SURVEY CHARGES FOR VESSEL NZ NINGBO OCTOBER VESSEL- CSTAR ARAP REF - SSI-JED08-10-25-96 | G159: 0 | H159: 3018.75 | I159: =IF(AND(G159="",H159=""),"",N(G159)-N(H159)) -> -3018.75 | J159: =IF(I159="","",ABS(I159)) -> 3018.75 | K159: =IF(S159="","",0) -> 0 | L159: =IF(J159="","",IF(AND(J159>'COGS Testing'!$E$9,K159=0),1,0)) -> 0 | M159: 0.75657284 | N159: =IF(OR(A159="",I159=""),"",IF(COUNTIFS($A$2:$A$400,A159,$D$2:$D$400,D159,$I$2:$I$400,I159)>1,"Possible duplicate","")) | O159: =IF(J159="","",IF(AND(L159=0,K159=0),1,0)) -> 1 | P159: =IF(L159=1,J159+ROW()/10^7,"") | Q159: =IF(O159=1,M159,"") -> 0.75657284 | R159: =IF(K159=1,ROW(),"") | S159: =IF(D159="","",TRIM(D159)) -> SURVEY CHARGES
A160: GJAMS0081/25 | B160: 46011 | C160: =IF(S160="","",IFERROR(IF(INDEX('Ledger Codes'!$C$6:$C$205,MATCH(S160,'Ledger Codes'!$B$6:$B$205,0))="","",INDEX('Ledger Codes'!$C$6:$C$205,MATCH(S160,'Ledger Codes'!$B$6:$B$205,0))),"")) -> 10088 | D160: W/O EXPENSES | F160: BEING FASAH CHARGES TRF TO W/O ITEMS FOR AL-RAQI HOME TRADING COMPANY-REC - (SUNDRY DEBTORS) SAR 17.26 | G160: 17.26 | H160: 0 | I160: =IF(AND(G160="",H160=""),"",N(G160)-N(H160)) -> 17.26 | J160: =IF(I160="","",ABS(I160)) -> 17.26 | K160: =IF(S160="","",0) -> 0 | L160: =IF(J160="","",IF(AND(J160>'COGS Testing'!$E$9,K160=0),1,0)) -> 0 | M160: 0.69327144 | N160: =IF(OR(A160="",I160=""),"",IF(COUNTIFS($A$2:$A$400,A160,$D$2:$D$400,D160,$I$2:$I$400,I160)>1,"Possible duplicate","")) | O160: =IF(J160="","",IF(AND(L160=0,K160=0),1,0)) -> 1 | P160: =IF(L160=1,J160+ROW()/10^7,"") | Q160: =IF(O160=1,M160,"") -> 0.69327144 | R160: =IF(K160=1,ROW(),"") | S160: =IF(D160="","",TRIM(D160)) -> W/O EXPENSES
A161: GJAMS0075/25 | B161: 46022 | C161: =IF(S161="","",IFERROR(IF(INDEX('Ledger Codes'!$C$6:$C$205,MATCH(S161,'Ledger Codes'!$B$6:$B$205,0))="","",INDEX('Ledger Codes'!$C$6:$C$205,MATCH(S161,'Ledger Codes'!$B$6:$B$205,0))),"")) -> 10088 | D161: W/O EXPENSES | G161: 1692.35 | H161: 0 | I161: =IF(AND(G161="",H161=""),"",N(G161)-N(H161)) -> 1692.35 | J161: =IF(I161="","",ABS(I161)) -> 1692.35 | K161: =IF(S161="","",0) -> 0 | L161: =IF(J161="","",IF(AND(J161>'COGS Testing'!$E$9,K161=0),1,0)) -> 0 | M161: 0.27388841 | N161: =IF(OR(A161="",I161=""),"",IF(COUNTIFS($A$2:$A$400,A161,$D$2:$D$400,D161,$I$2:$I$400,I161)>1,"Possible duplicate","")) | O161: =IF(J161="","",IF(AND(L161=0,K161=0),1,0)) -> 1 | P161: =IF(L161=1,J161+ROW()/10^7,"") | Q161: =IF(O161=1,M161,"") -> 0.27388841 | R161: =IF(K161=1,ROW(),"") | S161: =IF(D161="","",TRIM(D161)) -> W/O EXPENSES
A162: GJAMS0075/25 | B162: 46022 | C162: =IF(S162="","",IFERROR(IF(INDEX('Ledger Codes'!$C$6:$C$205,MATCH(S162,'Ledger Codes'!$B$6:$B$205,0))="","",INDEX('Ledger Codes'!$C$6:$C$205,MATCH(S162,'Ledger Codes'!$B$6:$B$205,0))),"")) -> 10088 | D162: W/O EXPENSES | G162: 0.03 | H162: 0 | I162: =IF(AND(G162="",H162=""),"",N(G162)-N(H162)) -> 0.03 | J162: =IF(I162="","",ABS(I162)) -> 0.03 | K162: =IF(S162="","",0) -> 0 | L162: =IF(J162="","",IF(AND(J162>'COGS Testing'!$E$9,K162=0),1,0)) -> 0 | M162: 0.76415248 | N162: =IF(OR(A162="",I162=""),"",IF(COUNTIFS($A$2:$A$400,A162,$D$2:$D$400,D162,$I$2:$I$400,I162)>1,"Possible duplicate","")) | O162: =IF(J162="","",IF(AND(L162=0,K162=0),1,0)) -> 1 | P162: =IF(L162=1,J162+ROW()/10^7,"") | Q162: =IF(O162=1,M162,"") -> 0.76415248 | R162: =IF(K162=1,ROW(),"") | S162: =IF(D162="","",TRIM(D162)) -> W/O EXPENSES
A163: GJAMS0075/25 | B163: 46022 | C163: =IF(S163="","",IFERROR(IF(INDEX('Ledger Codes'!$C$6:$C$205,MATCH(S163,'Ledger Codes'!$B$6:$B$205,0))="","",INDEX('Ledger Codes'!$C$6:$C$205,MATCH(S163,'Ledger Codes'!$B$6:$B$205,0))),"")) -> 10088 | D163: W/O EXPENSES | G163: 1230.84 | H163: 0 | I163: =IF(AND(G163="",H163=""),"",N(G163)-N(H163)) -> 1230.84 | J163: =IF(I163="","",ABS(I163)) -> 1230.84 | K163: =IF(S163="","",0) -> 0 | L163: =IF(J163="","",IF(AND(J163>'COGS Testing'!$E$9,K163=0),1,0)) -> 0 | M163: 0.96664363 | N163: =IF(OR(A163="",I163=""),"",IF(COUNTIFS($A$2:$A$400,A163,$D$2:$D$400,D163,$I$2:$I$400,I163)>1,"Possible duplicate","")) | O163: =IF(J163="","",IF(AND(L163=0,K163=0),1,0)) -> 1 | P163: =IF(L163=1,J163+ROW()/10^7,"") | Q163: =IF(O163=1,M163,"") -> 0.96664363 | R163: =IF(K163=1,ROW(),"") | S163: =IF(D163="","",TRIM(D163)) -> W/O EXPENSES
A164: GJAMS0076/25 | B164: 46022 | C164: =IF(S164="","",IFERROR(IF(INDEX('Ledger Codes'!$C$6:$C$205,MATCH(S164,'Ledger Codes'!$B$6:$B$205,0))="","",INDEX('Ledger Codes'!$C$6:$C$205,MATCH(S164,'Ledger Codes'!$B$6:$B$205,0))),"")) -> 10088 | D164: W/O EXPENSES | F164: BEING BALANCE PAYABLE OR RECEIVABLE W/O FOR DEBTORS AND CREDITORS AS ON 31ST DEC 2025 | G164: 0 | H164: 1 | I164: =IF(AND(G164="",H164=""),"",N(G164)-N(H164)) -> -1 | J164: =IF(I164="","",ABS(I164)) -> 1 | K164: =IF(S164="","",0) -> 0 | L164: =IF(J164="","",IF(AND(J164>'COGS Testing'!$E$9,K164=0),1,0)) -> 0 | M164: 0.92416576 | N164: =IF(OR(A164="",I164=""),"",IF(COUNTIFS($A$2:$A$400,A164,$D$2:$D$400,D164,$I$2:$I$400,I164)>1,"Possible duplicate","")) | O164: =IF(J164="","",IF(AND(L164=0,K164=0),1,0)) -> 1 | P164: =IF(L164=1,J164+ROW()/10^7,"") | Q164: =IF(O164=1,M164,"") -> 0.92416576 | R164: =IF(K164=1,ROW(),"") | S164: =IF(D164="","",TRIM(D164)) -> W/O EXPENSES
A165: GJAMS0076/25 | B165: 46022 | C165: =IF(S165="","",IFERROR(IF(INDEX('Ledger Codes'!$C$6:$C$205,MATCH(S165,'Ledger Codes'!$B$6:$B$205,0))="","",INDEX('Ledger Codes'!$C$6:$C$205,MATCH(S165,'Ledger Codes'!$B$6:$B$205,0))),"")) -> 10088 | D165: W/O EXPENSES | F165: BEING BALANCE PAYABLE OR RECEIVABLE W/O FOR DEBTORS AND CREDITORS AS ON 31ST DEC 2025 | G165: 0 | H165: 77.48 | I165: =IF(AND(G165="",H165=""),"",N(G165)-N(H165)) -> -77.48 | J165: =IF(I165="","",ABS(I165)) -> 77.48 | K165: =IF(S165="","",0) -> 0 | L165: =IF(J165="","",IF(AND(J165>'COGS Testing'!$E$9,K165=0),1,0)) -> 0 | M165: 0.89515828 | N165: =IF(OR(A165="",I165=""),"",IF(COUNTIFS($A$2:$A$400,A165,$D$2:$D$400,D165,$I$2:$I$400,I165)>1,"Possible duplicate","")) | O165: =IF(J165="","",IF(AND(L165=0,K165=0),1,0)) -> 1 | P165: =IF(L165=1,J165+ROW()/10^7,"") | Q165: =IF(O165=1,M165,"") -> 0.89515828 | R165: =IF(K165=1,ROW(),"") | S165: =IF(D165="","",TRIM(D165)) -> W/O EXPENSES
A166: GJAMS0082/25 | B166: 46022 | C166: =IF(S166="","",IFERROR(IF(INDEX('Ledger Codes'!$C$6:$C$205,MATCH(S166,'Ledger Codes'!$B$6:$B$205,0))="","",INDEX('Ledger Codes'!$C$6:$C$205,MATCH(S166,'Ledger Codes'!$B$6:$B$205,0))),"")) -> 10088 | D166: W/O EXPENSES | F166: BEING TRF OF FASAH CHGS SAR 60.41 TO W/O ITEMS FOR BIN DAWOOF SUPERSTORES | G166: 60.41 | H166: 0 | I166: =IF(AND(G166="",H166=""),"",N(G166)-N(H166)) -> 60.41 | J166: =IF(I166="","",ABS(I166)) -> 60.41 | K166: =IF(S166="","",0) -> 0 | L166: =IF(J166="","",IF(AND(J166>'COGS Testing'!$E$9,K166=0),1,0)) -> 0 | M166: 0.60262758 | N166: =IF(OR(A166="",I166=""),"",IF(COUNTIFS($A$2:$A$400,A166,$D$2:$D$400,D166,$I$2:$I$400,I166)>1,"Possible duplicate","")) | O166: =IF(J166="","",IF(AND(L166=0,K166=0),1,0)) -> 1 | P166: =IF(L166=1,J166+ROW()/10^7,"") | Q166: =IF(O166=1,M166,"") -> 0.60262758 | R166: =IF(K166=1,ROW(),"") | S166: =IF(D166="","",TRIM(D166)) -> W/O EXPENSES
A167: GJAMS0086/25 | B167: 46022 | C167: =IF(S167="","",IFERROR(IF(INDEX('Ledger Codes'!$C$6:$C$205,MATCH(S167,'Ledger Codes'!$B$6:$B$205,0))="","",INDEX('Ledger Codes'!$C$6:$C$205,MATCH(S167,'Ledger Codes'!$B$6:$B$205,0))),"")) -> 10089 | D167: EXPENSE Forwarding | E167: 000004/25 | F167: Service : LOCAL TRANSPORTATION | G167: 8634 | H167: 0 | I167: =IF(AND(G167="",H167=""),"",N(G167)-N(H167)) -> 8634 | J167: =IF(I167="","",ABS(I167)) -> 8634 | K167: =IF(S167="","",0) -> 0 | L167: =IF(J167="","",IF(AND(J167>'COGS Testing'!$E$9,K167=0),1,0)) -> 1 | M167: 0.51727168 | N167: =IF(OR(A167="",I167=""),"",IF(COUNTIFS($A$2:$A$400,A167,$D$2:$D$400,D167,$I$2:$I$400,I167)>1,"Possible duplicate","")) | O167: =IF(J167="","",IF(AND(L167=0,K167=0),1,0)) -> 0 | P167: =IF(L167=1,J167+ROW()/10^7,"") -> 8634 | Q167: =IF(O167=1,M167,"") | R167: =IF(K167=1,ROW(),"") | S167: =IF(D167="","",TRIM(D167)) -> EXPENSE Forwarding
A168: GJAMS0084/25 | B168: 45899 | C168: =IF(S168="","",IFERROR(IF(INDEX('Ledger Codes'!$C$6:$C$205,MATCH(S168,'Ledger Codes'!$B$6:$B$205,0))="","",INDEX('Ledger Codes'!$C$6:$C$205,MATCH(S168,'Ledger Codes'!$B$6:$B$205,0))),"")) -> 10090 | D168: EXPENSE-SEA FREIGHT EXPORT FCL | E168: 000002/25 | F168: Service : SEA FREIGHT EXPORT FCL | G168: 9250 | H168: 0 | I168: =IF(AND(G168="",H168=""),"",N(G168)-N(H168)) -> 9250 | J168: =IF(I168="","",ABS(I168)) -> 9250 | K168: =IF(S168="","",0) -> 0 | L168: =IF(J168="","",IF(AND(J168>'COGS Testing'!$E$9,K168=0),1,0)) -> 1 | M168: 0.67366669 | N168: =IF(OR(A168="",I168=""),"",IF(COUNTIFS($A$2:$A$400,A168,$D$2:$D$400,D168,$I$2:$I$400,I168)>1,"Possible duplicate","")) | O168: =IF(J168="","",IF(AND(L168=0,K168=0),1,0)) -> 0 | P168: =IF(L168=1,J168+ROW()/10^7,"") -> 9250 | Q168: =IF(O168=1,M168,"") | R168: =IF(K168=1,ROW(),"") | S168: =IF(D168="","",TRIM(D168)) -> EXPENSE-SEA FREIGHT EXPORT FCL
A169: GJAMS0087/25 | B169: 45971 | C169: =IF(S169="","",IFERROR(IF(INDEX('Ledger Codes'!$C$6:$C$205,MATCH(S169,'Ledger Codes'!$B$6:$B$205,0))="","",INDEX('Ledger Codes'!$C$6:$C$205,MATCH(S169,'Ledger Codes'!$B$6:$B$205,0))),"")) -> 10090 | D169: EXPENSE-SEA FREIGHT EXPORT FCL | E169: 000005/25 | F169: Service : SEA FREIGHT EXPORT FCL | G169: 562.5 | H169: 0 | I169: =IF(AND(G169="",H169=""),"",N(G169)-N(H169)) -> 562.5 | J169: =IF(I169="","",ABS(I169)) -> 562.5 | K169: =IF(S169="","",0) -> 0 | L169: =IF(J169="","",IF(AND(J169>'COGS Testing'!$E$9,K169=0),1,0)) -> 0 | M169: 0.68710375 | N169: =IF(OR(A169="",I169=""),"",IF(COUNTIFS($A$2:$A$400,A169,$D$2:$D$400,D169,$I$2:$I$400,I169)>1,"Possible duplicate","")) | O169: =IF(J169="","",IF(AND(L169=0,K169=0),1,0)) -> 1 | P169: =IF(L169=1,J169+ROW()/10^7,"") | Q169: =IF(O169=1,M169,"") -> 0.68710375 | R169: =IF(K169=1,ROW(),"") | S169: =IF(D169="","",TRIM(D169)) -> EXPENSE-SEA FREIGHT EXPORT FCL
A170: GJAMS0083/25 | B170: 45991 | C170: =IF(S170="","",IFERROR(IF(INDEX('Ledger Codes'!$C$6:$C$205,MATCH(S170,'Ledger Codes'!$B$6:$B$205,0))="","",INDEX('Ledger Codes'!$C$6:$C$205,MATCH(S170,'Ledger Codes'!$B$6:$B$205,0))),"")) -> 10090 | D170: EXPENSE-SEA FREIGHT EXPORT FCL | E170: 000001/25 | F170: Service : SEA FREIGHT EXPORT FCL | G170: 775 | H170: 0 | I170: =IF(AND(G170="",H170=""),"",N(G170)-N(H170)) -> 775 | J170: =IF(I170="","",ABS(I170)) -> 775 | K170: =IF(S170="","",0) -> 0 | L170: =IF(J170="","",IF(AND(J170>'COGS Testing'!$E$9,K170=0),1,0)) -> 0 | M170: 0.84812272 | N170: =IF(OR(A170="",I170=""),"",IF(COUNTIFS($A$2:$A$400,A170,$D$2:$D$400,D170,$I$2:$I$400,I170)>1,"Possible duplicate","")) | O170: =IF(J170="","",IF(AND(L170=0,K170=0),1,0)) -> 1 | P170: =IF(L170=1,J170+ROW()/10^7,"") | Q170: =IF(O170=1,M170,"") -> 0.84812272 | R170: =IF(K170=1,ROW(),"") | S170: =IF(D170="","",TRIM(D170)) -> EXPENSE-SEA FREIGHT EXPORT FCL
A171: GJAMS0085/25 | B171: 45991 | C171: =IF(S171="","",IFERROR(IF(INDEX('Ledger Codes'!$C$6:$C$205,MATCH(S171,'Ledger Codes'!$B$6:$B$205,0))="","",INDEX('Ledger Codes'!$C$6:$C$205,MATCH(S171,'Ledger Codes'!$B$6:$B$205,0))),"")) -> 10090 | D171: EXPENSE-SEA FREIGHT EXPORT FCL | E171: 000003/25 | F171: Service : SEA FREIGHT EXPORT FCL | G171: 750 | H171: 0 | I171: =IF(AND(G171="",H171=""),"",N(G171)-N(H171)) -> 750 | J171: =IF(I171="","",ABS(I171)) -> 750 | K171: =IF(S171="","",0) -> 0 | L171: =IF(J171="","",IF(AND(J171>'COGS Testing'!$E$9,K171=0),1,0)) -> 0 | M171: 0.37857361 | N171: =IF(OR(A171="",I171=""),"",IF(COUNTIFS($A$2:$A$400,A171,$D$2:$D$400,D171,$I$2:$I$400,I171)>1,"Possible duplicate","")) | O171: =IF(J171="","",IF(AND(L171=0,K171=0),1,0)) -> 1 | P171: =IF(L171=1,J171+ROW()/10^7,"") | Q171: =IF(O171=1,M171,"") -> 0.37857361 | R171: =IF(K171=1,ROW(),"") | S171: =IF(D171="","",TRIM(D171)) -> EXPENSE-SEA FREIGHT EXPORT FCL
A172: GJAMS0088/25 | B172: 45991 | C172: =IF(S172="","",IFERROR(IF(INDEX('Ledger Codes'!$C$6:$C$205,MATCH(S172,'Ledger Codes'!$B$6:$B$205,0))="","",INDEX('Ledger Codes'!$C$6:$C$205,MATCH(S172,'Ledger Codes'!$B$6:$B$205,0))),"")) -> 10090 | D172: EXPENSE-SEA FREIGHT EXPORT FCL | E172: 000006/25 | F172: Service : SEA FREIGHT EXPORT FCL | G172: 6512.5 | H172: 0 | I172: =IF(AND(G172="",H172=""),"",N(G172)-N(H172)) -> 6512.5 | J172: =IF(I172="","",ABS(I172)) -> 6512.5 | K172: =IF(S172="","",0) -> 0 | L172: =IF(J172="","",IF(AND(J172>'COGS Testing'!$E$9,K172=0),1,0)) -> 1 | M172: 0.1058946 | N172: =IF(OR(A172="",I172=""),"",IF(COUNTIFS($A$2:$A$400,A172,$D$2:$D$400,D172,$I$2:$I$400,I172)>1,"Possible duplicate","")) | O172: =IF(J172="","",IF(AND(L172=0,K172=0),1,0)) -> 0 | P172: =IF(L172=1,J172+ROW()/10^7,"") -> 6512.5 | Q172: =IF(O172=1,M172,"") | R172: =IF(K172=1,ROW(),"") | S172: =IF(D172="","",TRIM(D172)) -> EXPENSE-SEA FREIGHT EXPORT FCL
A173: GJAMS0089/25 | B173: 46022 | C173: =IF(S173="","",IFERROR(IF(INDEX('Ledger Codes'!$C$6:$C$205,MATCH(S173,'Ledger Codes'!$B$6:$B$205,0))="","",INDEX('Ledger Codes'!$C$6:$C$205,MATCH(S173,'Ledger Codes'!$B$6:$B$205,0))),"")) -> 10090 | D173: EXPENSE-SEA FREIGHT EXPORT FCL | E173: 000007/25 | F173: Service : SEA FREIGHT EXPORT FCL | G173: 122750 | H173: 0 | I173: =IF(AND(G173="",H173=""),"",N(G173)-N(H173)) -> 122750 | J173: =IF(I173="","",ABS(I173)) -> 122750 | K173: =IF(S173="","",0) -> 0 | L173: =IF(J173="","",IF(AND(J173>'COGS Testing'!$E$9,K173=0),1,0)) -> 1 | M173: 0.40017031 | N173: =IF(OR(A173="",I173=""),"",IF(COUNTIFS($A$2:$A$400,A173,$D$2:$D$400,D173,$I$2:$I$400,I173)>1,"Possible duplicate","")) | O173: =IF(J173="","",IF(AND(L173=0,K173=0),1,0)) -> 0 | P173: =IF(L173=1,J173+ROW()/10^7,"") -> 122750 | Q173: =IF(O173=1,M173,"") | R173: =IF(K173=1,ROW(),"") | S173: =IF(D173="","",TRIM(D173)) -> EXPENSE-SEA FREIGHT EXPORT FCL
C174: =IF(S174="","",IFERROR(IF(INDEX('Ledger Codes'!$C$6:$C$205,MATCH(S174,'Ledger Codes'!$B$6:$B$205,0))="","",INDEX('Ledger Codes'!$C$6:$C$205,MATCH(S174,'Ledger Codes'!$B$6:$B$205,0))),"")) | I174: =IF(AND(G174="",H174=""),"",N(G174)-N(H174)) | J174: =IF(I174="","",ABS(I174)) | K174: =IF(S174="","",0) | L174: =IF(J174="","",IF(AND(J174>'COGS Testing'!$E$9,K174=0),1,0)) | M174: 0.25738253 | N174: =IF(OR(A174="",I174=""),"",IF(COUNTIFS($A$2:$A$400,A174,$D$2:$D$400,D174,$I$2:$I$400,I174)>1,"Possible duplicate","")) | O174: =IF(J174="","",IF(AND(L174=0,K174=0),1,0)) | P174: =IF(L174=1,J174+ROW()/10^7,"") | Q174: =IF(O174=1,M174,"") | R174: =IF(K174=1,ROW(),"") | S174: =IF(D174="","",TRIM(D174))
C175: =IF(S175="","",IFERROR(IF(INDEX('Ledger Codes'!$C$6:$C$205,MATCH(S175,'Ledger Codes'!$B$6:$B$205,0))="","",INDEX('Ledger Codes'!$C$6:$C$205,MATCH(S175,'Ledger Codes'!$B$6:$B$205,0))),"")) | I175: =IF(AND(G175="",H175=""),"",N(G175)-N(H175)) | J175: =IF(I175="","",ABS(I175)) | K175: =IF(S175="","",0) | L175: =IF(J175="","",IF(AND(J175>'COGS Testing'!$E$9,K175=0),1,0)) | M175: 0.27340791 | N175: =IF(OR(A175="",I175=""),"",IF(COUNTIFS($A$2:$A$400,A175,$D$2:$D$400,D175,$I$2:$I$400,I175)>1,"Possible duplicate","")) | O175: =IF(J175="","",IF(AND(L175=0,K175=0),1,0)) | P175: =IF(L175=1,J175+ROW()/10^7,"") | Q175: =IF(O175=1,M175,"") | R175: =IF(K175=1,ROW(),"") | S175: =IF(D175="","",TRIM(D175))
C176: =IF(S176="","",IFERROR(IF(INDEX('Ledger Codes'!$C$6:$C$205,MATCH(S176,'Ledger Codes'!$B$6:$B$205,0))="","",INDEX('Ledger Codes'!$C$6:$C$205,MATCH(S176,'Ledger Codes'!$B$6:$B$205,0))),"")) | I176: =IF(AND(G176="",H176=""),"",N(G176)-N(H176)) | J176: =IF(I176="","",ABS(I176)) | K176: =IF(S176="","",0) | L176: =IF(J176="","",IF(AND(J176>'COGS Testing'!$E$9,K176=0),1,0)) | M176: 0.71798863 | N176: =IF(OR(A176="",I176=""),"",IF(COUNTIFS($A$2:$A$400,A176,$D$2:$D$400,D176,$I$2:$I$400,I176)>1,"Possible duplicate","")) | O176: =IF(J176="","",IF(AND(L176=0,K176=0),1,0)) | P176: =IF(L176=1,J176+ROW()/10^7,"") | Q176: =IF(O176=1,M176,"") | R176: =IF(K176=1,ROW(),"") | S176: =IF(D176="","",TRIM(D176))
C177: =IF(S177="","",IFERROR(IF(INDEX('Ledger Codes'!$C$6:$C$205,MATCH(S177,'Ledger Codes'!$B$6:$B$205,0))="","",INDEX('Ledger Codes'!$C$6:$C$205,MATCH(S177,'Ledger Codes'!$B$6:$B$205,0))),"")) | I177: =IF(AND(G177="",H177=""),"",N(G177)-N(H177)) | J177: =IF(I177="","",ABS(I177)) | K177: =IF(S177="","",0) | L177: =IF(J177="","",IF(AND(J177>'COGS Testing'!$E$9,K177=0),1,0)) | M177: 0.41956202 | N177: =IF(OR(A177="",I177=""),"",IF(COUNTIFS($A$2:$A$400,A177,$D$2:$D$400,D177,$I$2:$I$400,I177)>1,"Possible duplicate","")) | O177: =IF(J177="","",IF(AND(L177=0,K177=0),1,0)) | P177: =IF(L177=1,J177+ROW()/10^7,"") | Q177: =IF(O177=1,M177,"") | R177: =IF(K177=1,ROW(),"") | S177: =IF(D177="","",TRIM(D177))
C178: =IF(S178="","",IFERROR(IF(INDEX('Ledger Codes'!$C$6:$C$205,MATCH(S178,'Ledger Codes'!$B$6:$B$205,0))="","",INDEX('Ledger Codes'!$C$6:$C$205,MATCH(S178,'Ledger Codes'!$B$6:$B$205,0))),"")) | I178: =IF(AND(G178="",H178=""),"",N(G178)-N(H178)) | J178: =IF(I178="","",ABS(I178)) | K178: =IF(S178="","",0) | L178: =IF(J178="","",IF(AND(J178>'COGS Testing'!$E$9,K178=0),1,0)) | M178: 0.13921312 | N178: =IF(OR(A178="",I178=""),"",IF(COUNTIFS($A$2:$A$400,A178,$D$2:$D$400,D178,$I$2:$I$400,I178)>1,"Possible duplicate","")) | O178: =IF(J178="","",IF(AND(L178=0,K178=0),1,0)) | P178: =IF(L178=1,J178+ROW()/10^7,"") | Q178: =IF(O178=1,M178,"") | R178: =IF(K178=1,ROW(),"") | S178: =IF(D178="","",TRIM(D178))
C179: =IF(S179="","",IFERROR(IF(INDEX('Ledger Codes'!$C$6:$C$205,MATCH(S179,'Ledger Codes'!$B$6:$B$205,0))="","",INDEX('Ledger Codes'!$C$6:$C$205,MATCH(S179,'Ledger Codes'!$B$6:$B$205,0))),"")) | I179: =IF(AND(G179="",H179=""),"",N(G179)-N(H179)) | J179: =IF(I179="","",ABS(I179)) | K179: =IF(S179="","",0) | L179: =IF(J179="","",IF(AND(J179>'COGS Testing'!$E$9,K179=0),1,0)) | M179: 0.56606078 | N179: =IF(OR(A179="",I179=""),"",IF(COUNTIFS($A$2:$A$400,A179,$D$2:$D$400,D179,$I$2:$I$400,I179)>1,"Possible duplicate","")) | O179: =IF(J179="","",IF(AND(L179=0,K179=0),1,0)) | P179: =IF(L179=1,J179+ROW()/10^7,"") | Q179: =IF(O179=1,M179,"") | R179: =IF(K179=1,ROW(),"") | S179: =IF(D179="","",TRIM(D179))
C180: =IF(S180="","",IFERROR(IF(INDEX('Ledger Codes'!$C$6:$C$205,MATCH(S180,'Ledger Codes'!$B$6:$B$205,0))="","",INDEX('Ledger Codes'!$C$6:$C$205,MATCH(S180,'Ledger Codes'!$B$6:$B$205,0))),"")) | I180: =IF(AND(G180="",H180=""),"",N(G180)-N(H180)) | J180: =IF(I180="","",ABS(I180)) | K180: =IF(S180="","",0) | L180: =IF(J180="","",IF(AND(J180>'COGS Testing'!$E$9,K180=0),1,0)) | M180: 0.96518328 | N180: =IF(OR(A180="",I180=""),"",IF(COUNTIFS($A$2:$A$400,A180,$D$2:$D$400,D180,$I$2:$I$400,I180)>1,"Possible duplicate","")) | O180: =IF(J180="","",IF(AND(L180=0,K180=0),1,0)) | P180: =IF(L180=1,J180+ROW()/10^7,"") | Q180: =IF(O180=1,M180,"") | R180: =IF(K180=1,ROW(),"") | S180: =IF(D180="","",TRIM(D180))
C181: =IF(S181="","",IFERROR(IF(INDEX('Ledger Codes'!$C$6:$C$205,MATCH(S181,'Ledger Codes'!$B$6:$B$205,0))="","",INDEX('Ledger Codes'!$C$6:$C$205,MATCH(S181,'Ledger Codes'!$B$6:$B$205,0))),"")) | I181: =IF(AND(G181="",H181=""),"",N(G181)-N(H181)) | J181: =IF(I181="","",ABS(I181)) | K181: =IF(S181="","",0) | L181: =IF(J181="","",IF(AND(J181>'COGS Testing'!$E$9,K181=0),1,0)) | M181: 0.39438131 | N181: =IF(OR(A181="",I181=""),"",IF(COUNTIFS($A$2:$A$400,A181,$D$2:$D$400,D181,$I$2:$I$400,I181)>1,"Possible duplicate","")) | O181: =IF(J181="","",IF(AND(L181=0,K181=0),1,0)) | P181: =IF(L181=1,J181+ROW()/10^7,"") | Q181: =IF(O181=1,M181,"") | R181: =IF(K181=1,ROW(),"") | S181: =IF(D181="","",TRIM(D181))
C182: =IF(S182="","",IFERROR(IF(INDEX('Ledger Codes'!$C$6:$C$205,MATCH(S182,'Ledger Codes'!$B$6:$B$205,0))="","",INDEX('Ledger Codes'!$C$6:$C$205,MATCH(S182,'Ledger Codes'!$B$6:$B$205,0))),"")) | I182: =IF(AND(G182="",H182=""),"",N(G182)-N(H182)) | J182: =IF(I182="","",ABS(I182)) | K182: =IF(S182="","",0) | L182: =IF(J182="","",IF(AND(J182>'COGS Testing'!$E$9,K182=0),1,0)) | M182: 0.98536783 | N182: =IF(OR(A182="",I182=""),"",IF(COUNTIFS($A$2:$A$400,A182,$D$2:$D$400,D182,$I$2:$I$400,I182)>1,"Possible duplicate","")) | O182: =IF(J182="","",IF(AND(L182=0,K182=0),1,0)) | P182: =IF(L182=1,J182+ROW()/10^7,"") | Q182: =IF(O182=1,M182,"") | R182: =IF(K182=1,ROW(),"") | S182: =IF(D182="","",TRIM(D182))
C183: =IF(S183="","",IFERROR(IF(INDEX('Ledger Codes'!$C$6:$C$205,MATCH(S183,'Ledger Codes'!$B$6:$B$205,0))="","",INDEX('Ledger Codes'!$C$6:$C$205,MATCH(S183,'Ledger Codes'!$B$6:$B$205,0))),"")) | I183: =IF(AND(G183="",H183=""),"",N(G183)-N(H183)) | J183: =IF(I183="","",ABS(I183)) | K183: =IF(S183="","",0) | L183: =IF(J183="","",IF(AND(J183>'COGS Testing'!$E$9,K183=0),1,0)) | M183: 0.67965142 | N183: =IF(OR(A183="",I183=""),"",IF(COUNTIFS($A$2:$A$400,A183,$D$2:$D$400,D183,$I$2:$I$400,I183)>1,"Possible duplicate","")) | O183: =IF(J183="","",IF(AND(L183=0,K183=0),1,0)) | P183: =IF(L183=1,J183+ROW()/10^7,"") | Q183: =IF(O183=1,M183,"") | R183: =IF(K183=1,ROW(),"") | S183: =IF(D183="","",TRIM(D183))
C184: =IF(S184="","",IFERROR(IF(INDEX('Ledger Codes'!$C$6:$C$205,MATCH(S184,'Ledger Codes'!$B$6:$B$205,0))="","",INDEX('Ledger Codes'!$C$6:$C$205,MATCH(S184,'Ledger Codes'!$B$6:$B$205,0))),"")) | I184: =IF(AND(G184="",H184=""),"",N(G184)-N(H184)) | J184: =IF(I184="","",ABS(I184)) | K184: =IF(S184="","",0) | L184: =IF(J184="","",IF(AND(J184>'COGS Testing'!$E$9,K184=0),1,0)) | M184: 0.4888741 | N184: =IF(OR(A184="",I184=""),"",IF(COUNTIFS($A$2:$A$400,A184,$D$2:$D$400,D184,$I$2:$I$400,I184)>1,"Possible duplicate","")) | O184: =IF(J184="","",IF(AND(L184=0,K184=0),1,0)) | P184: =IF(L184=1,J184+ROW()/10^7,"") | Q184: =IF(O184=1,M184,"") | R184: =IF(K184=1,ROW(),"") | S184: =IF(D184="","",TRIM(D184))
C185: =IF(S185="","",IFERROR(IF(INDEX('Ledger Codes'!$C$6:$C$205,MATCH(S185,'Ledger Codes'!$B$6:$B$205,0))="","",INDEX('Ledger Codes'!$C$6:$C$205,MATCH(S185,'Ledger Codes'!$B$6:$B$205,0))),"")) | I185: =IF(AND(G185="",H185=""),"",N(G185)-N(H185)) | J185: =IF(I185="","",ABS(I185)) | K185: =IF(S185="","",0) | L185: =IF(J185="","",IF(AND(J185>'COGS Testing'!$E$9,K185=0),1,0)) | M185: 0.16045096 | N185: =IF(OR(A185="",I185=""),"",IF(COUNTIFS($A$2:$A$400,A185,$D$2:$D$400,D185,$I$2:$I$400,I185)>1,"Possible duplicate","")) | O185: =IF(J185="","",IF(AND(L185=0,K185=0),1,0)) | P185: =IF(L185=1,J185+ROW()/10^7,"") | Q185: =IF(O185=1,M185,"") | R185: =IF(K185=1,ROW(),"") | S185: =IF(D185="","",TRIM(D185))
... C400: =IF(S400="","",IFERROR(IF(INDEX('Ledger Codes'!$C$6:$C$205,MATCH(S400,'Ledger Codes'!$B$6:$B$205,0))="","",INDEX('Ledger Codes'!$C$6:$C$205,MATCH(S400,'Ledger Codes'!$B$6:$B$205,0))),"")) | I400: =IF(AND(G400="",H400=""),"",N(G400)-N(H400)) | J400: =IF(I400="","",ABS(I400)) | K400: =IF(S400="","",0) | L400: =IF(J400="","",IF(AND(J400>'COGS Testing'!$E$9,K400=0),1,0)) | M400: 0.25395506 | N400: =IF(OR(A400="",I400=""),"",IF(COUNTIFS($A$2:$A$400,A400,$D$2:$D$400,D400,$I$2:$I$400,I400)>1,"Possible duplicate","")) | O400: =IF(J400="","",IF(AND(L400=0,K400=0),1,0)) | P400: =IF(L400=1,J400+ROW()/10^7,"") | Q400: =IF(O400=1,M400,"") | R400: =IF(K400=1,ROW(),"") | S400: =IF(D400="","",TRIM(D400))

Sheet COGS Testing
A1: COGS – test of details: audit sample selection
A2: ="Client: "&Materiality!E3&" | Reporting date: "&Materiality!E5 -> Client: LRC | Reporting date: 31 March 2026
A4: MATERIALITY AND SETUP
C5: Test area | E5: COGS
C6: Sales / revenue considered (SR) | E6: =Materiality!F29 -> 1000000
C7: Materiality percentage applied | E7: =Materiality!G37/100 -> 0.005
C8: Calculated materiality = revenue × % (SR) | E8: =Materiality!H37 -> 5000
C9: Materiality used for sampling (SR) – per Materiality sheet | E9: =Materiality!H42 -> 4000
C10: Risk level for this test (drives the below-materiality sample size) | E10: Low to Moderate (2)
C11: Entity size (drives the maximum sample size) | E11: Medium
C12: Sample size override – leave blank to use the calculated size
A15: BELOW-MATERIALITY SAMPLE SIZE – formula from the 732 template | I15: Maximum sample size table (from 732 template)
C16: Remaining population = eligible items not above materiality (absolute value, SR) | E16: =SUMIF('COGS Ledger'!$O$2:$O$400,1,'COGS Ledger'!$J$2:$J$400) -> 111047.12 | I16: Risk level \ Entity size | J16: Small | K16: Medium | L16: Large
C17: Planning materiality (SR) | E17: =E9 -> 4000 | I17: Significant (4) | J17: 40 | K17: 50 | L17: 60
C18: Confidence factor (Low 0.25 / Low-Moderate 0.5 / Moderate 0.75 / Significant ~1) | E18: =IF(E10="Low (1)",0.25,IF(E10="Low to Moderate (2)",0.5,IF(E10="Moderate (3)",0.75,IF(E10="Significant (4)",0.999999,0.00001)))) -> 0.5 | I18: Moderate (3) | J18: 30 | K18: 40 | L18: 50
C19: Sampling interval = materiality ÷ confidence factor (SR) | E19: =IFERROR(E17/E18,0) -> 8000 | I19: Low to Moderate (2) | J19: 20 | K19: 30 | L19: 40
C20: Calculated sample size = ROUND(remaining population ÷ interval) | E20: =IFERROR(ROUND(E16/E19,0),0) -> 14 | I20: Low (1) | J20: 15 | K20: 25 | L20: 35
C21: Maximum sample size (risk level × entity size) | E21: =INDEX($J$17:$L$20,MATCH(E10,$I$17:$I$20,0),MATCH(E11,$J$16:$L$16,0)) -> 30
C22: Sample size per template = lower of calculated and maximum | E22: =MIN(E20,E21) -> 14
C23: SAMPLE SIZE USED | E23: =IF(E12<>"",E12,E22) -> 14
A25: SAMPLE SELECTION SUMMARY
C26: Total ledger transactions | E26: =COUNT('COGS Ledger'!$I$2:$I$400) -> 172
C27: Total ledger net amount – original signs (SR) | E27: =SUM('COGS Ledger'!$I$2:$I$400) -> 1232236.3
C28: Lines excluded – accounts set to Exclude (already tested) | E28: =COUNTIFS('COGS Ledger'!$K$2:$K$400,1) -> 0
C29: Excluded lines – absolute value (SR) | E29: =SUMIF('COGS Ledger'!$K$2:$K$400,1,'COGS Ledger'!$J$2:$J$400) -> 0
C30: Total eligible transactions | E30: =E26-E28 -> 172
C31: ABOVE MATERIALITY – items selected, 100% tested | E31: =SUM('COGS Ledger'!$L$2:$L$400) -> 45 | G31: View list →
C32: ABOVE MATERIALITY – absolute value (SR) | E32: =SUMIF('COGS Ledger'!$L$2:$L$400,1,'COGS Ledger'!$J$2:$J$400) -> 1486715.4
C33: BELOW MATERIALITY – eligible population (items) | E33: =SUM('COGS Ledger'!$O$2:$O$400) -> 127
C34: BELOW MATERIALITY – eligible population (absolute value, SR) | E34: =E16 -> 111047.12
C35: BELOW MATERIALITY – sample size used | E35: =E23 -> 14
C36: BELOW MATERIALITY – random samples selected | E36: =MIN(E35,E33) -> 14 | G36: View list →
C37: BELOW MATERIALITY – eligible items not selected | E37: =E33-E36 -> 113
C38: Above materiality: ABS(amount) > materiality → selected automatically (equal to materiality counts as below).
C39: Below materiality: eligible items → fixed random no. (ledger column M) → sorted high to low → top N. Numbers do not change on recalculation.
A41: VALIDATION CHECKS
C42: 1. Above-materiality completeness (eligible items above materiality = items listed) | E42: =IF(COUNT('COGS Above'!$A$5:$A$304)=COUNTIFS('COGS Ledger'!$J$2:$J$400,">"&$E$9,'COGS Ledger'!$K$2:$K$400,0),"PASS","FAIL") -> PASS | F42: ="Expected "&(COUNTIFS('COGS Ledger'!$J$2:$J$400,">"&$E$9,'COGS Ledger'!$K$2:$K$400,0))&", listed "&COUNT('COGS Above'!$A$5:$A$304) -> Expected 45, listed 45
C43: 2. Random population = eligible − above materiality | E43: =IF(E33=E30-E31,"PASS","FAIL") -> PASS
C44: 3. No item selected as both above-materiality and random | E44: =IF(COUNTIFS('COGS Ledger'!$L$2:$L$400,1,'COGS Ledger'!$O$2:$O$400,1)=0,"PASS","FAIL") -> PASS
C45: 4. Excluded accounts appear in neither list | E45: =IF(COUNTIFS('COGS Ledger'!$K$2:$K$400,1,'COGS Ledger'!$L$2:$L$400,1)+COUNTIFS('COGS Ledger'!$K$2:$K$400,1,'COGS Ledger'!$O$2:$O$400,1)=0,"PASS","FAIL") -> PASS
C46: 5. Missing data (date / account / amount / description) | E46: =IF((SUMPRODUCT(ISNUMBER('COGS Ledger'!$I$2:$I$400)*NOT(ISNUMBER('COGS Ledger'!$B$2:$B$400)))+SUMPRODUCT(ISNUMBER('COGS Ledger'!$I$2:$I$400)*('COGS Ledger'!$D$2:$D$400=""))+SUMPRODUCT(('COGS Ledger'!$I$2:$I$400="")*('COGS Ledger'!$D$2:$D$400<>""))+SUMPRODUCT(ISNUMBER('COGS Ledger'!$I$2:$I$400)*('COGS Ledger'!$F$2:$F$400="")))=0,"PASS","REVIEW") -> REVIEW | F46: ="Date: "&SUMPRODUCT(ISNUMBER('COGS Ledger'!$I$2:$I$400)*NOT(ISNUMBER('COGS Ledger'!$B$2:$B$400)))&" Account: "&SUMPRODUCT(ISNUMBER('COGS Ledger'!$I$2:$I$400)*('COGS Ledger'!$D$2:$D$400=""))&" Amount: "&SUMPRODUCT(('COGS Ledger'!$I$2:$I$400="")*('COGS Ledger'!$D$2:$D$400<>""))&" Description: "&SUMPRODUCT(ISNUMBER('COGS Ledger'!$I$2:$I$400)*('COGS Ledger'!$F$2:$F$400="")) -> Date: 0 Account: 0 Amount: 0 Description: 3
C47: 6. Source-data integrity (net amount = Σ debit − Σ credit) | E47: =IF(ROUND(SUM('COGS Ledger'!$I$2:$I$400)-(SUM('COGS Ledger'!$G$2:$G$400)-SUM('COGS Ledger'!$H$2:$H$400)),2)=0,"PASS","FAIL") -> PASS
C48: 7. Above-materiality list capacity | E48: =IF(E31<=300,"PASS","FAIL – extend list") -> PASS
C49: 8. Sample size does not exceed eligible population | E49: =IF(E35<=E33,"PASS","REVIEW") -> PASS | F49: =IF(E35>E33,"Sample size capped at the eligible population","")
C50: 9. Below-materiality list capacity | E50: =IF(E36<=100,"PASS","FAIL – extend list") -> PASS
C51: 10. Every ledger line has a ledger code | E51: =IF(SUMPRODUCT(('COGS Ledger'!$S$2:$S$400<>"")*('COGS Ledger'!$C$2:$C$400=""))=0,"PASS","REVIEW") -> PASS | F51: =SUMPRODUCT(('COGS Ledger'!$S$2:$S$400<>"")*('COGS Ledger'!$C$2:$C$400=""))&" line(s) without a ledger code – see Ledger Codes sheet" -> 0 line(s) without a ledger code – see Ledger Codes sheet

Sheet COGS Above
A1: COGS – ABOVE MATERIALITY: ALL ITEMS TESTED (100%)
A2: ="Materiality used: SR "&TEXT('COGS Testing'!E9,"#,##0")&" | Items selected: "&'COGS Testing'!E31&" | Absolute value: SR "&TEXT('COGS Testing'!E32,"#,##0.00")&" | Largest to smallest" -> Materiality used: SR 4,000 | Items selected: 45 | Absolute value: SR 1,486,715.38 | Largest to smallest
A3: Back to summary: COGS Testing
A4: Sample No. | B4: Date | C4: Ledger Code | D4: Ledger / Account | E4: Description | F4: Original Amount | G4: Absolute Amount | H4: Materiality | I4: Selection Basis | J4: Ledger row | K4: Voucher Ref | L4: Test result | M4: Comments
A5: =IF(ROWS($A$5:A5)<='COGS Testing'!$E$31,ROWS($A$5:A5),"") -> 1 | B5: =IF($A5="","",INDEX('COGS Ledger'!$B$1:$B$400,$J5)) -> 46022 | C5: =IF($A5="","",INDEX('COGS Ledger'!$C$1:$C$400,$J5)) -> 10077 | D5: =IF($A5="","",INDEX('COGS Ledger'!$D$1:$D$400,$J5)) -> SLOT CHARGES- EXP | E5: =IF($A5="","",INDEX('COGS Ledger'!$F$1:$F$400,$J5)&"") -> PJ Ref:AMSLAP0008/26 ; 2601002- SLOT CHARGES AGAINST PRINIPAL LINE CSTAR- USD 90,675/- | F5: =IF($A5="","",INDEX('COGS Ledger'!$I$1:$I$400,$J5)) -> 340031.25 | G5: =IF($A5="","",INDEX('COGS Ledger'!$J$1:$J$400,$J5)) -> 340031.25 | H5: =IF($A5="","",'COGS Testing'!$E$9) -> 4000 | I5: =IF($A5="","","Above materiality – automatically selected") -> Above materiality – automatically selected | J5: =IF($A5="","",MATCH(LARGE('COGS Ledger'!$P$2:$P$400,$A5),'COGS Ledger'!$P$2:$P$400,0)+1) -> 154 | K5: =IF($A5="","",INDEX('COGS Ledger'!$A$1:$A$400,$J5)&"") -> PJAMS0161/25
A6: =IF(ROWS($A$5:A6)<='COGS Testing'!$E$31,ROWS($A$5:A6),"") -> 2 | B6: =IF($A6="","",INDEX('COGS Ledger'!$B$1:$B$400,$J6)) -> 45909 | C6: =IF($A6="","",INDEX('COGS Ledger'!$C$1:$C$400,$J6)) -> 10056 | D6: =IF($A6="","",INDEX('COGS Ledger'!$D$1:$D$400,$J6)) -> RESTOW CHARGES - EXP | E6: =IF($A6="","",INDEX('COGS Ledger'!$F$1:$F$400,$J6)&"") -> PJ Ref:AMSLAP0004/25 ; RSGT- 2331988- CSTAR VOYAGER FRS01W- RESTOW CHARGES- DISCH RESTOW- 30X20 @ SAR 200 & 242X40 @ SAR 300 LOAD RESTOW 30X20 @ SAR 200 & 242X40 @ SAR 300 | F6: =IF($A6="","",INDEX('COGS Ledger'!$I$1:$I$400,$J6)) -> 157200 | G6: =IF($A6="","",INDEX('COGS Ledger'!$J$1:$J$400,$J6)) -> 157200 | H6: =IF($A6="","",'COGS Testing'!$E$9) -> 4000 | I6: =IF($A6="","","Above materiality – automatically selected") -> Above materiality – automatically selected | J6: =IF($A6="","",MATCH(LARGE('COGS Ledger'!$P$2:$P$400,$A6),'COGS Ledger'!$P$2:$P$400,0)+1) -> 151 | K6: =IF($A6="","",INDEX('COGS Ledger'!$A$1:$A$400,$J6)&"") -> PJAMS0023/25
A7: =IF(ROWS($A$5:A7)<='COGS Testing'!$E$31,ROWS($A$5:A7),"") -> 3 | B7: =IF($A7="","",INDEX('COGS Ledger'!$B$1:$B$400,$J7)) -> 46022 | C7: =IF($A7="","",INDEX('COGS Ledger'!$C$1:$C$400,$J7)) -> 10090 | D7: =IF($A7="","",INDEX('COGS Ledger'!$D$1:$D$400,$J7)) -> EXPENSE-SEA FREIGHT EXPORT FCL | E7: =IF($A7="","",INDEX('COGS Ledger'!$F$1:$F$400,$J7)&"") -> Service : SEA FREIGHT EXPORT FCL | F7: =IF($A7="","",INDEX('COGS Ledger'!$I$1:$I$400,$J7)) -> 122750 | G7: =IF($A7="","",INDEX('COGS Ledger'!$J$1:$J$400,$J7)) -> 122750 | H7: =IF($A7="","",'COGS Testing'!$E$9) -> 4000 | I7: =IF($A7="","","Above materiality – automatically selected") -> Above materiality – automatically selected | J7: =IF($A7="","",MATCH(LARGE('COGS Ledger'!$P$2:$P$400,$A7),'COGS Ledger'!$P$2:$P$400,0)+1) -> 173 | K7: =IF($A7="","",INDEX('COGS Ledger'!$A$1:$A$400,$J7)&"") -> GJAMS0089/25
A8: =IF(ROWS($A$5:A8)<='COGS Testing'!$E$31,ROWS($A$5:A8),"") -> 4 | B8: =IF($A8="","",INDEX('COGS Ledger'!$B$1:$B$400,$J8)) -> 45900 | C8: =IF($A8="","",INDEX('COGS Ledger'!$C$1:$C$400,$J8)) -> 10052 | D8: =IF($A8="","",INDEX('COGS Ledger'!$D$1:$D$400,$J8)) -> OCEAN FREIGHT- EXP | E8: =IF($A8="","",INDEX('COGS Ledger'!$F$1:$F$400,$J8)&"") -> REVERSAL OF PJAMS0176- OFRT FOR BALTIC- USD 1800 X 18 CONT- PJ ISSUED THROUGH JOB NO AMSSFEF0006 | F8: =IF($A8="","",INDEX('COGS Ledger'!$I$1:$I$400,$J8)) -> -121500 | G8: =IF($A8="","",INDEX('COGS Ledger'!$J$1:$J$400,$J8)) -> 121500 | H8: =IF($A8="","",'COGS Testing'!$E$9) -> 4000 | I8: =IF($A8="","","Above materiality – automatically selected") -> Above materiality – automatically selected | J8: =IF($A8="","",MATCH(LARGE('COGS Ledger'!$P$2:$P$400,$A8),'COGS Ledger'!$P$2:$P$400,0)+1) -> 72 | K8: =IF($A8="","",INDEX('COGS Ledger'!$A$1:$A$400,$J8)&"") -> DNAMS0046/25
A9: =IF(ROWS($A$5:A9)<='COGS Testing'!$E$31,ROWS($A$5:A9),"") -> 5 | B9: =IF($A9="","",INDEX('COGS Ledger'!$B$1:$B$400,$J9)) -> 45900 | C9: =IF($A9="","",INDEX('COGS Ledger'!$C$1:$C$400,$J9)) -> 10052 | D9: =IF($A9="","",INDEX('COGS Ledger'!$D$1:$D$400,$J9)) -> OCEAN FREIGHT- EXP | E9: =IF($A9="","",INDEX('COGS Ledger'!$F$1:$F$400,$J9)&"") -> PJ Ref:AMSLAP0055/25 ; OFRT- BALTIC INTERLINE- USD 1800 X 18 CONT- USD 32400- SAR 121500 AGREED BETWEEN BALTIC AND MOHTISIM KHAN CUSTOMER- BAHRI LOGISTICS | F9: =IF($A9="","",INDEX('COGS Ledger'!$I$1:$I$400,$J9)) -> 121500 | G9: =IF($A9="","",INDEX('COGS Ledger'!$J$1:$J$400,$J9)) -> 121500 | H9: =IF($A9="","",'COGS Testing'!$E$9) -> 4000 | I9: =IF($A9="","","Above materiality – automatically selected") -> Above materiality – automatically selected | J9: =IF($A9="","",MATCH(LARGE('COGS Ledger'!$P$2:$P$400,$A9),'COGS Ledger'!$P$2:$P$400,0)+1) -> 70 | K9: =IF($A9="","",INDEX('COGS Ledger'!$A$1:$A$400,$J9)&"") -> PJAMS0176/25
A10: =IF(ROWS($A$5:A10)<='COGS Testing'!$E$31,ROWS($A$5:A10),"") -> 6 | B10: =IF($A10="","",INDEX('COGS Ledger'!$B$1:$B$400,$J10)) -> 45958 | C10: =IF($A10="","",INDEX('COGS Ledger'!$C$1:$C$400,$J10)) -> 10053 | D10: =IF($A10="","",INDEX('COGS Ledger'!$D$1:$D$400,$J10)) -> OPERATION RECOVERY COST | E10: =IF($A10="","",INDEX('COGS Ledger'!$F$1:$F$400,$J10)&"") -> RSGT- 2368005- NZ NINGBO - NGBOFRS004E- DISCH IMPORT LADEN- 12X20'- SAR 300 DISCH IMPORT LADEN- 245X40'- SAR 450 DISCH T/S LADEN- 44X20'- SAR 140 DISCH T/S LADEN- 253X40'- SAR 210 | F10: =IF($A10="","",INDEX('COGS Ledger'!$I$1:$I$400,$J10)) -> 110250 | G10: =IF($A10="","",INDEX('COGS Ledger'!$J$1:$J$400,$J10)) -> 110250 | H10: =IF($A10="","",'COGS Testing'!$E$9) -> 4000 | I10: =IF($A10="","","Above materiality – automatically selected") -> Above materiality – automatically selected | J10: =IF($A10="","",MATCH(LARGE('COGS Ledger'!$P$2:$P$400,$A10),'COGS Ledger'!$P$2:$P$400,0)+1) -> 106 | K10: =IF($A10="","",INDEX('COGS Ledger'!$A$1:$A$400,$J10)&"") -> PJAMS0080/25
A11: =IF(ROWS($A$5:A11)<='COGS Testing'!$E$31,ROWS($A$5:A11),"") -> 7 | B11: =IF($A11="","",INDEX('COGS Ledger'!$B$1:$B$400,$J11)) -> 45909 | C11: =IF($A11="","",INDEX('COGS Ledger'!$C$1:$C$400,$J11)) -> 10053 | D11: =IF($A11="","",INDEX('COGS Ledger'!$D$1:$D$400,$J11)) -> OPERATION RECOVERY COST | E11: =IF($A11="","",INDEX('COGS Ledger'!$F$1:$F$400,$J11)&"") -> RSGT- 2331991- NZ SUZHOU - NZSUFRS03- DISCH IMP 16X20' INCLUDING 2 DG & 208X40' DISCH TRANS- 8X20' & 16X40' LOAD TRANS- 24X20' & 257X40' | F11: =IF($A11="","",INDEX('COGS Ledger'!$I$1:$I$400,$J11)) -> 93600 | G11: =IF($A11="","",INDEX('COGS Ledger'!$J$1:$J$400,$J11)) -> 93600 | H11: =IF($A11="","",'COGS Testing'!$E$9) -> 4000 | I11: =IF($A11="","","Above materiality – automatically selected") -> Above materiality – automatically selected | J11: =IF($A11="","",MATCH(LARGE('COGS Ledger'!$P$2:$P$400,$A11),'COGS Ledger'!$P$2:$P$400,0)+1) -> 87 | K11: =IF($A11="","",INDEX('COGS Ledger'!$A$1:$A$400,$J11)&"") -> PJAMS0005/25
A12: =IF(ROWS($A$5:A12)<='COGS Testing'!$E$31,ROWS($A$5:A12),"") -> 8 | B12: =IF($A12="","",INDEX('COGS Ledger'!$B$1:$B$400,$J12)) -> 45909 | C12: =IF($A12="","",INDEX('COGS Ledger'!$C$1:$C$400,$J12)) -> 10053 | D12: =IF($A12="","",INDEX('COGS Ledger'!$D$1:$D$400,$J12)) -> OPERATION RECOVERY COST | E12: =IF($A12="","",INDEX('COGS Ledger'!$F$1:$F$400,$J12)&"") -> 2331985- CSTAR VOYAGER - CSVOFRS01W- DISCH IMP- 35X20' & 126X40' LADEN NON CELLULAR DISCH TRAN- 28X20' & 261X40; NON CELLULAR | F12: =IF($A12="","",INDEX('COGS Ledger'!$I$1:$I$400,$J12)) -> 56700 | G12: =IF($A12="","",INDEX('COGS Ledger'!$J$1:$J$400,$J12)) -> 56700 | H12: =IF($A12="","",'COGS Testing'!$E$9) -> 4000 | I12: =IF($A12="","","Above materiality – automatically selected") -> Above materiality – automatically selected | J12: =IF($A12="","",MATCH(LARGE('COGS Ledger'!$P$2:$P$400,$A12),'COGS Ledger'!$P$2:$P$400,0)+1) -> 84 | K12: =IF($A12="","",INDEX('COGS Ledger'!$A$1:$A$400,$J12)&"") -> PJAMS0004/25
A13: =IF(ROWS($A$5:A13)<='COGS Testing'!$E$31,ROWS($A$5:A13),"") -> 9 | B13: =IF($A13="","",INDEX('COGS Ledger'!$B$1:$B$400,$J13)) -> 45914 | C13: =IF($A13="","",INDEX('COGS Ledger'!$C$1:$C$400,$J13)) -> 10047 | D13: =IF($A13="","",INDEX('COGS Ledger'!$D$1:$D$400,$J13)) -> BERTHING & UNBERTHING CHARGES- EXP | E13: =IF($A13="","",INDEX('COGS Ledger'!$F$1:$F$400,$J13)&"") -> PJ Ref:AMSLAP0006/25 ; WESTERN COAST -1025013361- BERTHING & UNBERTHING CHGS- SAR 8228.2X2 & SAR 4000 BERTH DUES | F13: =IF($A13="","",INDEX('COGS Ledger'!$I$1:$I$400,$J13)) -> 20456.4 | G13: =IF($A13="","",INDEX('COGS Ledger'!$J$1:$J$400,$J13)) -> 20456.4 | H13: =IF($A13="","",'COGS Testing'!$E$9) -> 4000 | I13: =IF($A13="","","Above materiality – automatically selected") -> Above materiality – automatically selected | J13: =IF($A13="","",MATCH(LARGE('COGS Ledger'!$P$2:$P$400,$A13),'COGS Ledger'!$P$2:$P$400,0)+1) -> 2 | K13: =IF($A13="","",INDEX('COGS Ledger'!$A$1:$A$400,$J13)&"") -> PJAMS0031/25
A14: =IF(ROWS($A$5:A14)<='COGS Testing'!$E$31,ROWS($A$5:A14),"") -> 10 | B14: =IF($A14="","",INDEX('COGS Ledger'!$B$1:$B$400,$J14)) -> 45959 | C14: =IF($A14="","",INDEX('COGS Ledger'!$C$1:$C$400,$J14)) -> 10047 | D14: =IF($A14="","",INDEX('COGS Ledger'!$D$1:$D$400,$J14)) -> BERTHING & UNBERTHING CHARGES- EXP | E14: =IF($A14="","",INDEX('COGS Ledger'!$F$1:$F$400,$J14)&"") -> PJ Ref:AMSLAP0039/25 ; WESTERN COAST- 1025014651- BERTHING AND UNBERTHING CHARGES- NZ SZUHOU FRS04E | F14: =IF($A14="","",INDEX('COGS Ledger'!$I$1:$I$400,$J14)) -> 18755.2 | G14: =IF($A14="","",INDEX('COGS Ledger'!$J$1:$J$400,$J14)) -> 18755.2 | H14: =IF($A14="","",'COGS Testing'!$E$9) -> 4000 | I14: =IF($A14="","","Above materiality – automatically selected") -> Above materiality – automatically selected | J14: =IF($A14="","",MATCH(LARGE('COGS Ledger'!$P$2:$P$400,$A14),'COGS Ledger'!$P$2:$P$400,0)+1) -> 6 | K14: =IF($A14="","",INDEX('COGS Ledger'!$A$1:$A$400,$J14)&"") -> PJAMS0103/25
A15: =IF(ROWS($A$5:A15)<='COGS Testing'!$E$31,ROWS($A$5:A15),"") -> 11 | B15: =IF($A15="","",INDEX('COGS Ledger'!$B$1:$B$400,$J15)) -> 45929 | C15: =IF($A15="","",INDEX('COGS Ledger'!$C$1:$C$400,$J15)) -> 10047 | D15: =IF($A15="","",INDEX('COGS Ledger'!$D$1:$D$400,$J15)) -> BERTHING & UNBERTHING CHARGES- EXP | E15: =IF($A15="","",INDEX('COGS Ledger'!$F$1:$F$400,$J15)&"") -> PJ Ref:AMSLAP0038/25 ; WESTERN COAST- 1025013889- BERTHING & UNBERTHING CHGS- CSTAR VOYAGER | F15: =IF($A15="","",INDEX('COGS Ledger'!$I$1:$I$400,$J15)) -> 18456 | G15: =IF($A15="","",INDEX('COGS Ledger'!$J$1:$J$400,$J15)) -> 18456 | H15: =IF($A15="","",'COGS Testing'!$E$9) -> 4000 | I15: =IF($A15="","","Above materiality – automatically selected") -> Above materiality – automatically selected | J15: =IF($A15="","",MATCH(LARGE('COGS Ledger'!$P$2:$P$400,$A15),'COGS Ledger'!$P$2:$P$400,0)+1) -> 5 | K15: =IF($A15="","",INDEX('COGS Ledger'!$A$1:$A$400,$J15)&"") -> PJAMS0102/25
A16: =IF(ROWS($A$5:A16)<='COGS Testing'!$E$31,ROWS($A$5:A16),"") -> 12 | B16: =IF($A16="","",INDEX('COGS Ledger'!$B$1:$B$400,$J16)) -> 45918 | C16: =IF($A16="","",INDEX('COGS Ledger'!$C$1:$C$400,$J16)) -> 10047 | D16: =IF($A16="","",INDEX('COGS Ledger'!$D$1:$D$400,$J16)) -> BERTHING & UNBERTHING CHARGES- EXP | E16: =IF($A16="","",INDEX('COGS Ledger'!$F$1:$F$400,$J16)&"") -> PJ Ref:AMSLAP0005/25 ; WEST COAST- 1025013568- NZ SUZHOU FRS03W- BERTHING & UNBERTHING CHGS SAR 7934X2 & SAR 2000 BERTH DUES | F16: =IF($A16="","",INDEX('COGS Ledger'!$I$1:$I$400,$J16)) -> 17868 | G16: =IF($A16="","",INDEX('COGS Ledger'!$J$1:$J$400,$J16)) -> 17868 | H16: =IF($A16="","",'COGS Testing'!$E$9) -> 4000 | I16: =IF($A16="","","Above materiality – automatically selected") -> Above materiality – automatically selected | J16: =IF($A16="","",MATCH(LARGE('COGS Ledger'!$P$2:$P$400,$A16),'COGS Ledger'!$P$2:$P$400,0)+1) -> 4 | K16: =IF($A16="","",INDEX('COGS Ledger'!$A$1:$A$400,$J16)&"") -> PJAMS0030/25
... A304: =IF(ROWS($A$5:A304)<='COGS Testing'!$E$31,ROWS($A$5:A304),"") | B304: =IF($A304="","",INDEX('COGS Ledger'!$B$1:$B$400,$J304)) | C304: =IF($A304="","",INDEX('COGS Ledger'!$C$1:$C$400,$J304)) | D304: =IF($A304="","",INDEX('COGS Ledger'!$D$1:$D$400,$J304)) | E304: =IF($A304="","",INDEX('COGS Ledger'!$F$1:$F$400,$J304)&"") | F304: =IF($A304="","",INDEX('COGS Ledger'!$I$1:$I$400,$J304)) | G304: =IF($A304="","",INDEX('COGS Ledger'!$J$1:$J$400,$J304)) | H304: =IF($A304="","",'COGS Testing'!$E$9) | I304: =IF($A304="","","Above materiality – automatically selected") | J304: =IF($A304="","",MATCH(LARGE('COGS Ledger'!$P$2:$P$400,$A304),'COGS Ledger'!$P$2:$P$400,0)+1) | K304: =IF($A304="","",INDEX('COGS Ledger'!$A$1:$A$400,$J304)&"")
E305: Total | F305: =SUM(F5:F304) -> 1155882.6 | G305: =SUM(G5:G304) -> 1486715.4

Sheet COGS Below
A1: COGS – BELOW MATERIALITY: RANDOM SAMPLE
A2: ="Sample: "&'COGS Testing'!E36&" of "&'COGS Testing'!E33&" eligible items | Risk level: "&'COGS Testing'!E10&" / "&'COGS Testing'!E11&" entity | Population value: SR "&TEXT('COGS Testing'!E34,"#,##0.00")&" | Random number high to low" -> Sample: 14 of 127 eligible items | Risk level: Low to Moderate (2) / Medium entity | Population value: SR 111,047.12 | Random number high to low
A3: Back to summary: COGS Testing
A4: Sample No. | B4: Date | C4: Ledger Code | D4: Ledger / Account | E4: Description | F4: Original Amount | G4: Absolute Amount | H4: Random Number | I4: Materiality | J4: Selection Basis | K4: Ledger row | L4: Voucher Ref | M4: Test result | N4: Comments
A5: =IF(ROWS($A$5:A5)<='COGS Testing'!$E$36,ROWS($A$5:A5),"") -> 1 | B5: =IF($A5="","",INDEX('COGS Ledger'!$B$1:$B$400,$K5)) -> 45991 | C5: =IF($A5="","",INDEX('COGS Ledger'!$C$1:$C$400,$K5)) -> 10054 | D5: =IF($A5="","",INDEX('COGS Ledger'!$D$1:$D$400,$K5)) -> PHOTO CHARGES- EXP | E5: =IF($A5="","",INDEX('COGS Ledger'!$F$1:$F$400,$K5)&"") -> PJ Ref:AMSLAP0050/25 ; DPW- SW-001087173- WAN HAI 501 / 261E- SAVI SHIPPING PHOTO CHARGES GATE FEES DICSH IMPORT LADEN- 1X40- SAR 481 LOAD EXPORT EMPTY- 1X40- SAR 510 | F5: =IF($A5="","",INDEX('COGS Ledger'!$I$1:$I$400,$K5)) -> 21 | G5: =IF($A5="","",INDEX('COGS Ledger'!$J$1:$J$400,$K5)) -> 21 | H5: =IF($A5="","",INDEX('COGS Ledger'!$M$1:$M$400,$K5)) -> 0.99930386 | I5: =IF($A5="","",'COGS Testing'!$E$9) -> 4000 | J5: =IF($A5="","","Below materiality – randomly selected") -> Below materiality – randomly selected | K5: =IF($A5="","",MATCH(LARGE('COGS Ledger'!$Q$2:$Q$400,$A5),'COGS Ledger'!$Q$2:$Q$400,0)+1) -> 138 | L5: =IF($A5="","",INDEX('COGS Ledger'!$A$1:$A$400,$K5)&"") -> PJAMS0165/25
A6: =IF(ROWS($A$5:A6)<='COGS Testing'!$E$36,ROWS($A$5:A6),"") -> 2 | B6: =IF($A6="","",INDEX('COGS Ledger'!$B$1:$B$400,$K6)) -> 45984 | C6: =IF($A6="","",INDEX('COGS Ledger'!$C$1:$C$400,$K6)) -> 10049 | D6: =IF($A6="","",INDEX('COGS Ledger'!$D$1:$D$400,$K6)) -> CONTAINER GATE PASS FEE- EXP | E6: =IF($A6="","",INDEX('COGS Ledger'!$F$1:$F$400,$K6)&"") -> RSGT- 2388686- GFS PERFECT - GFPT0071E GATE CHARGES EMPTY & LADEN- SAR 256 LOAD EXPORT LADEN- SAR 510 LOAD EXPORT EXPTY- SAR 449 PHOTO CHARGES | F6: =IF($A6="","",INDEX('COGS Ledger'!$I$1:$I$400,$K6)) -> 256 | G6: =IF($A6="","",INDEX('COGS Ledger'!$J$1:$J$400,$K6)) -> 256 | H6: =IF($A6="","",INDEX('COGS Ledger'!$M$1:$M$400,$K6)) -> 0.98031055 | I6: =IF($A6="","",'COGS Testing'!$E$9) -> 4000 | J6: =IF($A6="","","Below materiality – randomly selected") -> Below materiality – randomly selected | K6: =IF($A6="","",MATCH(LARGE('COGS Ledger'!$Q$2:$Q$400,$A6),'COGS Ledger'!$Q$2:$Q$400,0)+1) -> 18 | L6: =IF($A6="","",INDEX('COGS Ledger'!$A$1:$A$400,$K6)&"") -> PJAMS0152/25
A7: =IF(ROWS($A$5:A7)<='COGS Testing'!$E$36,ROWS($A$5:A7),"") -> 3 | B7: =IF($A7="","",INDEX('COGS Ledger'!$B$1:$B$400,$K7)) -> 45967 | C7: =IF($A7="","",INDEX('COGS Ledger'!$C$1:$C$400,$K7)) -> 10061 | D7: =IF($A7="","",INDEX('COGS Ledger'!$D$1:$D$400,$K7)) -> RENOMINATION CHARGES | E7: =IF($A7="","",INDEX('COGS Ledger'!$F$1:$F$400,$K7)&"") -> BOL : ;Job No : AMSLBK00002/25; For / Sailed :06-Nov-2025 | F7: =IF($A7="","",INDEX('COGS Ledger'!$I$1:$I$400,$K7)) -> -35 | G7: =IF($A7="","",INDEX('COGS Ledger'!$J$1:$J$400,$K7)) -> 35 | H7: =IF($A7="","",INDEX('COGS Ledger'!$M$1:$M$400,$K7)) -> 0.97830992 | I7: =IF($A7="","",'COGS Testing'!$E$9) -> 4000 | J7: =IF($A7="","","Below materiality – randomly selected") -> Below materiality – randomly selected | K7: =IF($A7="","",MATCH(LARGE('COGS Ledger'!$Q$2:$Q$400,$A7),'COGS Ledger'!$Q$2:$Q$400,0)+1) -> 147 | L7: =IF($A7="","",INDEX('COGS Ledger'!$A$1:$A$400,$K7)&"") -> SJAMS0008/25
A8: =IF(ROWS($A$5:A8)<='COGS Testing'!$E$36,ROWS($A$5:A8),"") -> 4 | B8: =IF($A8="","",INDEX('COGS Ledger'!$B$1:$B$400,$K8)) -> 45964 | C8: =IF($A8="","",INDEX('COGS Ledger'!$C$1:$C$400,$K8)) -> 10049 | D8: =IF($A8="","",INDEX('COGS Ledger'!$D$1:$D$400,$K8)) -> CONTAINER GATE PASS FEE- EXP | E8: =IF($A8="","",INDEX('COGS Ledger'!$F$1:$F$400,$K8)&"") -> RSGT- 2372841- SSF GALENE - GENE0001E- CAPE CONTAINERS GATE CHARGES- 2X20'- SAR 128 LOAD THC LADEN- 2X20'- SAR 299 PHOTO CHARGES- 2X20'- SAR 21 | F8: =IF($A8="","",INDEX('COGS Ledger'!$I$1:$I$400,$K8)) -> 256 | G8: =IF($A8="","",INDEX('COGS Ledger'!$J$1:$J$400,$K8)) -> 256 | H8: =IF($A8="","",INDEX('COGS Ledger'!$M$1:$M$400,$K8)) -> 0.97085663 | I8: =IF($A8="","",'COGS Testing'!$E$9) -> 4000 | J8: =IF($A8="","","Below materiality – randomly selected") -> Below materiality – randomly selected | K8: =IF($A8="","",MATCH(LARGE('COGS Ledger'!$Q$2:$Q$400,$A8),'COGS Ledger'!$Q$2:$Q$400,0)+1) -> 16 | L8: =IF($A8="","",INDEX('COGS Ledger'!$A$1:$A$400,$K8)&"") -> PJAMS0151/25
A9: =IF(ROWS($A$5:A9)<='COGS Testing'!$E$36,ROWS($A$5:A9),"") -> 5 | B9: =IF($A9="","",INDEX('COGS Ledger'!$B$1:$B$400,$K9)) -> 45935 | C9: =IF($A9="","",INDEX('COGS Ledger'!$C$1:$C$400,$K9)) -> 10048 | D9: =IF($A9="","",INDEX('COGS Ledger'!$D$1:$D$400,$K9)) -> CONTAINER DAMAGE CHARGES- COST | E9: =IF($A9="","",INDEX('COGS Ledger'!$F$1:$F$400,$K9)&"") -> PJ Ref:AMSLAP0026/25 ; CNTR DMG CHARGES- EMCU3778261 | F9: =IF($A9="","",INDEX('COGS Ledger'!$I$1:$I$400,$K9)) -> 150 | G9: =IF($A9="","",INDEX('COGS Ledger'!$J$1:$J$400,$K9)) -> 150 | H9: =IF($A9="","",INDEX('COGS Ledger'!$M$1:$M$400,$K9)) -> 0.96811716 | I9: =IF($A9="","",'COGS Testing'!$E$9) -> 4000 | J9: =IF($A9="","","Below materiality – randomly selected") -> Below materiality – randomly selected | K9: =IF($A9="","",MATCH(LARGE('COGS Ledger'!$Q$2:$Q$400,$A9),'COGS Ledger'!$Q$2:$Q$400,0)+1) -> 9 | L9: =IF($A9="","",INDEX('COGS Ledger'!$A$1:$A$400,$K9)&"") -> PJAMS0054/25
A10: =IF(ROWS($A$5:A10)<='COGS Testing'!$E$36,ROWS($A$5:A10),"") -> 6 | B10: =IF($A10="","",INDEX('COGS Ledger'!$B$1:$B$400,$K10)) -> 46020 | C10: =IF($A10="","",INDEX('COGS Ledger'!$C$1:$C$400,$K10)) -> 10061 | D10: =IF($A10="","",INDEX('COGS Ledger'!$D$1:$D$400,$K10)) -> RENOMINATION CHARGES | E10: =IF($A10="","",INDEX('COGS Ledger'!$F$1:$F$400,$K10)&"") -> RSGT- 2418232- SUNNY 77 - SN77SN-015S- SAVI SHIPPING LOAD T/S LADEN NON CELLULAR- 10X20'- SAR 200 RENOMINATION- SAR 37 | F10: =IF($A10="","",INDEX('COGS Ledger'!$I$1:$I$400,$K10)) -> 370 | G10: =IF($A10="","",INDEX('COGS Ledger'!$J$1:$J$400,$K10)) -> 370 | H10: =IF($A10="","",INDEX('COGS Ledger'!$M$1:$M$400,$K10)) -> 0.96672238 | I10: =IF($A10="","",'COGS Testing'!$E$9) -> 4000 | J10: =IF($A10="","","Below materiality – randomly selected") -> Below materiality – randomly selected | K10: =IF($A10="","",MATCH(LARGE('COGS Ledger'!$Q$2:$Q$400,$A10),'COGS Ledger'!$Q$2:$Q$400,0)+1) -> 149 | L10: =IF($A10="","",INDEX('COGS Ledger'!$A$1:$A$400,$K10)&"") -> PJAMS0156/25
A11: =IF(ROWS($A$5:A11)<='COGS Testing'!$E$36,ROWS($A$5:A11),"") -> 7 | B11: =IF($A11="","",INDEX('COGS Ledger'!$B$1:$B$400,$K11)) -> 46022 | C11: =IF($A11="","",INDEX('COGS Ledger'!$C$1:$C$400,$K11)) -> 10088 | D11: =IF($A11="","",INDEX('COGS Ledger'!$D$1:$D$400,$K11)) -> W/O EXPENSES | E11: =IF($A11="","",INDEX('COGS Ledger'!$F$1:$F$400,$K11)&"") | F11: =IF($A11="","",INDEX('COGS Ledger'!$I$1:$I$400,$K11)) -> 1230.84 | G11: =IF($A11="","",INDEX('COGS Ledger'!$J$1:$J$400,$K11)) -> 1230.84 | H11: =IF($A11="","",INDEX('COGS Ledger'!$M$1:$M$400,$K11)) -> 0.96664363 | I11: =IF($A11="","",'COGS Testing'!$E$9) -> 4000 | J11: =IF($A11="","","Below materiality – randomly selected") -> Below materiality – randomly selected | K11: =IF($A11="","",MATCH(LARGE('COGS Ledger'!$Q$2:$Q$400,$A11),'COGS Ledger'!$Q$2:$Q$400,0)+1) -> 163 | L11: =IF($A11="","",INDEX('COGS Ledger'!$A$1:$A$400,$K11)&"") -> GJAMS0075/25
A12: =IF(ROWS($A$5:A12)<='COGS Testing'!$E$36,ROWS($A$5:A12),"") -> 8 | B12: =IF($A12="","",INDEX('COGS Ledger'!$B$1:$B$400,$K12)) -> 45908 | C12: =IF($A12="","",INDEX('COGS Ledger'!$C$1:$C$400,$K12)) -> 10060 | D12: =IF($A12="","",INDEX('COGS Ledger'!$D$1:$D$400,$K12)) -> REEFER MONITORING/MAINTENANCE | E12: =IF($A12="","",INDEX('COGS Ledger'!$F$1:$F$400,$K12)&"") -> NVOIMP Against the IMP BOL - CCJEAJED25089039; Customer Ref: ;Remarks: | F12: =IF($A12="","",INDEX('COGS Ledger'!$I$1:$I$400,$K12)) -> -134 | G12: =IF($A12="","",INDEX('COGS Ledger'!$J$1:$J$400,$K12)) -> 134 | H12: =IF($A12="","",INDEX('COGS Ledger'!$M$1:$M$400,$K12)) -> 0.95621552 | I12: =IF($A12="","",'COGS Testing'!$E$9) -> 4000 | J12: =IF($A12="","","Below materiality – randomly selected") -> Below materiality – randomly selected | K12: =IF($A12="","",MATCH(LARGE('COGS Ledger'!$Q$2:$Q$400,$A12),'COGS Ledger'!$Q$2:$Q$400,0)+1) -> 145 | L12: =IF($A12="","",INDEX('COGS Ledger'!$A$1:$A$400,$K12)&"") -> SJAMS0482/25
A13: =IF(ROWS($A$5:A13)<='COGS Testing'!$E$36,ROWS($A$5:A13),"") -> 9 | B13: =IF($A13="","",INDEX('COGS Ledger'!$B$1:$B$400,$K13)) -> 46022 | C13: =IF($A13="","",INDEX('COGS Ledger'!$C$1:$C$400,$K13)) -> 10051 | D13: =IF($A13="","",INDEX('COGS Ledger'!$D$1:$D$400,$K13)) -> LOLO CHARGES - EXP | E13: =IF($A13="","",INDEX('COGS Ledger'!$F$1:$F$400,$K13)&"") -> CREDIT NOTE- FOR CHARGES GATE PASS, LOLO & PHOTO CHARGES- PELLATSOKJED0091125- 1X20DV 1X40HC PELLATSOKJED0061125- 12X40HC PELLATSOKJED0081125- 1X40HC APPROVED BY MR VISHNU- REF EMAIL- SAVI SHIPPING | F13: =IF($A13="","",INDEX('COGS Ledger'!$I$1:$I$400,$K13)) -> 1948 | G13: =IF($A13="","",INDEX('COGS Ledger'!$J$1:$J$400,$K13)) -> 1948 | H13: =IF($A13="","",INDEX('COGS Ledger'!$M$1:$M$400,$K13)) -> 0.95286901 | I13: =IF($A13="","",'COGS Testing'!$E$9) -> 4000 | J13: =IF($A13="","","Below materiality – randomly selected") -> Below materiality – randomly selected | K13: =IF($A13="","",MATCH(LARGE('COGS Ledger'!$Q$2:$Q$400,$A13),'COGS Ledger'!$Q$2:$Q$400,0)+1) -> 66 | L13: =IF($A13="","",INDEX('COGS Ledger'!$A$1:$A$400,$K13)&"") -> CNAMS0005/25
A14: =IF(ROWS($A$5:A14)<='COGS Testing'!$E$36,ROWS($A$5:A14),"") -> 10 | B14: =IF($A14="","",INDEX('COGS Ledger'!$B$1:$B$400,$K14)) -> 45947 | C14: =IF($A14="","",INDEX('COGS Ledger'!$C$1:$C$400,$K14)) -> 10053 | D14: =IF($A14="","",INDEX('COGS Ledger'!$D$1:$D$400,$K14)) -> OPERATION RECOVERY COST | E14: =IF($A14="","",INDEX('COGS Ledger'!$F$1:$F$400,$K14)&"") -> RSGT- 2358686- CUL BANGKOK - BANKCUBK2538W- DISCH IMPORT LADEN- 6X20'- SAR 300 DISCH IMPORT LADEN- 14X40'- SAR 450 DISCH T/S LADEN- 1X20'- SAR 140 DISCH T/S LADEN- 18X40'- SAR 210 | F14: =IF($A14="","",INDEX('COGS Ledger'!$I$1:$I$400,$K14)) -> 1800 | G14: =IF($A14="","",INDEX('COGS Ledger'!$J$1:$J$400,$K14)) -> 1800 | H14: =IF($A14="","",INDEX('COGS Ledger'!$M$1:$M$400,$K14)) -> 0.95027333 | I14: =IF($A14="","",'COGS Testing'!$E$9) -> 4000 | J14: =IF($A14="","","Below materiality – randomly selected") -> Below materiality – randomly selected | K14: =IF($A14="","",MATCH(LARGE('COGS Ledger'!$Q$2:$Q$400,$A14),'COGS Ledger'!$Q$2:$Q$400,0)+1) -> 98 | L14: =IF($A14="","",INDEX('COGS Ledger'!$A$1:$A$400,$K14)&"") -> PJAMS0076/25
A15: =IF(ROWS($A$5:A15)<='COGS Testing'!$E$36,ROWS($A$5:A15),"") -> 11 | B15: =IF($A15="","",INDEX('COGS Ledger'!$B$1:$B$400,$K15)) -> 46007 | C15: =IF($A15="","",INDEX('COGS Ledger'!$C$1:$C$400,$K15)) -> 10061 | D15: =IF($A15="","",INDEX('COGS Ledger'!$D$1:$D$400,$K15)) -> RENOMINATION CHARGES | E15: =IF($A15="","",INDEX('COGS Ledger'!$F$1:$F$400,$K15)&"") -> BOL : CCJEDJEA25129578;Job No : AMSLBK00005/25;BL FEE OF 100 SAR ADDED TO THIS INVOICE AS AGREED BL FEE WAS 250 AND IN FIRST INVOICE - AMSLE00005/25 WAS GENERATED WITH 150 SAR ONLY, ADDING 100 SAR HERE. BL - CCJEDJEA25129578 For / Sailed :19-Dec-2025 | F15: =IF($A15="","",INDEX('COGS Ledger'!$I$1:$I$400,$K15)) -> -37 | G15: =IF($A15="","",INDEX('COGS Ledger'!$J$1:$J$400,$K15)) -> 37 | H15: =IF($A15="","",INDEX('COGS Ledger'!$M$1:$M$400,$K15)) -> 0.93785785 | I15: =IF($A15="","",'COGS Testing'!$E$9) -> 4000 | J15: =IF($A15="","","Below materiality – randomly selected") -> Below materiality – randomly selected | K15: =IF($A15="","",MATCH(LARGE('COGS Ledger'!$Q$2:$Q$400,$A15),'COGS Ledger'!$Q$2:$Q$400,0)+1) -> 148 | L15: =IF($A15="","",INDEX('COGS Ledger'!$A$1:$A$400,$K15)&"") -> SJAMS0411/25
A16: =IF(ROWS($A$5:A16)<='COGS Testing'!$E$36,ROWS($A$5:A16),"") -> 12 | B16: =IF($A16="","",INDEX('COGS Ledger'!$B$1:$B$400,$K16)) -> 46022 | C16: =IF($A16="","",INDEX('COGS Ledger'!$C$1:$C$400,$K16)) -> 10066 | D16: =IF($A16="","",INDEX('COGS Ledger'!$D$1:$D$400,$K16)) -> FASAH APPOINTMENT FEES | E16: =IF($A16="","",INDEX('COGS Ledger'!$F$1:$F$400,$K16)&"") -> JSI-3986- LOCAL TRANSPORTATION AND FASAH APPOINTMENT FEES- FREIGHT WORLD- CONTAINER TRIU0777668 | F16: =IF($A16="","",INDEX('COGS Ledger'!$I$1:$I$400,$K16)) -> -34.5 | G16: =IF($A16="","",INDEX('COGS Ledger'!$J$1:$J$400,$K16)) -> 34.5 | H16: =IF($A16="","",INDEX('COGS Ledger'!$M$1:$M$400,$K16)) -> 0.9333356 | I16: =IF($A16="","",'COGS Testing'!$E$9) -> 4000 | J16: =IF($A16="","","Below materiality – randomly selected") -> Below materiality – randomly selected | K16: =IF($A16="","",MATCH(LARGE('COGS Ledger'!$Q$2:$Q$400,$A16),'COGS Ledger'!$Q$2:$Q$400,0)+1) -> 34 | L16: =IF($A16="","",INDEX('COGS Ledger'!$A$1:$A$400,$K16)&"") -> SJAMS0677/25
... A104: =IF(ROWS($A$5:A104)<='COGS Testing'!$E$36,ROWS($A$5:A104),"") | B104: =IF($A104="","",INDEX('COGS Ledger'!$B$1:$B$400,$K104)) | C104: =IF($A104="","",INDEX('COGS Ledger'!$C$1:$C$400,$K104)) | D104: =IF($A104="","",INDEX('COGS Ledger'!$D$1:$D$400,$K104)) | E104: =IF($A104="","",INDEX('COGS Ledger'!$F$1:$F$400,$K104)&"") | F104: =IF($A104="","",INDEX('COGS Ledger'!$I$1:$I$400,$K104)) | G104: =IF($A104="","",INDEX('COGS Ledger'!$J$1:$J$400,$K104)) | H104: =IF($A104="","",INDEX('COGS Ledger'!$M$1:$M$400,$K104)) | I104: =IF($A104="","",'COGS Testing'!$E$9) | J104: =IF($A104="","","Below materiality – randomly selected") | K104: =IF($A104="","",MATCH(LARGE('COGS Ledger'!$Q$2:$Q$400,$A104),'COGS Ledger'!$Q$2:$Q$400,0)+1) | L104: =IF($A104="","",INDEX('COGS Ledger'!$A$1:$A$400,$K104)&"")
E105: Total | F105: =SUM(F5:F104) -> 9261.34 | G105: =SUM(G5:G104) -> 9742.34

Sheet Expense Ledger
A1: Voucher Ref | B1: Date | C1: Ledger Code | D1: Ledger Name | E1: ArAp Ref | F1: Description (Remarks) | G1: Debit | H1: Credit | I1: Original Amount (Dr − Cr) | J1: Absolute Amount | K1: Excluded – account set to Exclude (1 = yes) | L1: Above materiality – selected (1 = yes) | M1: Random No. (fixed) | N1: Possible duplicate | O1: Below-materiality eligible pop. (1 = yes) | P1: Rank key – above | Q1: Rank key – random | R1: Excluded-record key | S1: Account key (trimmed)
